[
  {
    "Constant" : [

    ],
    "submodules" : [
      "bar",
      "item",
      "virtual"
    ],
    "Function" : [
      {
        "doc" : "Returns a boolean value indicathing whether or not the Apple Touch Bar is supported on this Macintosh.\n\nParameters:\n * `showLink` - a boolean, default false, specifying whether a dialog prompting the user to download the necessary update is presented if Apple Touch Bar support is not found in the current Operating System.\n\nReturns:\n * true if Apple Touch Bar support is found in the current Operating System or false if it is not.\n\nNotes:\n * the link in the prompt is https:\/\/support.apple.com\/kb\/dl1897",
        "stripped_doc" : [
          "Returns a boolean value indicathing whether or not the Apple Touch Bar is supported on this Macintosh.",
          ""
        ],
        "parameters" : [
          " * `showLink` - a boolean, default false, specifying whether a dialog prompting the user to download the necessary update is presented if Apple Touch Bar support is not found in the current Operating System.",
          ""
        ],
        "name" : "supported",
        "notes" : [
          " * the link in the prompt is https:\/\/support.apple.com\/kb\/dl1897"
        ],
        "signature" : "hs._asm.undocumented.touchbar.supported([showLink]) -> boolean",
        "type" : "Function",
        "returns" : [
          " * true if Apple Touch Bar support is found in the current Operating System or false if it is not.",
          ""
        ],
        "def" : "hs._asm.undocumented.touchbar.supported([showLink]) -> boolean",
        "desc" : "Returns a boolean value indicathing whether or not the Apple Touch Bar is supported on this Macintosh."
      },
      {
        "doc" : "Returns whether or not the touchbar exists on this machine, real *or* virtual.\n\nParameters:\n * None\n\nReturns:\n * a boolean value indicating whether or a not the touchbar exists (true) or does not exist (false) on this machine.\n\nNotes:\n * Checking the value of this function does not indicate whether or not the machine *can* support the Touch Bar but rather if it is *currently* supporting the Touch Bar; Use [hs._asm.undocumented.touchbar.supported](#supported) to check whether or not the machine *can* support the Touch Bar.\n\n * On machines with a physical touchbar (see also [hs._asm.undocumented.touchbar.physical](#physical)), this function will always return true.\n * On machines without a physical touchbar, this function will return true if a virtual touchbar has been created with the `hs._asm.undocumented.touchbar.virtual` submodule or through another third-party application.",
        "stripped_doc" : [
          "Returns whether or not the touchbar exists on this machine, real *or* virtual.",
          ""
        ],
        "parameters" : [
          " * None",
          ""
        ],
        "name" : "exists",
        "notes" : [
          " * Checking the value of this function does not indicate whether or not the machine *can* support the Touch Bar but rather if it is *currently* supporting the Touch Bar; Use [hs._asm.undocumented.touchbar.supported](#supported) to check whether or not the machine *can* support the Touch Bar.",
          "",
          " * On machines with a physical touchbar (see also [hs._asm.undocumented.touchbar.physical](#physical)), this function will always return true.",
          " * On machines without a physical touchbar, this function will return true if a virtual touchbar has been created with the `hs._asm.undocumented.touchbar.virtual` submodule or through another third-party application."
        ],
        "signature" : "hs._asm.undocumented.touchbar.exists() -> boolean",
        "type" : "Function",
        "returns" : [
          " * a boolean value indicating whether or a not the touchbar exists (true) or does not exist (false) on this machine.",
          ""
        ],
        "def" : "hs._asm.undocumented.touchbar.exists() -> boolean",
        "desc" : "Returns whether or not the touchbar exists on this machine, real *or* virtual."
      },
      {
        "doc" : "Returns whether or not the machine has a physical touchbar\n\nParameters:\n * None\n\nReturns:\n * a boolean value indicating whether or not the machine has a physical touchbar (true) or does not (false)\n\nNotes:\n * To determine if the machine is currently maintaining a touchbar, physical *or* virtual, use [hs._asm.undocumented.touchbar.exists](#exists).",
        "stripped_doc" : [
          "Returns whether or not the machine has a physical touchbar",
          ""
        ],
        "parameters" : [
          " * None",
          ""
        ],
        "name" : "physical",
        "notes" : [
          " * To determine if the machine is currently maintaining a touchbar, physical *or* virtual, use [hs._asm.undocumented.touchbar.exists](#exists)."
        ],
        "signature" : "hs._asm.undocumented.touchbar.physical() -> boolean",
        "type" : "Function",
        "returns" : [
          " * a boolean value indicating whether or not the machine has a physical touchbar (true) or does not (false)",
          ""
        ],
        "def" : "hs._asm.undocumented.touchbar.physical() -> boolean",
        "desc" : "Returns whether or not the machine has a physical touchbar"
      },
      {
        "doc" : "Returns the size of the touchbar as a size table\n\nParameters:\n * None\n\nReturns:\n * a table containing key-value fields for the height (h) and width (w) of the touchbar\n\nNotes:\n * On a machine without a physical touchbar, noth height and width will be 0 if no virtual touchbar is currently active.\n   * You can use this as a way to test if a third party application has created a virtual touchbar as long as you check **before** `hs._asm.undocumented.touchbar.virtual.new` has been used; once the virtual submodule's `new` function has been invoked, the height and width will match the virtual touchbar that Hammerspoon has created.",
        "stripped_doc" : [
          "Returns the size of the touchbar as a size table",
          ""
        ],
        "parameters" : [
          " * None",
          ""
        ],
        "name" : "size",
        "notes" : [
          " * On a machine without a physical touchbar, noth height and width will be 0 if no virtual touchbar is currently active.",
          "   * You can use this as a way to test if a third party application has created a virtual touchbar as long as you check **before** `hs._asm.undocumented.touchbar.virtual.new` has been used; once the virtual submodule's `new` function has been invoked, the height and width will match the virtual touchbar that Hammerspoon has created."
        ],
        "signature" : "hs._asm.undocumented.touchbar.size() -> sizeTable",
        "type" : "Function",
        "returns" : [
          " * a table containing key-value fields for the height (h) and width (w) of the touchbar",
          ""
        ],
        "def" : "hs._asm.undocumented.touchbar.size() -> sizeTable",
        "desc" : "Returns the size of the touchbar as a size table"
      }
    ],
    "Variable" : [

    ],
    "stripped_doc" : [

    ],
    "type" : "Module",
    "desc" : "This module and its submodules provide support for manipulating the Apple Touch Bar on newer Macbook Pro laptops. For machines that do not have a touchbar, the `hs._asm.undocumented.touchbar.virtual` submodule provides a method for mimicing one on screen.",
    "Deprecated" : [

    ],
    "Constructor" : [

    ],
    "doc" : "This module and its submodules provide support for manipulating the Apple Touch Bar on newer Macbook Pro laptops. For machines that do not have a touchbar, the `hs._asm.undocumented.touchbar.virtual` submodule provides a method for mimicing one on screen.\n\nUse of this module and its submodules in conunction with other third party applications that can create the virtual touchbar has not been tested specifically, but *should* work. I have not run into any problems or issues while using [Duet Display](https:\/\/www.duetdisplay.com), but haven't performed extensive testing.\n\nThis module and it's submodules require a mac that is running macOS 10.12.1 build 16B2657 or newer. If you wish to use this module in an environment where the end-user's machine may not have a new enough macOS release version, you should always check the value of [hs._asm.undocumented.touchbar.supported](#supported) before trying to create the Touch Bar and provide your own fallback or message. By supplying the argument `true` to this function, the user will be prompted to upgrade if necessary.\n\nThis module relies heavily on undocumented APIs in the macOS and may break with future OS updates. With minor updates and bug fixes, this module has continued to work through 10.15.2, and we hope to continue to maintain this, but no guarantees are given.\n\nBug fixes and feature updates are always welcome and can be submitted at https:\/\/github.com\/asmagill\/hs._asm.undocumented.touchbar.\n\nThis module is very experimental and is still under development, so the exact functions and methods may be subject to change without notice.\n\nSpecial thanks to @cmsj and @latenitefilms for code samples and bugfixes, and to @randomeizer, @Madd0g, and @medranocalvo for tests and reports. This is by no means a conclusive list, and if I've left anyone out, it's totally on me -- feel free to poke me with a (virtual) stick ðŸ˜œ.",
    "Method" : [

    ],
    "Command" : [

    ],
    "items" : [
      {
        "doc" : "Returns whether or not the touchbar exists on this machine, real *or* virtual.\n\nParameters:\n * None\n\nReturns:\n * a boolean value indicating whether or a not the touchbar exists (true) or does not exist (false) on this machine.\n\nNotes:\n * Checking the value of this function does not indicate whether or not the machine *can* support the Touch Bar but rather if it is *currently* supporting the Touch Bar; Use [hs._asm.undocumented.touchbar.supported](#supported) to check whether or not the machine *can* support the Touch Bar.\n\n * On machines with a physical touchbar (see also [hs._asm.undocumented.touchbar.physical](#physical)), this function will always return true.\n * On machines without a physical touchbar, this function will return true if a virtual touchbar has been created with the `hs._asm.undocumented.touchbar.virtual` submodule or through another third-party application.",
        "stripped_doc" : [
          "Returns whether or not the touchbar exists on this machine, real *or* virtual.",
          ""
        ],
        "parameters" : [
          " * None",
          ""
        ],
        "name" : "exists",
        "notes" : [
          " * Checking the value of this function does not indicate whether or not the machine *can* support the Touch Bar but rather if it is *currently* supporting the Touch Bar; Use [hs._asm.undocumented.touchbar.supported](#supported) to check whether or not the machine *can* support the Touch Bar.",
          "",
          " * On machines with a physical touchbar (see also [hs._asm.undocumented.touchbar.physical](#physical)), this function will always return true.",
          " * On machines without a physical touchbar, this function will return true if a virtual touchbar has been created with the `hs._asm.undocumented.touchbar.virtual` submodule or through another third-party application."
        ],
        "signature" : "hs._asm.undocumented.touchbar.exists() -> boolean",
        "type" : "Function",
        "returns" : [
          " * a boolean value indicating whether or a not the touchbar exists (true) or does not exist (false) on this machine.",
          ""
        ],
        "def" : "hs._asm.undocumented.touchbar.exists() -> boolean",
        "desc" : "Returns whether or not the touchbar exists on this machine, real *or* virtual."
      },
      {
        "doc" : "Returns whether or not the machine has a physical touchbar\n\nParameters:\n * None\n\nReturns:\n * a boolean value indicating whether or not the machine has a physical touchbar (true) or does not (false)\n\nNotes:\n * To determine if the machine is currently maintaining a touchbar, physical *or* virtual, use [hs._asm.undocumented.touchbar.exists](#exists).",
        "stripped_doc" : [
          "Returns whether or not the machine has a physical touchbar",
          ""
        ],
        "parameters" : [
          " * None",
          ""
        ],
        "name" : "physical",
        "notes" : [
          " * To determine if the machine is currently maintaining a touchbar, physical *or* virtual, use [hs._asm.undocumented.touchbar.exists](#exists)."
        ],
        "signature" : "hs._asm.undocumented.touchbar.physical() -> boolean",
        "type" : "Function",
        "returns" : [
          " * a boolean value indicating whether or not the machine has a physical touchbar (true) or does not (false)",
          ""
        ],
        "def" : "hs._asm.undocumented.touchbar.physical() -> boolean",
        "desc" : "Returns whether or not the machine has a physical touchbar"
      },
      {
        "doc" : "Returns the size of the touchbar as a size table\n\nParameters:\n * None\n\nReturns:\n * a table containing key-value fields for the height (h) and width (w) of the touchbar\n\nNotes:\n * On a machine without a physical touchbar, noth height and width will be 0 if no virtual touchbar is currently active.\n   * You can use this as a way to test if a third party application has created a virtual touchbar as long as you check **before** `hs._asm.undocumented.touchbar.virtual.new` has been used; once the virtual submodule's `new` function has been invoked, the height and width will match the virtual touchbar that Hammerspoon has created.",
        "stripped_doc" : [
          "Returns the size of the touchbar as a size table",
          ""
        ],
        "parameters" : [
          " * None",
          ""
        ],
        "name" : "size",
        "notes" : [
          " * On a machine without a physical touchbar, noth height and width will be 0 if no virtual touchbar is currently active.",
          "   * You can use this as a way to test if a third party application has created a virtual touchbar as long as you check **before** `hs._asm.undocumented.touchbar.virtual.new` has been used; once the virtual submodule's `new` function has been invoked, the height and width will match the virtual touchbar that Hammerspoon has created."
        ],
        "signature" : "hs._asm.undocumented.touchbar.size() -> sizeTable",
        "type" : "Function",
        "returns" : [
          " * a table containing key-value fields for the height (h) and width (w) of the touchbar",
          ""
        ],
        "def" : "hs._asm.undocumented.touchbar.size() -> sizeTable",
        "desc" : "Returns the size of the touchbar as a size table"
      },
      {
        "doc" : "Returns a boolean value indicathing whether or not the Apple Touch Bar is supported on this Macintosh.\n\nParameters:\n * `showLink` - a boolean, default false, specifying whether a dialog prompting the user to download the necessary update is presented if Apple Touch Bar support is not found in the current Operating System.\n\nReturns:\n * true if Apple Touch Bar support is found in the current Operating System or false if it is not.\n\nNotes:\n * the link in the prompt is https:\/\/support.apple.com\/kb\/dl1897",
        "stripped_doc" : [
          "Returns a boolean value indicathing whether or not the Apple Touch Bar is supported on this Macintosh.",
          ""
        ],
        "parameters" : [
          " * `showLink` - a boolean, default false, specifying whether a dialog prompting the user to download the necessary update is presented if Apple Touch Bar support is not found in the current Operating System.",
          ""
        ],
        "name" : "supported",
        "notes" : [
          " * the link in the prompt is https:\/\/support.apple.com\/kb\/dl1897"
        ],
        "signature" : "hs._asm.undocumented.touchbar.supported([showLink]) -> boolean",
        "type" : "Function",
        "returns" : [
          " * true if Apple Touch Bar support is found in the current Operating System or false if it is not.",
          ""
        ],
        "def" : "hs._asm.undocumented.touchbar.supported([showLink]) -> boolean",
        "desc" : "Returns a boolean value indicathing whether or not the Apple Touch Bar is supported on this Macintosh."
      }
    ],
    "Field" : [

    ],
    "name" : "hs._asm.undocumented.touchbar"
  },
  {
    "Constant" : [
      {
        "doc" : "A table of key-value pairs whose values represent built in touch bar items which can be used to adjust the layout of the bar object when it is being presented.\n\nCurrently the following keys are defined:\n * smallSpace      - provides a small space between items\n * largeSpace      - provides a larger space between items\n * flexibleSpace   - provides an expanding\/contracting space between items\n\nThe following is ignored for modally displayed bars, so it's effects are still being evaluated; documentation will be updated when nested bars can be tested and more fully understood within the context of the Hammerspoon console and webview.\n * otherItemsProxy - provides a place for nested bars to display items",
        "stripped_doc" : [
          "A table of key-value pairs whose values represent built in touch bar items which can be used to adjust the layout of the bar object when it is being presented.",
          "",
          "Currently the following keys are defined:",
          " * smallSpace      - provides a small space between items",
          " * largeSpace      - provides a larger space between items",
          " * flexibleSpace   - provides an expanding\/contracting space between items",
          "",
          "The following is ignored for modally displayed bars, so it's effects are still being evaluated; documentation will be updated when nested bars can be tested and more fully understood within the context of the Hammerspoon console and webview.",
          " * otherItemsProxy - provides a place for nested bars to display items"
        ],
        "parameters" : [

        ],
        "name" : "builtInIdentifiers",
        "notes" : [

        ],
        "signature" : "hs._asm.undocumented.touchbar.bar.builtInIdentifiers[]",
        "type" : "Constant",
        "returns" : [

        ],
        "def" : "hs._asm.undocumented.touchbar.bar.builtInIdentifiers[]",
        "desc" : "A table of key-value pairs whose values represent built in touch bar items which can be used to adjust the layout of the bar object when it is being presented."
      }
    ],
    "submodules" : [

    ],
    "Function" : [
      {
        "doc" : "(See Notes) Toggle's the Touch Bar customization panel for the Hammerspoon application\n\nParameters:\n * None\n\nReturns:\n * None\n\nNotes:\n * At present this function is not useful; it is expected to be more useful when Hammerspoon specific views can provide their own touchbars.\n\n * The customization panel allows modification of the current bar visible for the macOS application triggering the request within that applications resolver chain -- as such, it can only modify touchbar's attached to the Hammerspoon console or webview objects.\n * The customization panel cannot modify modally displayed bar objects.",
        "stripped_doc" : [
          "(See Notes) Toggle's the Touch Bar customization panel for the Hammerspoon application",
          ""
        ],
        "parameters" : [
          " * None",
          ""
        ],
        "name" : "toggleCustomization",
        "notes" : [
          " * At present this function is not useful; it is expected to be more useful when Hammerspoon specific views can provide their own touchbars.",
          "",
          " * The customization panel allows modification of the current bar visible for the macOS application triggering the request within that applications resolver chain -- as such, it can only modify touchbar's attached to the Hammerspoon console or webview objects.",
          " * The customization panel cannot modify modally displayed bar objects."
        ],
        "signature" : "hs._asm.undocumented.touchbar.bar.toggleCustomization() -> None",
        "type" : "Function",
        "returns" : [
          " * None",
          ""
        ],
        "def" : "hs._asm.undocumented.touchbar.bar.toggleCustomization() -> None",
        "desc" : "(See Notes) Toggle's the Touch Bar customization panel for the Hammerspoon application"
      }
    ],
    "Variable" : [

    ],
    "stripped_doc" : [

    ],
    "type" : "Module",
    "desc" : "This module is used to create and manipulate bar objects which can be displayed in the Touch Bar of new Macintosh Pro laptops or with the virtual Touch Bar provided by `hs._asm.undocumented.touchbar.virtual`.",
    "Deprecated" : [

    ],
    "Constructor" : [
      {
        "doc" : "Creates a new bar object\n\nParameters:\n * None\n\nReturns:\n * a new bar object",
        "stripped_doc" : [
          "Creates a new bar object",
          ""
        ],
        "parameters" : [
          " * None",
          ""
        ],
        "name" : "new",
        "notes" : [

        ],
        "signature" : "hs._asm.undocumented.touchbar.bar.new() -> barObject",
        "type" : "Constructor",
        "returns" : [
          " * a new bar object"
        ],
        "def" : "hs._asm.undocumented.touchbar.bar.new() -> barObject",
        "desc" : "Creates a new bar object"
      }
    ],
    "doc" : "This module is used to create and manipulate bar objects which can be displayed in the Touch Bar of new Macintosh Pro laptops or with the virtual Touch Bar provided by `hs._asm.undocumented.touchbar.virtual`.\n\nAt present, bar objects can be presented modally under Hammerspoon control but cannot be attached directly to the Hammerspoon console or webview objects to dynamically appear as application focus changes; this may change in the future.\n\nThis module is very experimental and is still under development, so the exact functions and methods may be subject to change without notice.\n\nThis module is based partially on some of the code examples and links referred to in the discussion at https:\/\/github.com\/Hammerspoon\/hammerspoon\/issues\/1096.",
    "Method" : [
      {
        "doc" : "Returns a boolean indicating whether the bar object is currently visible in the laptop or virtual Touch Bar.\n\nParameters:\n * None\n\nReturns:\n * a boolean value indicating whether or not the touchbar represented by the object is currently being displayed in the laptop or virtual Touch Bar.\n\nNotes:\n * The value returned by this method changes as expected when the [hs._asm.undocumented.touchbar.bar:dismissModalBar](#dismissModalBar) or [hs._asm.undocumented.touchbar.bar:minimizeModalBar](#minimizeModalBar) methods are used.\n * It does *NOT* reliably change when when the system dismiss button is used (when the second argument to [hs._asm.undocumented.touchbar.bar:presentModalBar](#presentModalBar) or `hs._asm.undocumented.touchbar.item:presentModalBar` is true (or not present)).  This is being investigated but at present no workaround is known.",
        "stripped_doc" : [
          "Returns a boolean indicating whether the bar object is currently visible in the laptop or virtual Touch Bar.",
          ""
        ],
        "parameters" : [
          " * None",
          ""
        ],
        "name" : "isVisible",
        "notes" : [
          " * The value returned by this method changes as expected when the [hs._asm.undocumented.touchbar.bar:dismissModalBar](#dismissModalBar) or [hs._asm.undocumented.touchbar.bar:minimizeModalBar](#minimizeModalBar) methods are used.",
          " * It does *NOT* reliably change when when the system dismiss button is used (when the second argument to [hs._asm.undocumented.touchbar.bar:presentModalBar](#presentModalBar) or `hs._asm.undocumented.touchbar.item:presentModalBar` is true (or not present)).  This is being investigated but at present no workaround is known."
        ],
        "signature" : "hs._asm.undocumented.touchbar.bar:isVisible() -> boolean",
        "type" : "Method",
        "returns" : [
          " * a boolean value indicating whether or not the touchbar represented by the object is currently being displayed in the laptop or virtual Touch Bar.",
          ""
        ],
        "def" : "hs._asm.undocumented.touchbar.bar:isVisible() -> boolean",
        "desc" : "Returns a boolean indicating whether the bar object is currently visible in the laptop or virtual Touch Bar."
      },
      {
        "doc" : "Returns an array of strings specifying the identifiers of the touchbar items currently presented by the bar object.\n\nParameters:\n * None\n\nReturns:\n * an array of strings specifying the identifiers of the touchbar items currently presented by the bar object.\n\nNotes:\n * If the user has not customized the bar, the list of identifiers will match the list provided by [hs._asm.undocumented.touchbar.bar:defaultIdentifiers()](#defaultIdentifiers).",
        "stripped_doc" : [
          "Returns an array of strings specifying the identifiers of the touchbar items currently presented by the bar object.",
          ""
        ],
        "parameters" : [
          " * None",
          ""
        ],
        "name" : "itemIdentifiers",
        "notes" : [
          " * If the user has not customized the bar, the list of identifiers will match the list provided by [hs._asm.undocumented.touchbar.bar:defaultIdentifiers()](#defaultIdentifiers)."
        ],
        "signature" : "hs._asm.undocumented.touchbar.bar:itemIdentifiers() -> table",
        "type" : "Method",
        "returns" : [
          " * an array of strings specifying the identifiers of the touchbar items currently presented by the bar object.",
          ""
        ],
        "def" : "hs._asm.undocumented.touchbar.bar:itemIdentifiers() -> table",
        "desc" : "Returns an array of strings specifying the identifiers of the touchbar items currently presented by the bar object."
      },
      {
        "doc" : "Get or set the customization label for saving and restoring user customizations for the bar.\n\nParameters:\n * `label` - an optional string, or explicit nil to disable, specifying the customization label for saving and restoring user customizations for the bar; defaults to nil.\n\nReturns:\n * If an argument is provided, returns the barObject; otherwise returns the current value.",
        "stripped_doc" : [
          "Get or set the customization label for saving and restoring user customizations for the bar.",
          ""
        ],
        "parameters" : [
          " * `label` - an optional string, or explicit nil to disable, specifying the customization label for saving and restoring user customizations for the bar; defaults to nil.",
          ""
        ],
        "name" : "customizationLabel",
        "notes" : [

        ],
        "signature" : "hs._asm.undocumented.touchbar.bar:customizationLabel([label]) -> barObject | string",
        "type" : "Method",
        "returns" : [
          " * If an argument is provided, returns the barObject; otherwise returns the current value."
        ],
        "def" : "hs._asm.undocumented.touchbar.bar:customizationLabel([label]) -> barObject | string",
        "desc" : "Get or set the customization label for saving and restoring user customizations for the bar."
      },
      {
        "doc" : "Get or set the principle item for the bar.\n\nParameters:\n * `identifer` - an optional string, or explicit nil to disable, specifying the principle item for the bar; defaults to nil.\n\nReturns:\n * If an argument is provided, returns the barObject; otherwise returns the current value.\n\nNotes:\n * the principle item will be centered in the displayed portion of the bar.\n\n * the identifier specified must belong to a touchbar items already assigned to the bar object with [hs._asm.undocumented.touchbar.bar:templateItems](#templateItems) or one of the built in identifier values defined in [hs._asm.undocumented.touchbar.bar.builtInIdentifiers](#builtInIdentifiers).",
        "stripped_doc" : [
          "Get or set the principle item for the bar.",
          ""
        ],
        "parameters" : [
          " * `identifer` - an optional string, or explicit nil to disable, specifying the principle item for the bar; defaults to nil.",
          ""
        ],
        "name" : "principleItem",
        "notes" : [
          " * the principle item will be centered in the displayed portion of the bar.",
          "",
          " * the identifier specified must belong to a touchbar items already assigned to the bar object with [hs._asm.undocumented.touchbar.bar:templateItems](#templateItems) or one of the built in identifier values defined in [hs._asm.undocumented.touchbar.bar.builtInIdentifiers](#builtInIdentifiers)."
        ],
        "signature" : "hs._asm.undocumented.touchbar.bar:principleItem([identifier]) -> barObject | string",
        "type" : "Method",
        "returns" : [
          " * If an argument is provided, returns the barObject; otherwise returns the current value.",
          ""
        ],
        "def" : "hs._asm.undocumented.touchbar.bar:principleItem([identifier]) -> barObject | string",
        "desc" : "Get or set the principle item for the bar."
      },
      {
        "doc" : "Get or set the item which replaces the system escape key for the bar.\n\nParameters:\n * `identifer` - an optional string, or explicit nil to disable, specifying the item which replaces the system escape key for the bar; defaults to nil.\n\nReturns:\n * If an argument is provided, returns the barObject; otherwise returns the current value.\n\nNotes:\n * This method has no effect on modally displayed bars.\n\n * the identifier specified must belong to a touchbar items already assigned to the bar object with [hs._asm.undocumented.touchbar.bar:templateItems](#templateItems).",
        "stripped_doc" : [
          "Get or set the item which replaces the system escape key for the bar.",
          ""
        ],
        "parameters" : [
          " * `identifer` - an optional string, or explicit nil to disable, specifying the item which replaces the system escape key for the bar; defaults to nil.",
          ""
        ],
        "name" : "escapeKeyReplacement",
        "notes" : [
          " * This method has no effect on modally displayed bars.",
          "",
          " * the identifier specified must belong to a touchbar items already assigned to the bar object with [hs._asm.undocumented.touchbar.bar:templateItems](#templateItems)."
        ],
        "signature" : "hs._asm.undocumented.touchbar.bar:escapeKeyReplacement([identifier]) -> barObject | string",
        "type" : "Method",
        "returns" : [
          " * If an argument is provided, returns the barObject; otherwise returns the current value.",
          ""
        ],
        "def" : "hs._asm.undocumented.touchbar.bar:escapeKeyReplacement([identifier]) -> barObject | string",
        "desc" : "Get or set the item which replaces the system escape key for the bar."
      },
      {
        "doc" : "Get or set an array of strings specifying the identifiers of the touchbar items that can be added or removed from the bar object through user customization.\n\nParameters:\n * `identifiersTable` - an optional table containing strings specifying the identifiers of touchbar items that can be added or removed from the bar object through user customization.\n\nReturns:\n * If an argument is provided, returns the barObject; otherwise returns the current value.\n\nNotes:\n * the identifiers specified must belong to touchbar items already assigned to the bar object with [hs._asm.undocumented.touchbar.bar:templateItems](#templateItems) or one of the built in identifier values defined in [hs._asm.undocumented.touchbar.bar.builtInIdentifiers](#builtInIdentifiers).",
        "stripped_doc" : [
          "Get or set an array of strings specifying the identifiers of the touchbar items that can be added or removed from the bar object through user customization.",
          ""
        ],
        "parameters" : [
          " * `identifiersTable` - an optional table containing strings specifying the identifiers of touchbar items that can be added or removed from the bar object through user customization.",
          ""
        ],
        "name" : "customizableIdentifiers",
        "notes" : [
          " * the identifiers specified must belong to touchbar items already assigned to the bar object with [hs._asm.undocumented.touchbar.bar:templateItems](#templateItems) or one of the built in identifier values defined in [hs._asm.undocumented.touchbar.bar.builtInIdentifiers](#builtInIdentifiers)."
        ],
        "signature" : "hs._asm.undocumented.touchbar.bar:customizableIdentifiers([identifiersTable]) -> barObject | table",
        "type" : "Method",
        "returns" : [
          " * If an argument is provided, returns the barObject; otherwise returns the current value.",
          ""
        ],
        "def" : "hs._asm.undocumented.touchbar.bar:customizableIdentifiers([identifiersTable]) -> barObject | table",
        "desc" : "Get or set an array of strings specifying the identifiers of the touchbar items that can be added or removed from the bar object through user customization."
      },
      {
        "doc" : "Get or set an array of strings specifying the identifiers of the touchbar items that cannot be removed from the bar object through user customization.\n\nParameters:\n * `identifiersTable` - an optional table containing strings specifying the identifiers of touchbar items that cannot be removed from the bar object through user customization.\n\nReturns:\n * If an argument is provided, returns the barObject; otherwise returns the current value.\n\nNotes:\n * the identifiers specified must belong to touchbar items already assigned to the bar object with [hs._asm.undocumented.touchbar.bar:templateItems](#templateItems) or one of the built in identifier values defined in [hs._asm.undocumented.touchbar.bar.builtInIdentifiers](#builtInIdentifiers).",
        "stripped_doc" : [
          "Get or set an array of strings specifying the identifiers of the touchbar items that cannot be removed from the bar object through user customization.",
          ""
        ],
        "parameters" : [
          " * `identifiersTable` - an optional table containing strings specifying the identifiers of touchbar items that cannot be removed from the bar object through user customization.",
          ""
        ],
        "name" : "requiredIdentifiers",
        "notes" : [
          " * the identifiers specified must belong to touchbar items already assigned to the bar object with [hs._asm.undocumented.touchbar.bar:templateItems](#templateItems) or one of the built in identifier values defined in [hs._asm.undocumented.touchbar.bar.builtInIdentifiers](#builtInIdentifiers)."
        ],
        "signature" : "hs._asm.undocumented.touchbar.bar:requiredIdentifiers([identifiersTable]) -> barObject | table",
        "type" : "Method",
        "returns" : [
          " * If an argument is provided, returns the barObject; otherwise returns the current value.",
          ""
        ],
        "def" : "hs._asm.undocumented.touchbar.bar:requiredIdentifiers([identifiersTable]) -> barObject | table",
        "desc" : "Get or set an array of strings specifying the identifiers of the touchbar items that cannot be removed from the bar object through user customization."
      },
      {
        "doc" : "Get or set an array of strings specifying the identifiers of the touchbar items added to the bar object by default, before any user customization.\n\nParameters:\n * `identifiersTable` - an optional table containing strings specifying the identifiers of touchbar items added to the bar object by default, before any user customization.\n\nReturns:\n * If an argument is provided, returns the barObject; otherwise returns the current value.\n\nNotes:\n * the identifiers specified must belong to touchbar items already assigned to the bar object with [hs._asm.undocumented.touchbar.bar:templateItems](#templateItems) or one of the built in identifier values defined in [hs._asm.undocumented.touchbar.bar.builtInIdentifiers](#builtInIdentifiers).",
        "stripped_doc" : [
          "Get or set an array of strings specifying the identifiers of the touchbar items added to the bar object by default, before any user customization.",
          ""
        ],
        "parameters" : [
          " * `identifiersTable` - an optional table containing strings specifying the identifiers of touchbar items added to the bar object by default, before any user customization.",
          ""
        ],
        "name" : "defaultIdentifiers",
        "notes" : [
          " * the identifiers specified must belong to touchbar items already assigned to the bar object with [hs._asm.undocumented.touchbar.bar:templateItems](#templateItems) or one of the built in identifier values defined in [hs._asm.undocumented.touchbar.bar.builtInIdentifiers](#builtInIdentifiers)."
        ],
        "signature" : "hs._asm.undocumented.touchbar.bar:defaultIdentifiers([identifiersTable]) -> barObject | table",
        "type" : "Method",
        "returns" : [
          " * If an argument is provided, returns the barObject; otherwise returns the current value.",
          ""
        ],
        "def" : "hs._asm.undocumented.touchbar.bar:defaultIdentifiers([identifiersTable]) -> barObject | table",
        "desc" : "Get or set an array of strings specifying the identifiers of the touchbar items added to the bar object by default, before any user customization."
      },
      {
        "doc" : "Get or set an array of `hs._asm.undocumented.touchbar.item` objects that can be presented by the bar object.\n\nParameters:\n * `itemsTable` - an optional table containing `hs._asm.undocumented.touchbar.item` objects that can be presented by the bar object.\n\nReturns:\n * If an argument is provided, returns the barObject; otherwise returns the current value.\n\nNotes:\n * only the identifiers of items assigned by this method can be used by the other methods in this module that use string identifiers in their arguments.",
        "stripped_doc" : [
          "Get or set an array of `hs._asm.undocumented.touchbar.item` objects that can be presented by the bar object.",
          ""
        ],
        "parameters" : [
          " * `itemsTable` - an optional table containing `hs._asm.undocumented.touchbar.item` objects that can be presented by the bar object.",
          ""
        ],
        "name" : "templateItems",
        "notes" : [
          " * only the identifiers of items assigned by this method can be used by the other methods in this module that use string identifiers in their arguments."
        ],
        "signature" : "hs._asm.undocumented.touchbar.bar:templateItems([itemsTable]) -> barObject | table",
        "type" : "Method",
        "returns" : [
          " * If an argument is provided, returns the barObject; otherwise returns the current value.",
          ""
        ],
        "def" : "hs._asm.undocumented.touchbar.bar:templateItems([itemsTable]) -> barObject | table",
        "desc" : "Get or set an array of `hs._asm.undocumented.touchbar.item` objects that can be presented by the bar object."
      },
      {
        "doc" : "Returns the touchbarItemObject for the identifier specified.\n\nParameters:\n * `identifier` - a string specifying the touchbarItem object to get from the items assigned to the bar with [hs._asm.undocumented.touchbar.bar:templateItems](#templateItems).\n\nReturns:\n * the touchbarItem object for the item specified or nil if no such item has been assigned to the bar.",
        "stripped_doc" : [
          "Returns the touchbarItemObject for the identifier specified.",
          ""
        ],
        "parameters" : [
          " * `identifier` - a string specifying the touchbarItem object to get from the items assigned to the bar with [hs._asm.undocumented.touchbar.bar:templateItems](#templateItems).",
          ""
        ],
        "name" : "itemForIdentifier",
        "notes" : [

        ],
        "signature" : "hs._asm.undocumented.touchbar.bar:itemForIdentifier([identifier]) -> touchbarItemObject | nil",
        "type" : "Method",
        "returns" : [
          " * the touchbarItem object for the item specified or nil if no such item has been assigned to the bar."
        ],
        "def" : "hs._asm.undocumented.touchbar.bar:itemForIdentifier([identifier]) -> touchbarItemObject | nil",
        "desc" : "Returns the touchbarItemObject for the identifier specified."
      },
      {
        "doc" : "Get or set the visibility callback function for the touch bar object.\n\nParameters:\n * `fn` - an optional function, or explicit nil to remove, specifying the visibility callback for the touch bar object.\n\nReturns:\n * if an argument is provided, returns the barObject; otherwise returns the current value\n\nNotes:\n * The callback function should expect two arguments, the barObject itself and a boolean indicating the new visibility of the touch bar.  It should return none.\n\n * This callback is invoked when the [hs._asm.undocumented.touchbar.bar:dismissModalBar](#dismissModalBar) or [hs._asm.undocumented.touchbar.bar:minimizeModalBar](#minimizeModalBar) methods are used.\n * This callback is *NOT* invoked when the system dismiss button is used (when the second argument to [hs._asm.undocumented.touchbar.bar:presentModalBar](#presentModalBar) or `hs._asm.undocumented.touchbar.item:presentModalBar` is true (or not present)). This is being investigated but at present no workaround is known.",
        "stripped_doc" : [
          "Get or set the visibility callback function for the touch bar object.",
          ""
        ],
        "parameters" : [
          " * `fn` - an optional function, or explicit nil to remove, specifying the visibility callback for the touch bar object.",
          ""
        ],
        "name" : "visibilityCallback",
        "notes" : [
          " * The callback function should expect two arguments, the barObject itself and a boolean indicating the new visibility of the touch bar.  It should return none.",
          "",
          " * This callback is invoked when the [hs._asm.undocumented.touchbar.bar:dismissModalBar](#dismissModalBar) or [hs._asm.undocumented.touchbar.bar:minimizeModalBar](#minimizeModalBar) methods are used.",
          " * This callback is *NOT* invoked when the system dismiss button is used (when the second argument to [hs._asm.undocumented.touchbar.bar:presentModalBar](#presentModalBar) or `hs._asm.undocumented.touchbar.item:presentModalBar` is true (or not present)). This is being investigated but at present no workaround is known."
        ],
        "signature" : "hs._asm.undocumented.touchbar.bar:visibilityCallback([fn | nil]) -> barObject | fn",
        "type" : "Method",
        "returns" : [
          " * if an argument is provided, returns the barObject; otherwise returns the current value",
          ""
        ],
        "def" : "hs._asm.undocumented.touchbar.bar:visibilityCallback([fn | nil]) -> barObject | fn",
        "desc" : "Get or set the visibility callback function for the touch bar object."
      },
      {
        "doc" : "Presents the bar in the touch bar display modally.\n\nParameters:\n * `itemObject`    - an optional `hs._asm.undocumented.touchbar.item` object which, if currently attached to the system tray, will be hidden while the bar is visible modally.\n * `dismissButton` - an optional boolean, default true, specifying whether or not the system escape (or its current replacement) button should be replaced by a button to remove the modal bar from the touch bar display when pressed.\n\nReturns:\n * the barObject\n\nNotes:\n * If you specify `dismissButton` as false, then you must use [hs._asm.undocumented.touchbar.bar:minimizeModalBar](#minimizeModalBar) or [hs._asm.undocumented.touchbar.bar:dismissModalBar](#dismissModalBar) to remove the modal bar from the touch bar display.\n\n * If you do not have \"Touch Bar Shows\" set to \"App Controls With Control Strip\" set in the Keyboard System Preferences, the modal bar will only be displayed when the Hammerspoon application is the frontmost application.\n\n * If you specify `itemObject` and the object is not currently attached to the system tray (see `hs._asm.undocumented.touchbar.item:addToSystemTray)`, or if you do not have \"Touch Bar Shows\" set to \"App Controls With Control Strip\" set in the Keyboard System Preferences, providing this argument has no effect.\n\n * This method uses undocumented functions and\/or framework methods and is not guaranteed to work with future updates to macOS. It has currently been tested with 10.12.6.",
        "stripped_doc" : [
          "Presents the bar in the touch bar display modally.",
          ""
        ],
        "parameters" : [
          " * `itemObject`    - an optional `hs._asm.undocumented.touchbar.item` object which, if currently attached to the system tray, will be hidden while the bar is visible modally.",
          " * `dismissButton` - an optional boolean, default true, specifying whether or not the system escape (or its current replacement) button should be replaced by a button to remove the modal bar from the touch bar display when pressed.",
          ""
        ],
        "name" : "presentModalBar",
        "notes" : [
          " * If you specify `dismissButton` as false, then you must use [hs._asm.undocumented.touchbar.bar:minimizeModalBar](#minimizeModalBar) or [hs._asm.undocumented.touchbar.bar:dismissModalBar](#dismissModalBar) to remove the modal bar from the touch bar display.",
          "",
          " * If you do not have \"Touch Bar Shows\" set to \"App Controls With Control Strip\" set in the Keyboard System Preferences, the modal bar will only be displayed when the Hammerspoon application is the frontmost application.",
          "",
          " * If you specify `itemObject` and the object is not currently attached to the system tray (see `hs._asm.undocumented.touchbar.item:addToSystemTray)`, or if you do not have \"Touch Bar Shows\" set to \"App Controls With Control Strip\" set in the Keyboard System Preferences, providing this argument has no effect.",
          "",
          " * This method uses undocumented functions and\/or framework methods and is not guaranteed to work with future updates to macOS. It has currently been tested with 10.12.6."
        ],
        "signature" : "hs._asm.undocumented.touchbar.bar:presentModalBar([itemObject], [dismissButton]) -> barObject",
        "type" : "Method",
        "returns" : [
          " * the barObject",
          ""
        ],
        "def" : "hs._asm.undocumented.touchbar.bar:presentModalBar([itemObject], [dismissButton]) -> barObject",
        "desc" : "Presents the bar in the touch bar display modally."
      },
      {
        "doc" : "Dismiss the bar from the touch bar display by removing it if it is currently being displayed modally.\n\nParameters:\n * None\n\nReturns:\n * the barObject\n\nNotes:\n * If an `itemObject` was specified with [hs._asm.undocumented.touchbar.bar:presentModalBar](#presentModalBar) or if the bar was displayed with `hs._asm.undocumented.touchbar.item:presentModalBar`, this method will ***not*** restore the item to the system tray.\n\n * This method uses undocumented functions and\/or framework methods and is not guaranteed to work with future updates to macOS. It has currently been tested with 10.12.6.",
        "stripped_doc" : [
          "Dismiss the bar from the touch bar display by removing it if it is currently being displayed modally.",
          ""
        ],
        "parameters" : [
          " * None",
          ""
        ],
        "name" : "dismissModalBar",
        "notes" : [
          " * If an `itemObject` was specified with [hs._asm.undocumented.touchbar.bar:presentModalBar](#presentModalBar) or if the bar was displayed with `hs._asm.undocumented.touchbar.item:presentModalBar`, this method will ***not*** restore the item to the system tray.",
          "",
          " * This method uses undocumented functions and\/or framework methods and is not guaranteed to work with future updates to macOS. It has currently been tested with 10.12.6."
        ],
        "signature" : "hs._asm.undocumented.touchbar.bar:dismissModalBar() -> barObject",
        "type" : "Method",
        "returns" : [
          " * the barObject",
          ""
        ],
        "def" : "hs._asm.undocumented.touchbar.bar:dismissModalBar() -> barObject",
        "desc" : "Dismiss the bar from the touch bar display by removing it if it is currently being displayed modally."
      },
      {
        "doc" : "Dismiss the bar from the touch bar display by minimizing it if it is currently being displayed modally.\n\nParameters:\n * None\n\nReturns:\n * the barObject\n\nNotes:\n * If an `itemObject` was specified with [hs._asm.undocumented.touchbar.bar:presentModalBar](#presentModalBar) or if the bar was displayed with `hs._asm.undocumented.touchbar.item:presentModalBar`, this method ***will*** restore the item to the system tray.\n\n * This method is the same as pressing the `dismissButton` if it was not set to false when [hs._asm.undocumented.touchbar.bar:presentModalBar](#presentModalBar) or `hs._asm.undocumented.touchbar.item:presentModalBar` was invoked.\n\n * This method uses undocumented functions and\/or framework methods and is not guaranteed to work with future updates to macOS. It has currently been tested with 10.12.6.",
        "stripped_doc" : [
          "Dismiss the bar from the touch bar display by minimizing it if it is currently being displayed modally.",
          ""
        ],
        "parameters" : [
          " * None",
          ""
        ],
        "name" : "minimizeModalBar",
        "notes" : [
          " * If an `itemObject` was specified with [hs._asm.undocumented.touchbar.bar:presentModalBar](#presentModalBar) or if the bar was displayed with `hs._asm.undocumented.touchbar.item:presentModalBar`, this method ***will*** restore the item to the system tray.",
          "",
          " * This method is the same as pressing the `dismissButton` if it was not set to false when [hs._asm.undocumented.touchbar.bar:presentModalBar](#presentModalBar) or `hs._asm.undocumented.touchbar.item:presentModalBar` was invoked.",
          "",
          " * This method uses undocumented functions and\/or framework methods and is not guaranteed to work with future updates to macOS. It has currently been tested with 10.12.6."
        ],
        "signature" : "hs._asm.undocumented.touchbar.bar:minimizeModalBar() -> barObject",
        "type" : "Method",
        "returns" : [
          " * the barObject",
          ""
        ],
        "def" : "hs._asm.undocumented.touchbar.bar:minimizeModalBar() -> barObject",
        "desc" : "Dismiss the bar from the touch bar display by minimizing it if it is currently being displayed modally."
      }
    ],
    "Command" : [

    ],
    "items" : [
      {
        "doc" : "A table of key-value pairs whose values represent built in touch bar items which can be used to adjust the layout of the bar object when it is being presented.\n\nCurrently the following keys are defined:\n * smallSpace      - provides a small space between items\n * largeSpace      - provides a larger space between items\n * flexibleSpace   - provides an expanding\/contracting space between items\n\nThe following is ignored for modally displayed bars, so it's effects are still being evaluated; documentation will be updated when nested bars can be tested and more fully understood within the context of the Hammerspoon console and webview.\n * otherItemsProxy - provides a place for nested bars to display items",
        "stripped_doc" : [
          "A table of key-value pairs whose values represent built in touch bar items which can be used to adjust the layout of the bar object when it is being presented.",
          "",
          "Currently the following keys are defined:",
          " * smallSpace      - provides a small space between items",
          " * largeSpace      - provides a larger space between items",
          " * flexibleSpace   - provides an expanding\/contracting space between items",
          "",
          "The following is ignored for modally displayed bars, so it's effects are still being evaluated; documentation will be updated when nested bars can be tested and more fully understood within the context of the Hammerspoon console and webview.",
          " * otherItemsProxy - provides a place for nested bars to display items"
        ],
        "parameters" : [

        ],
        "name" : "builtInIdentifiers",
        "notes" : [

        ],
        "signature" : "hs._asm.undocumented.touchbar.bar.builtInIdentifiers[]",
        "type" : "Constant",
        "returns" : [

        ],
        "def" : "hs._asm.undocumented.touchbar.bar.builtInIdentifiers[]",
        "desc" : "A table of key-value pairs whose values represent built in touch bar items which can be used to adjust the layout of the bar object when it is being presented."
      },
      {
        "doc" : "(See Notes) Toggle's the Touch Bar customization panel for the Hammerspoon application\n\nParameters:\n * None\n\nReturns:\n * None\n\nNotes:\n * At present this function is not useful; it is expected to be more useful when Hammerspoon specific views can provide their own touchbars.\n\n * The customization panel allows modification of the current bar visible for the macOS application triggering the request within that applications resolver chain -- as such, it can only modify touchbar's attached to the Hammerspoon console or webview objects.\n * The customization panel cannot modify modally displayed bar objects.",
        "stripped_doc" : [
          "(See Notes) Toggle's the Touch Bar customization panel for the Hammerspoon application",
          ""
        ],
        "parameters" : [
          " * None",
          ""
        ],
        "name" : "toggleCustomization",
        "notes" : [
          " * At present this function is not useful; it is expected to be more useful when Hammerspoon specific views can provide their own touchbars.",
          "",
          " * The customization panel allows modification of the current bar visible for the macOS application triggering the request within that applications resolver chain -- as such, it can only modify touchbar's attached to the Hammerspoon console or webview objects.",
          " * The customization panel cannot modify modally displayed bar objects."
        ],
        "signature" : "hs._asm.undocumented.touchbar.bar.toggleCustomization() -> None",
        "type" : "Function",
        "returns" : [
          " * None",
          ""
        ],
        "def" : "hs._asm.undocumented.touchbar.bar.toggleCustomization() -> None",
        "desc" : "(See Notes) Toggle's the Touch Bar customization panel for the Hammerspoon application"
      },
      {
        "doc" : "Creates a new bar object\n\nParameters:\n * None\n\nReturns:\n * a new bar object",
        "stripped_doc" : [
          "Creates a new bar object",
          ""
        ],
        "parameters" : [
          " * None",
          ""
        ],
        "name" : "new",
        "notes" : [

        ],
        "signature" : "hs._asm.undocumented.touchbar.bar.new() -> barObject",
        "type" : "Constructor",
        "returns" : [
          " * a new bar object"
        ],
        "def" : "hs._asm.undocumented.touchbar.bar.new() -> barObject",
        "desc" : "Creates a new bar object"
      },
      {
        "doc" : "Get or set an array of strings specifying the identifiers of the touchbar items that can be added or removed from the bar object through user customization.\n\nParameters:\n * `identifiersTable` - an optional table containing strings specifying the identifiers of touchbar items that can be added or removed from the bar object through user customization.\n\nReturns:\n * If an argument is provided, returns the barObject; otherwise returns the current value.\n\nNotes:\n * the identifiers specified must belong to touchbar items already assigned to the bar object with [hs._asm.undocumented.touchbar.bar:templateItems](#templateItems) or one of the built in identifier values defined in [hs._asm.undocumented.touchbar.bar.builtInIdentifiers](#builtInIdentifiers).",
        "stripped_doc" : [
          "Get or set an array of strings specifying the identifiers of the touchbar items that can be added or removed from the bar object through user customization.",
          ""
        ],
        "parameters" : [
          " * `identifiersTable` - an optional table containing strings specifying the identifiers of touchbar items that can be added or removed from the bar object through user customization.",
          ""
        ],
        "name" : "customizableIdentifiers",
        "notes" : [
          " * the identifiers specified must belong to touchbar items already assigned to the bar object with [hs._asm.undocumented.touchbar.bar:templateItems](#templateItems) or one of the built in identifier values defined in [hs._asm.undocumented.touchbar.bar.builtInIdentifiers](#builtInIdentifiers)."
        ],
        "signature" : "hs._asm.undocumented.touchbar.bar:customizableIdentifiers([identifiersTable]) -> barObject | table",
        "type" : "Method",
        "returns" : [
          " * If an argument is provided, returns the barObject; otherwise returns the current value.",
          ""
        ],
        "def" : "hs._asm.undocumented.touchbar.bar:customizableIdentifiers([identifiersTable]) -> barObject | table",
        "desc" : "Get or set an array of strings specifying the identifiers of the touchbar items that can be added or removed from the bar object through user customization."
      },
      {
        "doc" : "Get or set the customization label for saving and restoring user customizations for the bar.\n\nParameters:\n * `label` - an optional string, or explicit nil to disable, specifying the customization label for saving and restoring user customizations for the bar; defaults to nil.\n\nReturns:\n * If an argument is provided, returns the barObject; otherwise returns the current value.",
        "stripped_doc" : [
          "Get or set the customization label for saving and restoring user customizations for the bar.",
          ""
        ],
        "parameters" : [
          " * `label` - an optional string, or explicit nil to disable, specifying the customization label for saving and restoring user customizations for the bar; defaults to nil.",
          ""
        ],
        "name" : "customizationLabel",
        "notes" : [

        ],
        "signature" : "hs._asm.undocumented.touchbar.bar:customizationLabel([label]) -> barObject | string",
        "type" : "Method",
        "returns" : [
          " * If an argument is provided, returns the barObject; otherwise returns the current value."
        ],
        "def" : "hs._asm.undocumented.touchbar.bar:customizationLabel([label]) -> barObject | string",
        "desc" : "Get or set the customization label for saving and restoring user customizations for the bar."
      },
      {
        "doc" : "Get or set an array of strings specifying the identifiers of the touchbar items added to the bar object by default, before any user customization.\n\nParameters:\n * `identifiersTable` - an optional table containing strings specifying the identifiers of touchbar items added to the bar object by default, before any user customization.\n\nReturns:\n * If an argument is provided, returns the barObject; otherwise returns the current value.\n\nNotes:\n * the identifiers specified must belong to touchbar items already assigned to the bar object with [hs._asm.undocumented.touchbar.bar:templateItems](#templateItems) or one of the built in identifier values defined in [hs._asm.undocumented.touchbar.bar.builtInIdentifiers](#builtInIdentifiers).",
        "stripped_doc" : [
          "Get or set an array of strings specifying the identifiers of the touchbar items added to the bar object by default, before any user customization.",
          ""
        ],
        "parameters" : [
          " * `identifiersTable` - an optional table containing strings specifying the identifiers of touchbar items added to the bar object by default, before any user customization.",
          ""
        ],
        "name" : "defaultIdentifiers",
        "notes" : [
          " * the identifiers specified must belong to touchbar items already assigned to the bar object with [hs._asm.undocumented.touchbar.bar:templateItems](#templateItems) or one of the built in identifier values defined in [hs._asm.undocumented.touchbar.bar.builtInIdentifiers](#builtInIdentifiers)."
        ],
        "signature" : "hs._asm.undocumented.touchbar.bar:defaultIdentifiers([identifiersTable]) -> barObject | table",
        "type" : "Method",
        "returns" : [
          " * If an argument is provided, returns the barObject; otherwise returns the current value.",
          ""
        ],
        "def" : "hs._asm.undocumented.touchbar.bar:defaultIdentifiers([identifiersTable]) -> barObject | table",
        "desc" : "Get or set an array of strings specifying the identifiers of the touchbar items added to the bar object by default, before any user customization."
      },
      {
        "doc" : "Dismiss the bar from the touch bar display by removing it if it is currently being displayed modally.\n\nParameters:\n * None\n\nReturns:\n * the barObject\n\nNotes:\n * If an `itemObject` was specified with [hs._asm.undocumented.touchbar.bar:presentModalBar](#presentModalBar) or if the bar was displayed with `hs._asm.undocumented.touchbar.item:presentModalBar`, this method will ***not*** restore the item to the system tray.\n\n * This method uses undocumented functions and\/or framework methods and is not guaranteed to work with future updates to macOS. It has currently been tested with 10.12.6.",
        "stripped_doc" : [
          "Dismiss the bar from the touch bar display by removing it if it is currently being displayed modally.",
          ""
        ],
        "parameters" : [
          " * None",
          ""
        ],
        "name" : "dismissModalBar",
        "notes" : [
          " * If an `itemObject` was specified with [hs._asm.undocumented.touchbar.bar:presentModalBar](#presentModalBar) or if the bar was displayed with `hs._asm.undocumented.touchbar.item:presentModalBar`, this method will ***not*** restore the item to the system tray.",
          "",
          " * This method uses undocumented functions and\/or framework methods and is not guaranteed to work with future updates to macOS. It has currently been tested with 10.12.6."
        ],
        "signature" : "hs._asm.undocumented.touchbar.bar:dismissModalBar() -> barObject",
        "type" : "Method",
        "returns" : [
          " * the barObject",
          ""
        ],
        "def" : "hs._asm.undocumented.touchbar.bar:dismissModalBar() -> barObject",
        "desc" : "Dismiss the bar from the touch bar display by removing it if it is currently being displayed modally."
      },
      {
        "doc" : "Get or set the item which replaces the system escape key for the bar.\n\nParameters:\n * `identifer` - an optional string, or explicit nil to disable, specifying the item which replaces the system escape key for the bar; defaults to nil.\n\nReturns:\n * If an argument is provided, returns the barObject; otherwise returns the current value.\n\nNotes:\n * This method has no effect on modally displayed bars.\n\n * the identifier specified must belong to a touchbar items already assigned to the bar object with [hs._asm.undocumented.touchbar.bar:templateItems](#templateItems).",
        "stripped_doc" : [
          "Get or set the item which replaces the system escape key for the bar.",
          ""
        ],
        "parameters" : [
          " * `identifer` - an optional string, or explicit nil to disable, specifying the item which replaces the system escape key for the bar; defaults to nil.",
          ""
        ],
        "name" : "escapeKeyReplacement",
        "notes" : [
          " * This method has no effect on modally displayed bars.",
          "",
          " * the identifier specified must belong to a touchbar items already assigned to the bar object with [hs._asm.undocumented.touchbar.bar:templateItems](#templateItems)."
        ],
        "signature" : "hs._asm.undocumented.touchbar.bar:escapeKeyReplacement([identifier]) -> barObject | string",
        "type" : "Method",
        "returns" : [
          " * If an argument is provided, returns the barObject; otherwise returns the current value.",
          ""
        ],
        "def" : "hs._asm.undocumented.touchbar.bar:escapeKeyReplacement([identifier]) -> barObject | string",
        "desc" : "Get or set the item which replaces the system escape key for the bar."
      },
      {
        "doc" : "Returns a boolean indicating whether the bar object is currently visible in the laptop or virtual Touch Bar.\n\nParameters:\n * None\n\nReturns:\n * a boolean value indicating whether or not the touchbar represented by the object is currently being displayed in the laptop or virtual Touch Bar.\n\nNotes:\n * The value returned by this method changes as expected when the [hs._asm.undocumented.touchbar.bar:dismissModalBar](#dismissModalBar) or [hs._asm.undocumented.touchbar.bar:minimizeModalBar](#minimizeModalBar) methods are used.\n * It does *NOT* reliably change when when the system dismiss button is used (when the second argument to [hs._asm.undocumented.touchbar.bar:presentModalBar](#presentModalBar) or `hs._asm.undocumented.touchbar.item:presentModalBar` is true (or not present)).  This is being investigated but at present no workaround is known.",
        "stripped_doc" : [
          "Returns a boolean indicating whether the bar object is currently visible in the laptop or virtual Touch Bar.",
          ""
        ],
        "parameters" : [
          " * None",
          ""
        ],
        "name" : "isVisible",
        "notes" : [
          " * The value returned by this method changes as expected when the [hs._asm.undocumented.touchbar.bar:dismissModalBar](#dismissModalBar) or [hs._asm.undocumented.touchbar.bar:minimizeModalBar](#minimizeModalBar) methods are used.",
          " * It does *NOT* reliably change when when the system dismiss button is used (when the second argument to [hs._asm.undocumented.touchbar.bar:presentModalBar](#presentModalBar) or `hs._asm.undocumented.touchbar.item:presentModalBar` is true (or not present)).  This is being investigated but at present no workaround is known."
        ],
        "signature" : "hs._asm.undocumented.touchbar.bar:isVisible() -> boolean",
        "type" : "Method",
        "returns" : [
          " * a boolean value indicating whether or not the touchbar represented by the object is currently being displayed in the laptop or virtual Touch Bar.",
          ""
        ],
        "def" : "hs._asm.undocumented.touchbar.bar:isVisible() -> boolean",
        "desc" : "Returns a boolean indicating whether the bar object is currently visible in the laptop or virtual Touch Bar."
      },
      {
        "doc" : "Returns the touchbarItemObject for the identifier specified.\n\nParameters:\n * `identifier` - a string specifying the touchbarItem object to get from the items assigned to the bar with [hs._asm.undocumented.touchbar.bar:templateItems](#templateItems).\n\nReturns:\n * the touchbarItem object for the item specified or nil if no such item has been assigned to the bar.",
        "stripped_doc" : [
          "Returns the touchbarItemObject for the identifier specified.",
          ""
        ],
        "parameters" : [
          " * `identifier` - a string specifying the touchbarItem object to get from the items assigned to the bar with [hs._asm.undocumented.touchbar.bar:templateItems](#templateItems).",
          ""
        ],
        "name" : "itemForIdentifier",
        "notes" : [

        ],
        "signature" : "hs._asm.undocumented.touchbar.bar:itemForIdentifier([identifier]) -> touchbarItemObject | nil",
        "type" : "Method",
        "returns" : [
          " * the touchbarItem object for the item specified or nil if no such item has been assigned to the bar."
        ],
        "def" : "hs._asm.undocumented.touchbar.bar:itemForIdentifier([identifier]) -> touchbarItemObject | nil",
        "desc" : "Returns the touchbarItemObject for the identifier specified."
      },
      {
        "doc" : "Returns an array of strings specifying the identifiers of the touchbar items currently presented by the bar object.\n\nParameters:\n * None\n\nReturns:\n * an array of strings specifying the identifiers of the touchbar items currently presented by the bar object.\n\nNotes:\n * If the user has not customized the bar, the list of identifiers will match the list provided by [hs._asm.undocumented.touchbar.bar:defaultIdentifiers()](#defaultIdentifiers).",
        "stripped_doc" : [
          "Returns an array of strings specifying the identifiers of the touchbar items currently presented by the bar object.",
          ""
        ],
        "parameters" : [
          " * None",
          ""
        ],
        "name" : "itemIdentifiers",
        "notes" : [
          " * If the user has not customized the bar, the list of identifiers will match the list provided by [hs._asm.undocumented.touchbar.bar:defaultIdentifiers()](#defaultIdentifiers)."
        ],
        "signature" : "hs._asm.undocumented.touchbar.bar:itemIdentifiers() -> table",
        "type" : "Method",
        "returns" : [
          " * an array of strings specifying the identifiers of the touchbar items currently presented by the bar object.",
          ""
        ],
        "def" : "hs._asm.undocumented.touchbar.bar:itemIdentifiers() -> table",
        "desc" : "Returns an array of strings specifying the identifiers of the touchbar items currently presented by the bar object."
      },
      {
        "doc" : "Dismiss the bar from the touch bar display by minimizing it if it is currently being displayed modally.\n\nParameters:\n * None\n\nReturns:\n * the barObject\n\nNotes:\n * If an `itemObject` was specified with [hs._asm.undocumented.touchbar.bar:presentModalBar](#presentModalBar) or if the bar was displayed with `hs._asm.undocumented.touchbar.item:presentModalBar`, this method ***will*** restore the item to the system tray.\n\n * This method is the same as pressing the `dismissButton` if it was not set to false when [hs._asm.undocumented.touchbar.bar:presentModalBar](#presentModalBar) or `hs._asm.undocumented.touchbar.item:presentModalBar` was invoked.\n\n * This method uses undocumented functions and\/or framework methods and is not guaranteed to work with future updates to macOS. It has currently been tested with 10.12.6.",
        "stripped_doc" : [
          "Dismiss the bar from the touch bar display by minimizing it if it is currently being displayed modally.",
          ""
        ],
        "parameters" : [
          " * None",
          ""
        ],
        "name" : "minimizeModalBar",
        "notes" : [
          " * If an `itemObject` was specified with [hs._asm.undocumented.touchbar.bar:presentModalBar](#presentModalBar) or if the bar was displayed with `hs._asm.undocumented.touchbar.item:presentModalBar`, this method ***will*** restore the item to the system tray.",
          "",
          " * This method is the same as pressing the `dismissButton` if it was not set to false when [hs._asm.undocumented.touchbar.bar:presentModalBar](#presentModalBar) or `hs._asm.undocumented.touchbar.item:presentModalBar` was invoked.",
          "",
          " * This method uses undocumented functions and\/or framework methods and is not guaranteed to work with future updates to macOS. It has currently been tested with 10.12.6."
        ],
        "signature" : "hs._asm.undocumented.touchbar.bar:minimizeModalBar() -> barObject",
        "type" : "Method",
        "returns" : [
          " * the barObject",
          ""
        ],
        "def" : "hs._asm.undocumented.touchbar.bar:minimizeModalBar() -> barObject",
        "desc" : "Dismiss the bar from the touch bar display by minimizing it if it is currently being displayed modally."
      },
      {
        "doc" : "Presents the bar in the touch bar display modally.\n\nParameters:\n * `itemObject`    - an optional `hs._asm.undocumented.touchbar.item` object which, if currently attached to the system tray, will be hidden while the bar is visible modally.\n * `dismissButton` - an optional boolean, default true, specifying whether or not the system escape (or its current replacement) button should be replaced by a button to remove the modal bar from the touch bar display when pressed.\n\nReturns:\n * the barObject\n\nNotes:\n * If you specify `dismissButton` as false, then you must use [hs._asm.undocumented.touchbar.bar:minimizeModalBar](#minimizeModalBar) or [hs._asm.undocumented.touchbar.bar:dismissModalBar](#dismissModalBar) to remove the modal bar from the touch bar display.\n\n * If you do not have \"Touch Bar Shows\" set to \"App Controls With Control Strip\" set in the Keyboard System Preferences, the modal bar will only be displayed when the Hammerspoon application is the frontmost application.\n\n * If you specify `itemObject` and the object is not currently attached to the system tray (see `hs._asm.undocumented.touchbar.item:addToSystemTray)`, or if you do not have \"Touch Bar Shows\" set to \"App Controls With Control Strip\" set in the Keyboard System Preferences, providing this argument has no effect.\n\n * This method uses undocumented functions and\/or framework methods and is not guaranteed to work with future updates to macOS. It has currently been tested with 10.12.6.",
        "stripped_doc" : [
          "Presents the bar in the touch bar display modally.",
          ""
        ],
        "parameters" : [
          " * `itemObject`    - an optional `hs._asm.undocumented.touchbar.item` object which, if currently attached to the system tray, will be hidden while the bar is visible modally.",
          " * `dismissButton` - an optional boolean, default true, specifying whether or not the system escape (or its current replacement) button should be replaced by a button to remove the modal bar from the touch bar display when pressed.",
          ""
        ],
        "name" : "presentModalBar",
        "notes" : [
          " * If you specify `dismissButton` as false, then you must use [hs._asm.undocumented.touchbar.bar:minimizeModalBar](#minimizeModalBar) or [hs._asm.undocumented.touchbar.bar:dismissModalBar](#dismissModalBar) to remove the modal bar from the touch bar display.",
          "",
          " * If you do not have \"Touch Bar Shows\" set to \"App Controls With Control Strip\" set in the Keyboard System Preferences, the modal bar will only be displayed when the Hammerspoon application is the frontmost application.",
          "",
          " * If you specify `itemObject` and the object is not currently attached to the system tray (see `hs._asm.undocumented.touchbar.item:addToSystemTray)`, or if you do not have \"Touch Bar Shows\" set to \"App Controls With Control Strip\" set in the Keyboard System Preferences, providing this argument has no effect.",
          "",
          " * This method uses undocumented functions and\/or framework methods and is not guaranteed to work with future updates to macOS. It has currently been tested with 10.12.6."
        ],
        "signature" : "hs._asm.undocumented.touchbar.bar:presentModalBar([itemObject], [dismissButton]) -> barObject",
        "type" : "Method",
        "returns" : [
          " * the barObject",
          ""
        ],
        "def" : "hs._asm.undocumented.touchbar.bar:presentModalBar([itemObject], [dismissButton]) -> barObject",
        "desc" : "Presents the bar in the touch bar display modally."
      },
      {
        "doc" : "Get or set the principle item for the bar.\n\nParameters:\n * `identifer` - an optional string, or explicit nil to disable, specifying the principle item for the bar; defaults to nil.\n\nReturns:\n * If an argument is provided, returns the barObject; otherwise returns the current value.\n\nNotes:\n * the principle item will be centered in the displayed portion of the bar.\n\n * the identifier specified must belong to a touchbar items already assigned to the bar object with [hs._asm.undocumented.touchbar.bar:templateItems](#templateItems) or one of the built in identifier values defined in [hs._asm.undocumented.touchbar.bar.builtInIdentifiers](#builtInIdentifiers).",
        "stripped_doc" : [
          "Get or set the principle item for the bar.",
          ""
        ],
        "parameters" : [
          " * `identifer` - an optional string, or explicit nil to disable, specifying the principle item for the bar; defaults to nil.",
          ""
        ],
        "name" : "principleItem",
        "notes" : [
          " * the principle item will be centered in the displayed portion of the bar.",
          "",
          " * the identifier specified must belong to a touchbar items already assigned to the bar object with [hs._asm.undocumented.touchbar.bar:templateItems](#templateItems) or one of the built in identifier values defined in [hs._asm.undocumented.touchbar.bar.builtInIdentifiers](#builtInIdentifiers)."
        ],
        "signature" : "hs._asm.undocumented.touchbar.bar:principleItem([identifier]) -> barObject | string",
        "type" : "Method",
        "returns" : [
          " * If an argument is provided, returns the barObject; otherwise returns the current value.",
          ""
        ],
        "def" : "hs._asm.undocumented.touchbar.bar:principleItem([identifier]) -> barObject | string",
        "desc" : "Get or set the principle item for the bar."
      },
      {
        "doc" : "Get or set an array of strings specifying the identifiers of the touchbar items that cannot be removed from the bar object through user customization.\n\nParameters:\n * `identifiersTable` - an optional table containing strings specifying the identifiers of touchbar items that cannot be removed from the bar object through user customization.\n\nReturns:\n * If an argument is provided, returns the barObject; otherwise returns the current value.\n\nNotes:\n * the identifiers specified must belong to touchbar items already assigned to the bar object with [hs._asm.undocumented.touchbar.bar:templateItems](#templateItems) or one of the built in identifier values defined in [hs._asm.undocumented.touchbar.bar.builtInIdentifiers](#builtInIdentifiers).",
        "stripped_doc" : [
          "Get or set an array of strings specifying the identifiers of the touchbar items that cannot be removed from the bar object through user customization.",
          ""
        ],
        "parameters" : [
          " * `identifiersTable` - an optional table containing strings specifying the identifiers of touchbar items that cannot be removed from the bar object through user customization.",
          ""
        ],
        "name" : "requiredIdentifiers",
        "notes" : [
          " * the identifiers specified must belong to touchbar items already assigned to the bar object with [hs._asm.undocumented.touchbar.bar:templateItems](#templateItems) or one of the built in identifier values defined in [hs._asm.undocumented.touchbar.bar.builtInIdentifiers](#builtInIdentifiers)."
        ],
        "signature" : "hs._asm.undocumented.touchbar.bar:requiredIdentifiers([identifiersTable]) -> barObject | table",
        "type" : "Method",
        "returns" : [
          " * If an argument is provided, returns the barObject; otherwise returns the current value.",
          ""
        ],
        "def" : "hs._asm.undocumented.touchbar.bar:requiredIdentifiers([identifiersTable]) -> barObject | table",
        "desc" : "Get or set an array of strings specifying the identifiers of the touchbar items that cannot be removed from the bar object through user customization."
      },
      {
        "doc" : "Get or set an array of `hs._asm.undocumented.touchbar.item` objects that can be presented by the bar object.\n\nParameters:\n * `itemsTable` - an optional table containing `hs._asm.undocumented.touchbar.item` objects that can be presented by the bar object.\n\nReturns:\n * If an argument is provided, returns the barObject; otherwise returns the current value.\n\nNotes:\n * only the identifiers of items assigned by this method can be used by the other methods in this module that use string identifiers in their arguments.",
        "stripped_doc" : [
          "Get or set an array of `hs._asm.undocumented.touchbar.item` objects that can be presented by the bar object.",
          ""
        ],
        "parameters" : [
          " * `itemsTable` - an optional table containing `hs._asm.undocumented.touchbar.item` objects that can be presented by the bar object.",
          ""
        ],
        "name" : "templateItems",
        "notes" : [
          " * only the identifiers of items assigned by this method can be used by the other methods in this module that use string identifiers in their arguments."
        ],
        "signature" : "hs._asm.undocumented.touchbar.bar:templateItems([itemsTable]) -> barObject | table",
        "type" : "Method",
        "returns" : [
          " * If an argument is provided, returns the barObject; otherwise returns the current value.",
          ""
        ],
        "def" : "hs._asm.undocumented.touchbar.bar:templateItems([itemsTable]) -> barObject | table",
        "desc" : "Get or set an array of `hs._asm.undocumented.touchbar.item` objects that can be presented by the bar object."
      },
      {
        "doc" : "Get or set the visibility callback function for the touch bar object.\n\nParameters:\n * `fn` - an optional function, or explicit nil to remove, specifying the visibility callback for the touch bar object.\n\nReturns:\n * if an argument is provided, returns the barObject; otherwise returns the current value\n\nNotes:\n * The callback function should expect two arguments, the barObject itself and a boolean indicating the new visibility of the touch bar.  It should return none.\n\n * This callback is invoked when the [hs._asm.undocumented.touchbar.bar:dismissModalBar](#dismissModalBar) or [hs._asm.undocumented.touchbar.bar:minimizeModalBar](#minimizeModalBar) methods are used.\n * This callback is *NOT* invoked when the system dismiss button is used (when the second argument to [hs._asm.undocumented.touchbar.bar:presentModalBar](#presentModalBar) or `hs._asm.undocumented.touchbar.item:presentModalBar` is true (or not present)). This is being investigated but at present no workaround is known.",
        "stripped_doc" : [
          "Get or set the visibility callback function for the touch bar object.",
          ""
        ],
        "parameters" : [
          " * `fn` - an optional function, or explicit nil to remove, specifying the visibility callback for the touch bar object.",
          ""
        ],
        "name" : "visibilityCallback",
        "notes" : [
          " * The callback function should expect two arguments, the barObject itself and a boolean indicating the new visibility of the touch bar.  It should return none.",
          "",
          " * This callback is invoked when the [hs._asm.undocumented.touchbar.bar:dismissModalBar](#dismissModalBar) or [hs._asm.undocumented.touchbar.bar:minimizeModalBar](#minimizeModalBar) methods are used.",
          " * This callback is *NOT* invoked when the system dismiss button is used (when the second argument to [hs._asm.undocumented.touchbar.bar:presentModalBar](#presentModalBar) or `hs._asm.undocumented.touchbar.item:presentModalBar` is true (or not present)). This is being investigated but at present no workaround is known."
        ],
        "signature" : "hs._asm.undocumented.touchbar.bar:visibilityCallback([fn | nil]) -> barObject | fn",
        "type" : "Method",
        "returns" : [
          " * if an argument is provided, returns the barObject; otherwise returns the current value",
          ""
        ],
        "def" : "hs._asm.undocumented.touchbar.bar:visibilityCallback([fn | nil]) -> barObject | fn",
        "desc" : "Get or set the visibility callback function for the touch bar object."
      }
    ],
    "Field" : [

    ],
    "name" : "hs._asm.undocumented.touchbar.bar"
  },
  {
    "Constant" : [
      {
        "doc" : "Predefined visibility priorities for use with [hs._asm.undocumented.touchbar.item:visibilityPriority](#visibilityPriority)\n\nA table containing key-value pairs of predefined visibility priorities used when the touch bar isn't large enough to display all of the items which are eligible for presentation. Items with lower priorities are hidden first. These numbers are only suggestions and other numbers are also valid for use with [hs._asm.undocumented.touchbar.item:visibilityPriority](#visibilityPriority).\n\nPredefined values are as follows:\n * `low`   - -1000.0\n * `normal`-     0.0 (this is the default value assigned to an item when it is first created)\n * `high`  -  1000.0",
        "stripped_doc" : [
          "Predefined visibility priorities for use with [hs._asm.undocumented.touchbar.item:visibilityPriority](#visibilityPriority)",
          "",
          "A table containing key-value pairs of predefined visibility priorities used when the touch bar isn't large enough to display all of the items which are eligible for presentation. Items with lower priorities are hidden first. These numbers are only suggestions and other numbers are also valid for use with [hs._asm.undocumented.touchbar.item:visibilityPriority](#visibilityPriority).",
          "",
          "Predefined values are as follows:",
          " * `low`   - -1000.0",
          " * `normal`-     0.0 (this is the default value assigned to an item when it is first created)",
          " * `high`  -  1000.0"
        ],
        "parameters" : [

        ],
        "name" : "visibilityPriorities",
        "notes" : [

        ],
        "signature" : "hs._asm.undocumented.touchbar.item.visibilityPriorities[]",
        "type" : "Constant",
        "returns" : [

        ],
        "def" : "hs._asm.undocumented.touchbar.item.visibilityPriorities[]",
        "desc" : "Predefined visibility priorities for use with [hs._asm.undocumented.touchbar.item:visibilityPriority](#visibilityPriority)"
      }
    ],
    "submodules" : [

    ],
    "Function" : [

    ],
    "Variable" : [

    ],
    "stripped_doc" : [

    ],
    "type" : "Module",
    "desc" : "This module is used to create and manipulate touchbar item objects which can added to `hs._asm.undocumented.touchbar.bar` objects and displayed in the Touch Bar of new Macintosh Pro laptops or with the virtual Touch Bar provided by `hs._asm.undocumented.touchbar.virtual`.",
    "Deprecated" : [

    ],
    "Constructor" : [
      {
        "doc" : "Create a new group touchbarItem object which can contain other touchbar items.\n\nParameters:\n * `identifier` - An optional string specifying the identifier for this touchbar item. Must be unique within the bar the item will be assigned to if specified. If not specified, a new UUID is generated for the item.\n\nReturns:\n * a touchbarItemObject or nil if an error occurs",
        "stripped_doc" : [
          "Create a new group touchbarItem object which can contain other touchbar items.",
          ""
        ],
        "parameters" : [
          " * `identifier` - An optional string specifying the identifier for this touchbar item. Must be unique within the bar the item will be assigned to if specified. If not specified, a new UUID is generated for the item.",
          ""
        ],
        "name" : "newGroup",
        "notes" : [

        ],
        "signature" : "hs._asm.undocumented.touchbar.item.newGroup([title], [image], [identifier]) -> touchbarItemObject",
        "type" : "Constructor",
        "returns" : [
          " * a touchbarItemObject or nil if an error occurs"
        ],
        "def" : "hs._asm.undocumented.touchbar.item.newGroup([title], [image], [identifier]) -> touchbarItemObject",
        "desc" : "Create a new group touchbarItem object which can contain other touchbar items."
      },
      {
        "doc" : "Create a new slider touchbarItem object.\n\nParameters:\n * `identifier` - An optional string specifying the identifier for this touchbar item. Must be unique within the bar the item will be assigned to if specified. If not specified, a new UUID is generated for the item.\n\nReturns:\n * a touchbarItemObject or nil if an error occurs\n\nNotes:\n * The slider object will expand to fill as much space as it can within the touchbar.",
        "stripped_doc" : [
          "Create a new slider touchbarItem object.",
          ""
        ],
        "parameters" : [
          " * `identifier` - An optional string specifying the identifier for this touchbar item. Must be unique within the bar the item will be assigned to if specified. If not specified, a new UUID is generated for the item.",
          ""
        ],
        "name" : "newSlider",
        "notes" : [
          " * The slider object will expand to fill as much space as it can within the touchbar."
        ],
        "signature" : "hs._asm.undocumented.touchbar.item.newSlider([identifier]) -> touchbarItemObject",
        "type" : "Constructor",
        "returns" : [
          " * a touchbarItemObject or nil if an error occurs",
          ""
        ],
        "def" : "hs._asm.undocumented.touchbar.item.newSlider([identifier]) -> touchbarItemObject",
        "desc" : "Create a new slider touchbarItem object."
      },
      {
        "doc" : "Create a new touchbarItem object from an `hs.canvas` object..\n\nParameters:\n * `canvas`     - The `hs.canvas` object to use as a touchbar item.\n * `identifier` - An optional string specifying the identifier for this touchbar item. Must be unique within the bar the item will be assigned to if specified. If not specified, a new UUID is generated for the item.\n\nReturns:\n * a touchbarItemObject or nil if an error occurs\n\nNotes:\n * The touch bar object will be proportionally resized so that it has the same height as the touchbar if it does not already. Currently this is 30, but in case future models differ from this, you can get the current value with from `hs._asm.undocumented.touchbar.size`.\n * If canvas callbacks for `mouseDown`, `mouseUp`, `mouseEnterExit`, and `mouseMove` are enabled, the canvas callback will be invoked as if the left mouse button had been used.",
        "stripped_doc" : [
          "Create a new touchbarItem object from an `hs.canvas` object..",
          ""
        ],
        "parameters" : [
          " * `canvas`     - The `hs.canvas` object to use as a touchbar item.",
          " * `identifier` - An optional string specifying the identifier for this touchbar item. Must be unique within the bar the item will be assigned to if specified. If not specified, a new UUID is generated for the item.",
          ""
        ],
        "name" : "newCanvas",
        "notes" : [
          " * The touch bar object will be proportionally resized so that it has the same height as the touchbar if it does not already. Currently this is 30, but in case future models differ from this, you can get the current value with from `hs._asm.undocumented.touchbar.size`.",
          " * If canvas callbacks for `mouseDown`, `mouseUp`, `mouseEnterExit`, and `mouseMove` are enabled, the canvas callback will be invoked as if the left mouse button had been used."
        ],
        "signature" : "hs._asm.undocumented.touchbar.item.newCanvas(canvas, [identifier]) -> touchbarItemObject",
        "type" : "Constructor",
        "returns" : [
          " * a touchbarItemObject or nil if an error occurs",
          ""
        ],
        "def" : "hs._asm.undocumented.touchbar.item.newCanvas(canvas, [identifier]) -> touchbarItemObject",
        "desc" : "Create a new touchbarItem object from an `hs.canvas` object.."
      },
      {
        "doc" : "Create a new button touchbarItem object.\n\nParameters:\n * `title`      - A string specifying the title for the button. Optional if `image` is specified.\n * `image`      - An `hs.image` object specifying the image for the button.  Optional is `title` is specified.\n * `identifier` - An optional string specifying the identifier for this touchbar item. Must be unique within the bar the item will be assigned to if specified. If not specified, a new UUID is generated for the item.\n\nReturns:\n * a touchbarItemObject or nil if an error occurs\n\nNotes:\n * You can change the button's title with [hs._asm.undocumented.touchbar.item:title](#title) only if you initially assign one with this constructor.\n * You can change the button's image with [hs._asm.undocumented.touchbar.item:image](#title) only if you initially assign one with this constructor.\n * If you intend to allow customization of the touch bar, it is highly recommended that you specify an identifier, since the UUID will change each time the item is regenerated (when Hammerspoon reloads or restarts).",
        "stripped_doc" : [
          "Create a new button touchbarItem object.",
          ""
        ],
        "parameters" : [
          " * `title`      - A string specifying the title for the button. Optional if `image` is specified.",
          " * `image`      - An `hs.image` object specifying the image for the button.  Optional is `title` is specified.",
          " * `identifier` - An optional string specifying the identifier for this touchbar item. Must be unique within the bar the item will be assigned to if specified. If not specified, a new UUID is generated for the item.",
          ""
        ],
        "name" : "newButton",
        "notes" : [
          " * You can change the button's title with [hs._asm.undocumented.touchbar.item:title](#title) only if you initially assign one with this constructor.",
          " * You can change the button's image with [hs._asm.undocumented.touchbar.item:image](#title) only if you initially assign one with this constructor.",
          " * If you intend to allow customization of the touch bar, it is highly recommended that you specify an identifier, since the UUID will change each time the item is regenerated (when Hammerspoon reloads or restarts)."
        ],
        "signature" : "hs._asm.undocumented.touchbar.item.newButton([title], [image], [identifier]) -> touchbarItemObject",
        "type" : "Constructor",
        "returns" : [
          " * a touchbarItemObject or nil if an error occurs",
          ""
        ],
        "def" : "hs._asm.undocumented.touchbar.item.newButton([title], [image], [identifier]) -> touchbarItemObject",
        "desc" : "Create a new button touchbarItem object."
      }
    ],
    "doc" : "This module is used to create and manipulate touchbar item objects which can added to `hs._asm.undocumented.touchbar.bar` objects and displayed in the Touch Bar of new Macintosh Pro laptops or with the virtual Touch Bar provided by `hs._asm.undocumented.touchbar.virtual`.\n\nAt present, only simple button type items are supported.\n\nThis module is very experimental and is still under development, so the exact functions and methods may be subject to change without notice.\n\nThis module is based partially on some of the code examples and links referred to in the discussion at https:\/\/github.com\/Hammerspoon\/hammerspoon\/issues\/1096.",
    "Method" : [
      {
        "doc" : "Presents a bar in the touch bar display modally and hides this item if it is present in the System Tray of the touch bar display.\n\nParameters:\n * `touchbar` - An `hs._asm.undocumented.touchbar.bar` object of the bar to display modally in the touch bar display.\n * `dismissButton` - an optional boolean, default true, specifying whether or not the system escape (or its current replacement) button should be replaced by a button to remove the modal bar from the touch bar display when pressed.\n\nReturns:\n * the touchbarItem object\n\nNotes:\n * If you specify `dismissButton` as false, then you must use `hs._asm.undocumented.touchbar.bar:minimizeModalBar` or `hs._asm.undocumented.touchbar.bar:dismissModalBar` to remove the modal bar from the touch bar display.\n   * Use `hs._asm.undocumented.touchbar.bar:minimizeModalBar` if you want the item to reappear in the System Tray (if it was present before displaying the bar).\n\n * If you do not have \"Touch Bar Shows\" set to \"App Controls With Control Strip\" set in the Keyboard System Preferences, the modal bar will only be displayed when the Hammerspoon application is the frontmost application.\n\n * This method is actually a wrapper to `hs._asm.undocumented.touchbar.bar:presentModalBar` provided for convenience.\n\n * This method uses undocumented functions and\/or framework methods and is not guaranteed to work with future updates to macOS. It has currently been tested with 10.12.6.",
        "stripped_doc" : [
          "Presents a bar in the touch bar display modally and hides this item if it is present in the System Tray of the touch bar display.",
          ""
        ],
        "parameters" : [
          " * `touchbar` - An `hs._asm.undocumented.touchbar.bar` object of the bar to display modally in the touch bar display.",
          " * `dismissButton` - an optional boolean, default true, specifying whether or not the system escape (or its current replacement) button should be replaced by a button to remove the modal bar from the touch bar display when pressed.",
          ""
        ],
        "name" : "presentModalBar",
        "notes" : [
          " * If you specify `dismissButton` as false, then you must use `hs._asm.undocumented.touchbar.bar:minimizeModalBar` or `hs._asm.undocumented.touchbar.bar:dismissModalBar` to remove the modal bar from the touch bar display.",
          "   * Use `hs._asm.undocumented.touchbar.bar:minimizeModalBar` if you want the item to reappear in the System Tray (if it was present before displaying the bar).",
          "",
          " * If you do not have \"Touch Bar Shows\" set to \"App Controls With Control Strip\" set in the Keyboard System Preferences, the modal bar will only be displayed when the Hammerspoon application is the frontmost application.",
          "",
          " * This method is actually a wrapper to `hs._asm.undocumented.touchbar.bar:presentModalBar` provided for convenience.",
          "",
          " * This method uses undocumented functions and\/or framework methods and is not guaranteed to work with future updates to macOS. It has currently been tested with 10.12.6."
        ],
        "signature" : "hs._asm.undocumented.touchbar.item:presentModalBar(touchbar, [dismissButton]) -> touchbarItemObject",
        "type" : "Method",
        "returns" : [
          " * the touchbarItem object",
          ""
        ],
        "def" : "hs._asm.undocumented.touchbar.item:presentModalBar(touchbar, [dismissButton]) -> touchbarItemObject",
        "desc" : "Presents a bar in the touch bar display modally and hides this item if it is present in the System Tray of the touch bar display."
      },
      {
        "doc" : "Get or set the touchbar item objects which belong to this group touchbar item.\n\nParameters:\n * `itemsTable` - an optional table as an array of touchbar item objects to display when this group touchbar item is present in the touchbar.\n\nReturns:\n * if an argument is provided, returns the touchbarItem object; otherwise returns the current value\n\nNotes:\n * This method will generate an error if the touchbar item was not created with the [hs._asm.undocumented.touchbar.item.newGroup](#newGroup) constructor.\n * The group touchbar item's callback, if set, is never invoked; instead the callback for the items within the group item is invoked when the item is touched.\n * This is a convenience method which creates an `hs._asm.undocumented.touchbar.bar` object and uses [hs._asm.undocumented.touchbar.item:groupTouchbar](#groupTouchbar) to assign the items to the group item.",
        "stripped_doc" : [
          "Get or set the touchbar item objects which belong to this group touchbar item.",
          ""
        ],
        "parameters" : [
          " * `itemsTable` - an optional table as an array of touchbar item objects to display when this group touchbar item is present in the touchbar.",
          ""
        ],
        "name" : "groupItems",
        "notes" : [
          " * This method will generate an error if the touchbar item was not created with the [hs._asm.undocumented.touchbar.item.newGroup](#newGroup) constructor.",
          " * The group touchbar item's callback, if set, is never invoked; instead the callback for the items within the group item is invoked when the item is touched.",
          " * This is a convenience method which creates an `hs._asm.undocumented.touchbar.bar` object and uses [hs._asm.undocumented.touchbar.item:groupTouchbar](#groupTouchbar) to assign the items to the group item."
        ],
        "signature" : "hs._asm.undocumented.touchbar.item:groupItems([itemsTable]) -> touchbarItemObject | current value",
        "type" : "Method",
        "returns" : [
          " * if an argument is provided, returns the touchbarItem object; otherwise returns the current value",
          ""
        ],
        "def" : "hs._asm.undocumented.touchbar.item:groupItems([itemsTable]) -> touchbarItemObject | current value",
        "desc" : "Get or set the touchbar item objects which belong to this group touchbar item."
      },
      {
        "doc" : "Get or set the visibility callback function for the touchbar item object.\n\nParameters:\n * `fn` - an optional function, or explicit nil to remove, specifying the visibility callback for the touchbar item object.\n\nReturns:\n * if an argument is provided, returns the touchbarItem object; otherwise returns the current value\n\nNotes:\n * The callback function should expect two arguments, the touchbarItem itself and a boolean indicating the new visibility of the item.  It should return none.\n\n * See also the notes for [hs._asm.undocumented.touchbar.item:isVisible](#isVisible) and `hs._asm.undocumented.touchbar.bar.visibilityCallback`.",
        "stripped_doc" : [
          "Get or set the visibility callback function for the touchbar item object.",
          ""
        ],
        "parameters" : [
          " * `fn` - an optional function, or explicit nil to remove, specifying the visibility callback for the touchbar item object.",
          ""
        ],
        "name" : "visibilityCallback",
        "notes" : [
          " * The callback function should expect two arguments, the touchbarItem itself and a boolean indicating the new visibility of the item.  It should return none.",
          "",
          " * See also the notes for [hs._asm.undocumented.touchbar.item:isVisible](#isVisible) and `hs._asm.undocumented.touchbar.bar.visibilityCallback`."
        ],
        "signature" : "hs._asm.undocumented.touchbar.item:visibilityCallback([fn | nil]) -> touchbarItemObject | current value",
        "type" : "Method",
        "returns" : [
          " * if an argument is provided, returns the touchbarItem object; otherwise returns the current value",
          ""
        ],
        "def" : "hs._asm.undocumented.touchbar.item:visibilityCallback([fn | nil]) -> touchbarItemObject | current value",
        "desc" : "Get or set the visibility callback function for the touchbar item object."
      },
      {
        "doc" : "Get or set the image displayed at the left side of a slider touchbar item.\n\nParameters:\n * `image` - an optional image, or explicit nil to remove, specifying the image to be displayed at the left side of a slider touchbar item.  Defaults to nil.\n\nReturns:\n * if an argument is provided, returns the touchbarItem object; otherwise returns the current value\n\nNotes:\n * This method will generate an error if the touchbar item was not created with the [hs._asm.undocumented.touchbar.item.newSlider](#newSlider) constructor.\n * When this image is clicked on, the touchbar item's callback, if set, will receive the string \"minimum\" as it's second argument.",
        "stripped_doc" : [
          "Get or set the image displayed at the left side of a slider touchbar item.",
          ""
        ],
        "parameters" : [
          " * `image` - an optional image, or explicit nil to remove, specifying the image to be displayed at the left side of a slider touchbar item.  Defaults to nil.",
          ""
        ],
        "name" : "sliderMinImage",
        "notes" : [
          " * This method will generate an error if the touchbar item was not created with the [hs._asm.undocumented.touchbar.item.newSlider](#newSlider) constructor.",
          " * When this image is clicked on, the touchbar item's callback, if set, will receive the string \"minimum\" as it's second argument."
        ],
        "signature" : "hs._asm.undocumented.touchbar.item:sliderMinImage([image]) -> touchbarItemObject | current value",
        "type" : "Method",
        "returns" : [
          " * if an argument is provided, returns the touchbarItem object; otherwise returns the current value",
          ""
        ],
        "def" : "hs._asm.undocumented.touchbar.item:sliderMinImage([image]) -> touchbarItemObject | current value",
        "desc" : "Get or set the image displayed at the left side of a slider touchbar item."
      },
      {
        "doc" : "Get or set the image displayed at the right side of a slider touchbar item.\n\nParameters:\n * `image` - an optional image, or explicit nil to remove, specifying the image to be displayed at the right side of a slider touchbar item.  Defaults to nil.\n\nReturns:\n * if an argument is provided, returns the touchbarItem object; otherwise returns the current value\n\nNotes:\n * This method will generate an error if the touchbar item was not created with the [hs._asm.undocumented.touchbar.item.newSlider](#newSlider) constructor.\n * When this image is clicked on, the touchbar item's callback, if set, will receive the string \"maximum\" as it's second argument.",
        "stripped_doc" : [
          "Get or set the image displayed at the right side of a slider touchbar item.",
          ""
        ],
        "parameters" : [
          " * `image` - an optional image, or explicit nil to remove, specifying the image to be displayed at the right side of a slider touchbar item.  Defaults to nil.",
          ""
        ],
        "name" : "sliderMaxImage",
        "notes" : [
          " * This method will generate an error if the touchbar item was not created with the [hs._asm.undocumented.touchbar.item.newSlider](#newSlider) constructor.",
          " * When this image is clicked on, the touchbar item's callback, if set, will receive the string \"maximum\" as it's second argument."
        ],
        "signature" : "hs._asm.undocumented.touchbar.item:sliderMaxImage([image]) -> touchbarItemObject | current value",
        "type" : "Method",
        "returns" : [
          " * if an argument is provided, returns the touchbarItem object; otherwise returns the current value",
          ""
        ],
        "def" : "hs._asm.undocumented.touchbar.item:sliderMaxImage([image]) -> touchbarItemObject | current value",
        "desc" : "Get or set the image displayed at the right side of a slider touchbar item."
      },
      {
        "doc" : "Get or set the minimum value for a slider touchbar item.\n\nParameters:\n * `value` - an optional number specifying the minimum value for a slider touchbar item. This represents the slider's value when the knob of the slider is all the way to the left. Defaults to 0.0.\n\nReturns:\n * if an argument is provided, returns the touchbarItem object; otherwise returns the current value\n\nNotes:\n * This method will generate an error if the touchbar item was not created with the [hs._asm.undocumented.touchbar.item.newSlider](#newSlider) constructor.",
        "stripped_doc" : [
          "Get or set the minimum value for a slider touchbar item.",
          ""
        ],
        "parameters" : [
          " * `value` - an optional number specifying the minimum value for a slider touchbar item. This represents the slider's value when the knob of the slider is all the way to the left. Defaults to 0.0.",
          ""
        ],
        "name" : "sliderMin",
        "notes" : [
          " * This method will generate an error if the touchbar item was not created with the [hs._asm.undocumented.touchbar.item.newSlider](#newSlider) constructor."
        ],
        "signature" : "hs._asm.undocumented.touchbar.item:sliderMin([value]) -> touchbarItemObject | current value",
        "type" : "Method",
        "returns" : [
          " * if an argument is provided, returns the touchbarItem object; otherwise returns the current value",
          ""
        ],
        "def" : "hs._asm.undocumented.touchbar.item:sliderMin([value]) -> touchbarItemObject | current value",
        "desc" : "Get or set the minimum value for a slider touchbar item."
      },
      {
        "doc" : "Get or set the maximum value for a slider touchbar item.\n\nParameters:\n * `value` - an optional number specifying the maximum value for a slider touchbar item. This represents the slider's value when the knob of the slider is all the way to the right. Defaults to 1.0.\n\nReturns:\n * if an argument is provided, returns the touchbarItem object; otherwise returns the current value\n\nNotes:\n * This method will generate an error if the touchbar item was not created with the [hs._asm.undocumented.touchbar.item.newSlider](#newSlider) constructor.",
        "stripped_doc" : [
          "Get or set the maximum value for a slider touchbar item.",
          ""
        ],
        "parameters" : [
          " * `value` - an optional number specifying the maximum value for a slider touchbar item. This represents the slider's value when the knob of the slider is all the way to the right. Defaults to 1.0.",
          ""
        ],
        "name" : "sliderMax",
        "notes" : [
          " * This method will generate an error if the touchbar item was not created with the [hs._asm.undocumented.touchbar.item.newSlider](#newSlider) constructor."
        ],
        "signature" : "hs._asm.undocumented.touchbar.item:sliderMax([value]) -> touchbarItemObject | current value",
        "type" : "Method",
        "returns" : [
          " * if an argument is provided, returns the touchbarItem object; otherwise returns the current value",
          ""
        ],
        "def" : "hs._asm.undocumented.touchbar.item:sliderMax([value]) -> touchbarItemObject | current value",
        "desc" : "Get or set the maximum value for a slider touchbar item."
      },
      {
        "doc" : "Get or set the current value for a slider touchbar item.\n\nParameters:\n * `value` - an optional number specifying the value to set for the slider. This value will be automatically constrained to the current minimum and maximum as set by [hs._asm.undocumented.touchbar.item:sliderMin](#sliderMin) and [hs._asm.undocumented.touchbar.item:sliderMax](#sliderMax).\n\nReturns:\n * if an argument is provided, returns the touchbarItem object; otherwise returns the current value\n\nNotes:\n * This method will generate an error if the touchbar item was not created with the [hs._asm.undocumented.touchbar.item.newSlider](#newSlider) constructor.\n * The slider touchbar items callback, if set, will not be invoked if you use this method to change the slider's value.",
        "stripped_doc" : [
          "Get or set the current value for a slider touchbar item.",
          ""
        ],
        "parameters" : [
          " * `value` - an optional number specifying the value to set for the slider. This value will be automatically constrained to the current minimum and maximum as set by [hs._asm.undocumented.touchbar.item:sliderMin](#sliderMin) and [hs._asm.undocumented.touchbar.item:sliderMax](#sliderMax).",
          ""
        ],
        "name" : "sliderValue",
        "notes" : [
          " * This method will generate an error if the touchbar item was not created with the [hs._asm.undocumented.touchbar.item.newSlider](#newSlider) constructor.",
          " * The slider touchbar items callback, if set, will not be invoked if you use this method to change the slider's value."
        ],
        "signature" : "hs._asm.undocumented.touchbar.item:sliderValue([value]) -> touchbarItemObject | current value",
        "type" : "Method",
        "returns" : [
          " * if an argument is provided, returns the touchbarItem object; otherwise returns the current value",
          ""
        ],
        "def" : "hs._asm.undocumented.touchbar.item:sliderValue([value]) -> touchbarItemObject | current value",
        "desc" : "Get or set the current value for a slider touchbar item."
      },
      {
        "doc" : "Get or set the bar object which contains the touchbar items that belong to the group touchbar item.\n\nParameters:\n * `touchbar` - an optional `hs._asm.undocumented.touchbar.bar` object containing the touchbar items to display when this group touchbar item is present in the touchbar.\n\nReturns:\n * if an argument is provided, returns the touchbarItem object; otherwise returns the current value\n\nNotes:\n * This method will generate an error if the touchbar item was not created with the [hs._asm.undocumented.touchbar.item.newGroup](#newGroup) constructor.\n * The group touchbar item's callback, if set, is never invoked; instead the callback for the items within the group item is invoked when the item is touched.\n * See also [hs._asm.undocumented.touchbar.item:groupItems](#groupItems)",
        "stripped_doc" : [
          "Get or set the bar object which contains the touchbar items that belong to the group touchbar item.",
          ""
        ],
        "parameters" : [
          " * `touchbar` - an optional `hs._asm.undocumented.touchbar.bar` object containing the touchbar items to display when this group touchbar item is present in the touchbar.",
          ""
        ],
        "name" : "groupTouchbar",
        "notes" : [
          " * This method will generate an error if the touchbar item was not created with the [hs._asm.undocumented.touchbar.item.newGroup](#newGroup) constructor.",
          " * The group touchbar item's callback, if set, is never invoked; instead the callback for the items within the group item is invoked when the item is touched.",
          " * See also [hs._asm.undocumented.touchbar.item:groupItems](#groupItems)"
        ],
        "signature" : "hs._asm.undocumented.touchbar.item:groupTouchbar([touchbar]) -> touchbarItemObject | current value",
        "type" : "Method",
        "returns" : [
          " * if an argument is provided, returns the touchbarItem object; otherwise returns the current value",
          ""
        ],
        "def" : "hs._asm.undocumented.touchbar.item:groupTouchbar([touchbar]) -> touchbarItemObject | current value",
        "desc" : "Get or set the bar object which contains the touchbar items that belong to the group touchbar item."
      },
      {
        "doc" : "Get or set the label displayed for the item when the customization panel is being displayed for the touch bar.\n\nParameters:\n * `label` - an optional string, or explicit nil to reset to an empty string, specifying the label to be displayed with the item when the customization panel is being displayed for the touch bar.  Defaults to an empty string.\n\nReturns:\n * if an argument is provided, returns the touchbarItem object; otherwise returns the current value",
        "stripped_doc" : [
          "Get or set the label displayed for the item when the customization panel is being displayed for the touch bar.",
          ""
        ],
        "parameters" : [
          " * `label` - an optional string, or explicit nil to reset to an empty string, specifying the label to be displayed with the item when the customization panel is being displayed for the touch bar.  Defaults to an empty string.",
          ""
        ],
        "name" : "customizationLabel",
        "notes" : [

        ],
        "signature" : "hs._asm.undocumented.touchbar.item:customizationLabel([label]) -> touchbarItemObject | current value",
        "type" : "Method",
        "returns" : [
          " * if an argument is provided, returns the touchbarItem object; otherwise returns the current value"
        ],
        "def" : "hs._asm.undocumented.touchbar.item:customizationLabel([label]) -> touchbarItemObject | current value",
        "desc" : "Get or set the label displayed for the item when the customization panel is being displayed for the touch bar."
      },
      {
        "doc" : "Get or set the image for a button item which was initially given an image when created.\n\nParameters:\n * `image` - an optional `hs.image` object, or explicit nil, specifying the image for the button item.\n\nReturns:\n * if an argument is provided, returns the touchbarItem object; otherwise returns the current value\n\nNotes:\n * This method will generate an error if the touchbar item was not created with the [hs._asm.undocumented.touchbar.item.newButton](#newButton) constructor.\n * This method will generate an error if an image was not provided when the object was created.\n * Setting the image to nil will remove the image and shrink the button, but not as tightly as the button would appear if it had been initially created without an image at all.",
        "stripped_doc" : [
          "Get or set the image for a button item which was initially given an image when created.",
          ""
        ],
        "parameters" : [
          " * `image` - an optional `hs.image` object, or explicit nil, specifying the image for the button item.",
          ""
        ],
        "name" : "buttonImage",
        "notes" : [
          " * This method will generate an error if the touchbar item was not created with the [hs._asm.undocumented.touchbar.item.newButton](#newButton) constructor.",
          " * This method will generate an error if an image was not provided when the object was created.",
          " * Setting the image to nil will remove the image and shrink the button, but not as tightly as the button would appear if it had been initially created without an image at all."
        ],
        "signature" : "hs._asm.undocumented.touchbar.item:buttonImage([image]) -> touchbarItemObject | hs.image object",
        "type" : "Method",
        "returns" : [
          " * if an argument is provided, returns the touchbarItem object; otherwise returns the current value",
          ""
        ],
        "def" : "hs._asm.undocumented.touchbar.item:buttonImage([image]) -> touchbarItemObject | hs.image object",
        "desc" : "Get or set the image for a button item which was initially given an image when created."
      },
      {
        "doc" : "Get or set the title for a button item which was initially given a title when created.\n\nParameters:\n * `title` - an optional string, or explicit nil, specifying the title for the button item.\n\nReturns:\n * if an argument is provided, returns the touchbarItem object; otherwise returns the current value\n\nNotes:\n * This method will generate an error if the touchbar item was not created with the [hs._asm.undocumented.touchbar.item.newButton](#newButton) constructor.\n * This method will generate an error if a title was not provided when the object was created.\n * Setting the title to nil will remove the title and shrink the button, but not as tightly as the button would appear if it had been initially created without a title at all.",
        "stripped_doc" : [
          "Get or set the title for a button item which was initially given a title when created.",
          ""
        ],
        "parameters" : [
          " * `title` - an optional string, or explicit nil, specifying the title for the button item.",
          ""
        ],
        "name" : "buttonTitle",
        "notes" : [
          " * This method will generate an error if the touchbar item was not created with the [hs._asm.undocumented.touchbar.item.newButton](#newButton) constructor.",
          " * This method will generate an error if a title was not provided when the object was created.",
          " * Setting the title to nil will remove the title and shrink the button, but not as tightly as the button would appear if it had been initially created without a title at all."
        ],
        "signature" : "hs._asm.undocumented.touchbar.item:buttonTitle([title]) -> touchbarItemObject | current value",
        "type" : "Method",
        "returns" : [
          " * if an argument is provided, returns the touchbarItem object; otherwise returns the current value",
          ""
        ],
        "def" : "hs._asm.undocumented.touchbar.item:buttonTitle([title]) -> touchbarItemObject | current value",
        "desc" : "Get or set the title for a button item which was initially given a title when created."
      },
      {
        "doc" : "Get or set the width of a canvas touchbar item in the touchbar.\n\nParameters:\n * `width` - an optional number specifying the width of the canvas touchbar item in the touchbar.\n\nReturns:\n * if an argument is provided, returns the touchbarItem object; otherwise returns the current value\n\nNotes:\n * This method will generate an error if the touchbar item was not created with the [hs._asm.undocumented.touchbar.item.newCanvas](#newCanvas) constructor.",
        "stripped_doc" : [
          "Get or set the width of a canvas touchbar item in the touchbar.",
          ""
        ],
        "parameters" : [
          " * `width` - an optional number specifying the width of the canvas touchbar item in the touchbar.",
          ""
        ],
        "name" : "canvasWidth",
        "notes" : [
          " * This method will generate an error if the touchbar item was not created with the [hs._asm.undocumented.touchbar.item.newCanvas](#newCanvas) constructor."
        ],
        "signature" : "hs._asm.undocumented.touchbar.item:canvasWidth([width]) -> touchbarItemObject | current value",
        "type" : "Method",
        "returns" : [
          " * if an argument is provided, returns the touchbarItem object; otherwise returns the current value",
          ""
        ],
        "def" : "hs._asm.undocumented.touchbar.item:canvasWidth([width]) -> touchbarItemObject | current value",
        "desc" : "Get or set the width of a canvas touchbar item in the touchbar."
      },
      {
        "doc" : "Get or set the background color displayed when a canvas touchbar item is currently being touched.\n\nParameters:\n * `color` - an optional table specifying a color as defined in the `hs.drawing.color` module, or an explicit nil to reset it to the default. Defaults to the macOS System Selected Control Color (`hs.drawing.color.colorsFor(\"System\")[\"selectedControlColor\"]`).\n\nReturns:\n * if an argument is provided, returns the touchbarItem object; otherwise returns the current value\n\nNotes:\n * This method will generate an error if the touchbar item was not created with the [hs._asm.undocumented.touchbar.item.newCanvas](#newCanvas) constructor.\n * To specify that no background color should be displayed when the canvas touchbar item is in an active state, specify a color with an alpha value of 0, e.g. `{ alpha = 0 }`.",
        "stripped_doc" : [
          "Get or set the background color displayed when a canvas touchbar item is currently being touched.",
          ""
        ],
        "parameters" : [
          " * `color` - an optional table specifying a color as defined in the `hs.drawing.color` module, or an explicit nil to reset it to the default. Defaults to the macOS System Selected Control Color (`hs.drawing.color.colorsFor(\"System\")[\"selectedControlColor\"]`).",
          ""
        ],
        "name" : "canvasClickColor",
        "notes" : [
          " * This method will generate an error if the touchbar item was not created with the [hs._asm.undocumented.touchbar.item.newCanvas](#newCanvas) constructor.",
          " * To specify that no background color should be displayed when the canvas touchbar item is in an active state, specify a color with an alpha value of 0, e.g. `{ alpha = 0 }`."
        ],
        "signature" : "hs._asm.undocumented.touchbar.item:canvasClickColor([color]) -> touchbarItemObject | current value",
        "type" : "Method",
        "returns" : [
          " * if an argument is provided, returns the touchbarItem object; otherwise returns the current value",
          ""
        ],
        "def" : "hs._asm.undocumented.touchbar.item:canvasClickColor([color]) -> touchbarItemObject | current value",
        "desc" : "Get or set the background color displayed when a canvas touchbar item is currently being touched."
      },
      {
        "doc" : "Get or set whether the touchbar item is enabled (accepting touches) or disabled.\n\nParameters:\n * `state` - an optional boolean, default true, specifying whether or not the touchbar item is currently enabled.\n\nReturns:\n * if an argument is provided, returns the touchbarItem object; otherwise returns the current value\n\nNotes:\n * This method will generate an error if the touchbar item was not created with the [hs._asm.undocumented.touchbar.item.newButton](#newButton) or [hs._asm.undocumented.touchbar.item.newCanvas](#newCanvas) constructors.",
        "stripped_doc" : [
          "Get or set whether the touchbar item is enabled (accepting touches) or disabled.",
          ""
        ],
        "parameters" : [
          " * `state` - an optional boolean, default true, specifying whether or not the touchbar item is currently enabled.",
          ""
        ],
        "name" : "enabled",
        "notes" : [
          " * This method will generate an error if the touchbar item was not created with the [hs._asm.undocumented.touchbar.item.newButton](#newButton) or [hs._asm.undocumented.touchbar.item.newCanvas](#newCanvas) constructors."
        ],
        "signature" : "hs._asm.undocumented.touchbar.item:enabled([state]) -> touchbarItemObject | current value",
        "type" : "Method",
        "returns" : [
          " * if an argument is provided, returns the touchbarItem object; otherwise returns the current value",
          ""
        ],
        "def" : "hs._asm.undocumented.touchbar.item:enabled([state]) -> touchbarItemObject | current value",
        "desc" : "Get or set whether the touchbar item is enabled (accepting touches) or disabled."
      },
      {
        "doc" : "Get or set the button touchbar item's button size.\n\nParameters:\n * `size` - an optional string, default \"regular\", specifying the button touchbar button size.  Must be one of \"regular\", \"small\", or \"mini\".\n\nReturns:\n * if an argument is provided, returns the touchbarItem object; otherwise returns the current value\n\nNotes:\n * This method will generate an error if the touchbar item was not created with the [hs._asm.undocumented.touchbar.item.newButton](#newButton) or [hs._asm.undocumented.touchbar.item.newCanvas](#newCanvas) constructors.\n * The button sizes are defined by the macOS operating system and under macOS 10.12 have the following visual effects (this may change with future macOS updates):\n   * `regular` - presents the button as a rounded grey rectangle with the image and\/or title inside of the grey area.\n   * `mini`    - presents the image and\/or title of the button without a rounded rectangle background. Takes up less space then `regular`.\n   * `small`   - presents the image and\/or title of the button without a rounded rectangle background. Takes up less space in the touchbar then `mini`.",
        "stripped_doc" : [
          "Get or set the button touchbar item's button size.",
          ""
        ],
        "parameters" : [
          " * `size` - an optional string, default \"regular\", specifying the button touchbar button size.  Must be one of \"regular\", \"small\", or \"mini\".",
          ""
        ],
        "name" : "buttonSize",
        "notes" : [
          " * This method will generate an error if the touchbar item was not created with the [hs._asm.undocumented.touchbar.item.newButton](#newButton) or [hs._asm.undocumented.touchbar.item.newCanvas](#newCanvas) constructors.",
          " * The button sizes are defined by the macOS operating system and under macOS 10.12 have the following visual effects (this may change with future macOS updates):",
          "   * `regular` - presents the button as a rounded grey rectangle with the image and\/or title inside of the grey area.",
          "   * `mini`    - presents the image and\/or title of the button without a rounded rectangle background. Takes up less space then `regular`.",
          "   * `small`   - presents the image and\/or title of the button without a rounded rectangle background. Takes up less space in the touchbar then `mini`."
        ],
        "signature" : "hs._asm.undocumented.touchbar.item:buttonSize([size]) -> touchbarItemObject | current value",
        "type" : "Method",
        "returns" : [
          " * if an argument is provided, returns the touchbarItem object; otherwise returns the current value",
          ""
        ],
        "def" : "hs._asm.undocumented.touchbar.item:buttonSize([size]) -> touchbarItemObject | current value",
        "desc" : "Get or set the button touchbar item's button size."
      },
      {
        "doc" : "Returns the identifier for the touchbarItem object\n\nParameters:\n * None\n\nReturns:\n * the identifier for the item as a string",
        "stripped_doc" : [
          "Returns the identifier for the touchbarItem object",
          ""
        ],
        "parameters" : [
          " * None",
          ""
        ],
        "name" : "identifier",
        "notes" : [

        ],
        "signature" : "hs._asm.undocumented.touchbar.item:identifier() -> string",
        "type" : "Method",
        "returns" : [
          " * the identifier for the item as a string"
        ],
        "def" : "hs._asm.undocumented.touchbar.item:identifier() -> string",
        "desc" : "Returns the identifier for the touchbarItem object"
      },
      {
        "doc" : "Returns the type of the touchbar item as a string.\n\nParameters:\n * None\n\nReturns:\n * the type of the touchbar item as one of the following strings: \"buttonWithText\", \"buttonWithImage\", \"buttonWithImageAndText\", \"group\", \"slider\", or \"canvas\".\n\nNotes:\n * other types may be added in future updates.",
        "stripped_doc" : [
          "Returns the type of the touchbar item as a string.",
          ""
        ],
        "parameters" : [
          " * None",
          ""
        ],
        "name" : "itemType",
        "notes" : [
          " * other types may be added in future updates."
        ],
        "signature" : "hs._asm.undocumented.touchbar.item:itemType() -> string",
        "type" : "Method",
        "returns" : [
          " * the type of the touchbar item as one of the following strings: \"buttonWithText\", \"buttonWithImage\", \"buttonWithImageAndText\", \"group\", \"slider\", or \"canvas\".",
          ""
        ],
        "def" : "hs._asm.undocumented.touchbar.item:itemType() -> string",
        "desc" : "Returns the type of the touchbar item as a string."
      },
      {
        "doc" : "Returns a boolean indicating whether or not the item is currently visible in the bar that it is assigned to.\n\nParameters:\n * None\n\nReturns:\n * a boolean specifying whether or not the item is currently visible in the bar that it is assigned to.\n\nNotes:\n * If the bar that the item is assigned to has been visible at some point in the past, and the item was visible at that time, this method will return true even if the bar is not currently visible. If you want to know if the item is visible in the touch bar display *right now*, you should use `reallyVisible = bar:isVisible() and item:isVisible()`",
        "stripped_doc" : [
          "Returns a boolean indicating whether or not the item is currently visible in the bar that it is assigned to.",
          ""
        ],
        "parameters" : [
          " * None",
          ""
        ],
        "name" : "isVisible",
        "notes" : [
          " * If the bar that the item is assigned to has been visible at some point in the past, and the item was visible at that time, this method will return true even if the bar is not currently visible. If you want to know if the item is visible in the touch bar display *right now*, you should use `reallyVisible = bar:isVisible() and item:isVisible()`"
        ],
        "signature" : "hs._asm.undocumented.touchbar.item:isVisible() -> boolean",
        "type" : "Method",
        "returns" : [
          " * a boolean specifying whether or not the item is currently visible in the bar that it is assigned to.",
          ""
        ],
        "def" : "hs._asm.undocumented.touchbar.item:isVisible() -> boolean",
        "desc" : "Returns a boolean indicating whether or not the item is currently visible in the bar that it is assigned to."
      },
      {
        "doc" : "Get or set the visibility priority for the touchbar item.\n\nParameters:\n * `priority` - an optional number specifying the visibility priority for the item.\n\nReturns:\n * if an argument is provided, returns the touchbarItem object; otherwise returns the current value\n\nNotes:\n * If their are more items to be presented in the touch bar display than space permits, items with a lower visibility priority will be hidden first.\n * Some predefined visibility values are defined in [hs._asm.undocumented.touchbar.item.visibilityPriorities](#visibilityPriorities), though others are allowed. The default priority for an item object is `hs._asm.undocumented.touchbar.item.visibilityPriorities.normal`.",
        "stripped_doc" : [
          "Get or set the visibility priority for the touchbar item.",
          ""
        ],
        "parameters" : [
          " * `priority` - an optional number specifying the visibility priority for the item.",
          ""
        ],
        "name" : "visibilityPriority",
        "notes" : [
          " * If their are more items to be presented in the touch bar display than space permits, items with a lower visibility priority will be hidden first.",
          " * Some predefined visibility values are defined in [hs._asm.undocumented.touchbar.item.visibilityPriorities](#visibilityPriorities), though others are allowed. The default priority for an item object is `hs._asm.undocumented.touchbar.item.visibilityPriorities.normal`."
        ],
        "signature" : "hs._asm.undocumented.touchbar.item:visibilityPriority([priority]) -> touchbarItemObject | current value",
        "type" : "Method",
        "returns" : [
          " * if an argument is provided, returns the touchbarItem object; otherwise returns the current value",
          ""
        ],
        "def" : "hs._asm.undocumented.touchbar.item:visibilityPriority([priority]) -> touchbarItemObject | current value",
        "desc" : "Get or set the visibility priority for the touchbar item."
      },
      {
        "doc" : "Get or set the callback function for the touchbar item.\n\nParameters:\n * `fn` - an optional function, or explicit nil to remove, specifying the callback to be invoked when the item is pressed.\n\nReturns:\n * if an argument is provided, returns the touchbarItem object; otherwise returns the current value\n\nNotes:\n * The callback function should return nothing. The arguments provided are type dependent, described here:\n   * Items constructed with [hs._asm.undocumented.touchbar.item.newButton](#newButton):\n     * the touchbar item itself\n\n   * Items constructed with [hs._asm.undocumented.touchbar.item.newCanvas](#newCanvas):\n     * the touchbar item itself\n   * Note that if you use `hs.canvas:canvasMouseEvents` and `hs.canvas:mouseCallback` on the canvas object, you can get `mouseDown`, `mouseUp`, `mouseEntered`, `mouseExited`, and `mouseMove` callbacks as if they were generated by the left mouse button.  You do not need to set a touchbar item callback to take advantage of the canvas callbacks.\n\n   * Items constructed with [hs._asm.undocumented.touchbar.item.newGroup](#newGroup):\n   * A callback assigned to a group touchbar item will never be invoked; instead if the items within the group have a callback assigned, the specific item within the group will have its callback invoked.\n\n   * Items constructed with [hs._asm.undocumented.touchbar.item.newSlider](#newSlider):\n     * the touchbar item itself\n     * a number or string as follows:\n       * if the image assigned with [hs._asm.undocumented.touchbar.item:sliderMinImage](#sliderMinImage) is touched, the string \"minimum\".\n       * if the image assigned with [hs._asm.undocumented.touchbar.item:sliderMaxImage](#sliderMaxImage) is touched, the string \"maximum\".\n       * if the slider knob is moved to a new position, returns a number between [hs._asm.undocumented.touchbar.item:sliderMin](#sliderMin) and [hs._asm.undocumented.touchbar.item:sliderMax](#sliderMax) indicating the new position.",
        "stripped_doc" : [
          "Get or set the callback function for the touchbar item.",
          ""
        ],
        "parameters" : [
          " * `fn` - an optional function, or explicit nil to remove, specifying the callback to be invoked when the item is pressed.",
          ""
        ],
        "name" : "callback",
        "notes" : [
          " * The callback function should return nothing. The arguments provided are type dependent, described here:",
          "   * Items constructed with [hs._asm.undocumented.touchbar.item.newButton](#newButton):",
          "     * the touchbar item itself",
          "",
          "   * Items constructed with [hs._asm.undocumented.touchbar.item.newCanvas](#newCanvas):",
          "     * the touchbar item itself",
          "   * Note that if you use `hs.canvas:canvasMouseEvents` and `hs.canvas:mouseCallback` on the canvas object, you can get `mouseDown`, `mouseUp`, `mouseEntered`, `mouseExited`, and `mouseMove` callbacks as if they were generated by the left mouse button.  You do not need to set a touchbar item callback to take advantage of the canvas callbacks.",
          "",
          "   * Items constructed with [hs._asm.undocumented.touchbar.item.newGroup](#newGroup):",
          "   * A callback assigned to a group touchbar item will never be invoked; instead if the items within the group have a callback assigned, the specific item within the group will have its callback invoked.",
          "",
          "   * Items constructed with [hs._asm.undocumented.touchbar.item.newSlider](#newSlider):",
          "     * the touchbar item itself",
          "     * a number or string as follows:",
          "       * if the image assigned with [hs._asm.undocumented.touchbar.item:sliderMinImage](#sliderMinImage) is touched, the string \"minimum\".",
          "       * if the image assigned with [hs._asm.undocumented.touchbar.item:sliderMaxImage](#sliderMaxImage) is touched, the string \"maximum\".",
          "       * if the slider knob is moved to a new position, returns a number between [hs._asm.undocumented.touchbar.item:sliderMin](#sliderMin) and [hs._asm.undocumented.touchbar.item:sliderMax](#sliderMax) indicating the new position."
        ],
        "signature" : "hs._asm.undocumented.touchbar.item:callback([fn | nil]) -> touchbarItemObject | current value",
        "type" : "Method",
        "returns" : [
          " * if an argument is provided, returns the touchbarItem object; otherwise returns the current value",
          ""
        ],
        "def" : "hs._asm.undocumented.touchbar.item:callback([fn | nil]) -> touchbarItemObject | current value",
        "desc" : "Get or set the callback function for the touchbar item."
      },
      {
        "doc" : "Add or remove the touchbar item from the System Tray in the touch bar display.\n\nParameters:\n * `state` - a boolean specifying if the item should be displayed in the System Tray (true) or not (false).\n\nReturns:\n * the touchbarItem object\n\nNotes:\n * The item will only be visible in the System Tray if you have \"Touch Bar Shows\" set to \"App Controls With Control Strip\" set in the Keyboard System Preferences.\n\n * Initial experiments suggest that only one item *from any macOS application currently running* may be added to the System Tray at a time.\n * Adding a new item will hide any previous item assigned; however they do appear to stack, so removing an existing item with this method, or if it has bar object attached with [hs._asm.undocumented.touchbar.item:presentModalBar](#presentModalBar) and you dismiss the bar with `hs._asm.undocumented.touchbar.bar:dismissModalBar`, the previous item should become visible again.\n\n * At present, there is no known way to determine which item is currently displayed in the System Tray or detect when a specific item is replaced ([hs._asm.undocumented.touchbar.item:isVisible](#isVisible) returns false). Please submit an issue if you know of a solution.\n\n * This method uses undocumented functions and\/or framework methods and is not guaranteed to work with future updates to macOS. It has currently been tested with 10.12.6.",
        "stripped_doc" : [
          "Add or remove the touchbar item from the System Tray in the touch bar display.",
          ""
        ],
        "parameters" : [
          " * `state` - a boolean specifying if the item should be displayed in the System Tray (true) or not (false).",
          ""
        ],
        "name" : "addToSystemTray",
        "notes" : [
          " * The item will only be visible in the System Tray if you have \"Touch Bar Shows\" set to \"App Controls With Control Strip\" set in the Keyboard System Preferences.",
          "",
          " * Initial experiments suggest that only one item *from any macOS application currently running* may be added to the System Tray at a time.",
          " * Adding a new item will hide any previous item assigned; however they do appear to stack, so removing an existing item with this method, or if it has bar object attached with [hs._asm.undocumented.touchbar.item:presentModalBar](#presentModalBar) and you dismiss the bar with `hs._asm.undocumented.touchbar.bar:dismissModalBar`, the previous item should become visible again.",
          "",
          " * At present, there is no known way to determine which item is currently displayed in the System Tray or detect when a specific item is replaced ([hs._asm.undocumented.touchbar.item:isVisible](#isVisible) returns false). Please submit an issue if you know of a solution.",
          "",
          " * This method uses undocumented functions and\/or framework methods and is not guaranteed to work with future updates to macOS. It has currently been tested with 10.12.6."
        ],
        "signature" : "hs._asm.undocumented.touchbar.item:addToSystemTray(state) -> touchbarItemObject",
        "type" : "Method",
        "returns" : [
          " * the touchbarItem object",
          ""
        ],
        "def" : "hs._asm.undocumented.touchbar.item:addToSystemTray(state) -> touchbarItemObject",
        "desc" : "Add or remove the touchbar item from the System Tray in the touch bar display."
      }
    ],
    "Command" : [

    ],
    "items" : [
      {
        "doc" : "Predefined visibility priorities for use with [hs._asm.undocumented.touchbar.item:visibilityPriority](#visibilityPriority)\n\nA table containing key-value pairs of predefined visibility priorities used when the touch bar isn't large enough to display all of the items which are eligible for presentation. Items with lower priorities are hidden first. These numbers are only suggestions and other numbers are also valid for use with [hs._asm.undocumented.touchbar.item:visibilityPriority](#visibilityPriority).\n\nPredefined values are as follows:\n * `low`   - -1000.0\n * `normal`-     0.0 (this is the default value assigned to an item when it is first created)\n * `high`  -  1000.0",
        "stripped_doc" : [
          "Predefined visibility priorities for use with [hs._asm.undocumented.touchbar.item:visibilityPriority](#visibilityPriority)",
          "",
          "A table containing key-value pairs of predefined visibility priorities used when the touch bar isn't large enough to display all of the items which are eligible for presentation. Items with lower priorities are hidden first. These numbers are only suggestions and other numbers are also valid for use with [hs._asm.undocumented.touchbar.item:visibilityPriority](#visibilityPriority).",
          "",
          "Predefined values are as follows:",
          " * `low`   - -1000.0",
          " * `normal`-     0.0 (this is the default value assigned to an item when it is first created)",
          " * `high`  -  1000.0"
        ],
        "parameters" : [

        ],
        "name" : "visibilityPriorities",
        "notes" : [

        ],
        "signature" : "hs._asm.undocumented.touchbar.item.visibilityPriorities[]",
        "type" : "Constant",
        "returns" : [

        ],
        "def" : "hs._asm.undocumented.touchbar.item.visibilityPriorities[]",
        "desc" : "Predefined visibility priorities for use with [hs._asm.undocumented.touchbar.item:visibilityPriority](#visibilityPriority)"
      },
      {
        "doc" : "Create a new button touchbarItem object.\n\nParameters:\n * `title`      - A string specifying the title for the button. Optional if `image` is specified.\n * `image`      - An `hs.image` object specifying the image for the button.  Optional is `title` is specified.\n * `identifier` - An optional string specifying the identifier for this touchbar item. Must be unique within the bar the item will be assigned to if specified. If not specified, a new UUID is generated for the item.\n\nReturns:\n * a touchbarItemObject or nil if an error occurs\n\nNotes:\n * You can change the button's title with [hs._asm.undocumented.touchbar.item:title](#title) only if you initially assign one with this constructor.\n * You can change the button's image with [hs._asm.undocumented.touchbar.item:image](#title) only if you initially assign one with this constructor.\n * If you intend to allow customization of the touch bar, it is highly recommended that you specify an identifier, since the UUID will change each time the item is regenerated (when Hammerspoon reloads or restarts).",
        "stripped_doc" : [
          "Create a new button touchbarItem object.",
          ""
        ],
        "parameters" : [
          " * `title`      - A string specifying the title for the button. Optional if `image` is specified.",
          " * `image`      - An `hs.image` object specifying the image for the button.  Optional is `title` is specified.",
          " * `identifier` - An optional string specifying the identifier for this touchbar item. Must be unique within the bar the item will be assigned to if specified. If not specified, a new UUID is generated for the item.",
          ""
        ],
        "name" : "newButton",
        "notes" : [
          " * You can change the button's title with [hs._asm.undocumented.touchbar.item:title](#title) only if you initially assign one with this constructor.",
          " * You can change the button's image with [hs._asm.undocumented.touchbar.item:image](#title) only if you initially assign one with this constructor.",
          " * If you intend to allow customization of the touch bar, it is highly recommended that you specify an identifier, since the UUID will change each time the item is regenerated (when Hammerspoon reloads or restarts)."
        ],
        "signature" : "hs._asm.undocumented.touchbar.item.newButton([title], [image], [identifier]) -> touchbarItemObject",
        "type" : "Constructor",
        "returns" : [
          " * a touchbarItemObject or nil if an error occurs",
          ""
        ],
        "def" : "hs._asm.undocumented.touchbar.item.newButton([title], [image], [identifier]) -> touchbarItemObject",
        "desc" : "Create a new button touchbarItem object."
      },
      {
        "doc" : "Create a new touchbarItem object from an `hs.canvas` object..\n\nParameters:\n * `canvas`     - The `hs.canvas` object to use as a touchbar item.\n * `identifier` - An optional string specifying the identifier for this touchbar item. Must be unique within the bar the item will be assigned to if specified. If not specified, a new UUID is generated for the item.\n\nReturns:\n * a touchbarItemObject or nil if an error occurs\n\nNotes:\n * The touch bar object will be proportionally resized so that it has the same height as the touchbar if it does not already. Currently this is 30, but in case future models differ from this, you can get the current value with from `hs._asm.undocumented.touchbar.size`.\n * If canvas callbacks for `mouseDown`, `mouseUp`, `mouseEnterExit`, and `mouseMove` are enabled, the canvas callback will be invoked as if the left mouse button had been used.",
        "stripped_doc" : [
          "Create a new touchbarItem object from an `hs.canvas` object..",
          ""
        ],
        "parameters" : [
          " * `canvas`     - The `hs.canvas` object to use as a touchbar item.",
          " * `identifier` - An optional string specifying the identifier for this touchbar item. Must be unique within the bar the item will be assigned to if specified. If not specified, a new UUID is generated for the item.",
          ""
        ],
        "name" : "newCanvas",
        "notes" : [
          " * The touch bar object will be proportionally resized so that it has the same height as the touchbar if it does not already. Currently this is 30, but in case future models differ from this, you can get the current value with from `hs._asm.undocumented.touchbar.size`.",
          " * If canvas callbacks for `mouseDown`, `mouseUp`, `mouseEnterExit`, and `mouseMove` are enabled, the canvas callback will be invoked as if the left mouse button had been used."
        ],
        "signature" : "hs._asm.undocumented.touchbar.item.newCanvas(canvas, [identifier]) -> touchbarItemObject",
        "type" : "Constructor",
        "returns" : [
          " * a touchbarItemObject or nil if an error occurs",
          ""
        ],
        "def" : "hs._asm.undocumented.touchbar.item.newCanvas(canvas, [identifier]) -> touchbarItemObject",
        "desc" : "Create a new touchbarItem object from an `hs.canvas` object.."
      },
      {
        "doc" : "Create a new group touchbarItem object which can contain other touchbar items.\n\nParameters:\n * `identifier` - An optional string specifying the identifier for this touchbar item. Must be unique within the bar the item will be assigned to if specified. If not specified, a new UUID is generated for the item.\n\nReturns:\n * a touchbarItemObject or nil if an error occurs",
        "stripped_doc" : [
          "Create a new group touchbarItem object which can contain other touchbar items.",
          ""
        ],
        "parameters" : [
          " * `identifier` - An optional string specifying the identifier for this touchbar item. Must be unique within the bar the item will be assigned to if specified. If not specified, a new UUID is generated for the item.",
          ""
        ],
        "name" : "newGroup",
        "notes" : [

        ],
        "signature" : "hs._asm.undocumented.touchbar.item.newGroup([title], [image], [identifier]) -> touchbarItemObject",
        "type" : "Constructor",
        "returns" : [
          " * a touchbarItemObject or nil if an error occurs"
        ],
        "def" : "hs._asm.undocumented.touchbar.item.newGroup([title], [image], [identifier]) -> touchbarItemObject",
        "desc" : "Create a new group touchbarItem object which can contain other touchbar items."
      },
      {
        "doc" : "Create a new slider touchbarItem object.\n\nParameters:\n * `identifier` - An optional string specifying the identifier for this touchbar item. Must be unique within the bar the item will be assigned to if specified. If not specified, a new UUID is generated for the item.\n\nReturns:\n * a touchbarItemObject or nil if an error occurs\n\nNotes:\n * The slider object will expand to fill as much space as it can within the touchbar.",
        "stripped_doc" : [
          "Create a new slider touchbarItem object.",
          ""
        ],
        "parameters" : [
          " * `identifier` - An optional string specifying the identifier for this touchbar item. Must be unique within the bar the item will be assigned to if specified. If not specified, a new UUID is generated for the item.",
          ""
        ],
        "name" : "newSlider",
        "notes" : [
          " * The slider object will expand to fill as much space as it can within the touchbar."
        ],
        "signature" : "hs._asm.undocumented.touchbar.item.newSlider([identifier]) -> touchbarItemObject",
        "type" : "Constructor",
        "returns" : [
          " * a touchbarItemObject or nil if an error occurs",
          ""
        ],
        "def" : "hs._asm.undocumented.touchbar.item.newSlider([identifier]) -> touchbarItemObject",
        "desc" : "Create a new slider touchbarItem object."
      },
      {
        "doc" : "Add or remove the touchbar item from the System Tray in the touch bar display.\n\nParameters:\n * `state` - a boolean specifying if the item should be displayed in the System Tray (true) or not (false).\n\nReturns:\n * the touchbarItem object\n\nNotes:\n * The item will only be visible in the System Tray if you have \"Touch Bar Shows\" set to \"App Controls With Control Strip\" set in the Keyboard System Preferences.\n\n * Initial experiments suggest that only one item *from any macOS application currently running* may be added to the System Tray at a time.\n * Adding a new item will hide any previous item assigned; however they do appear to stack, so removing an existing item with this method, or if it has bar object attached with [hs._asm.undocumented.touchbar.item:presentModalBar](#presentModalBar) and you dismiss the bar with `hs._asm.undocumented.touchbar.bar:dismissModalBar`, the previous item should become visible again.\n\n * At present, there is no known way to determine which item is currently displayed in the System Tray or detect when a specific item is replaced ([hs._asm.undocumented.touchbar.item:isVisible](#isVisible) returns false). Please submit an issue if you know of a solution.\n\n * This method uses undocumented functions and\/or framework methods and is not guaranteed to work with future updates to macOS. It has currently been tested with 10.12.6.",
        "stripped_doc" : [
          "Add or remove the touchbar item from the System Tray in the touch bar display.",
          ""
        ],
        "parameters" : [
          " * `state` - a boolean specifying if the item should be displayed in the System Tray (true) or not (false).",
          ""
        ],
        "name" : "addToSystemTray",
        "notes" : [
          " * The item will only be visible in the System Tray if you have \"Touch Bar Shows\" set to \"App Controls With Control Strip\" set in the Keyboard System Preferences.",
          "",
          " * Initial experiments suggest that only one item *from any macOS application currently running* may be added to the System Tray at a time.",
          " * Adding a new item will hide any previous item assigned; however they do appear to stack, so removing an existing item with this method, or if it has bar object attached with [hs._asm.undocumented.touchbar.item:presentModalBar](#presentModalBar) and you dismiss the bar with `hs._asm.undocumented.touchbar.bar:dismissModalBar`, the previous item should become visible again.",
          "",
          " * At present, there is no known way to determine which item is currently displayed in the System Tray or detect when a specific item is replaced ([hs._asm.undocumented.touchbar.item:isVisible](#isVisible) returns false). Please submit an issue if you know of a solution.",
          "",
          " * This method uses undocumented functions and\/or framework methods and is not guaranteed to work with future updates to macOS. It has currently been tested with 10.12.6."
        ],
        "signature" : "hs._asm.undocumented.touchbar.item:addToSystemTray(state) -> touchbarItemObject",
        "type" : "Method",
        "returns" : [
          " * the touchbarItem object",
          ""
        ],
        "def" : "hs._asm.undocumented.touchbar.item:addToSystemTray(state) -> touchbarItemObject",
        "desc" : "Add or remove the touchbar item from the System Tray in the touch bar display."
      },
      {
        "doc" : "Get or set the image for a button item which was initially given an image when created.\n\nParameters:\n * `image` - an optional `hs.image` object, or explicit nil, specifying the image for the button item.\n\nReturns:\n * if an argument is provided, returns the touchbarItem object; otherwise returns the current value\n\nNotes:\n * This method will generate an error if the touchbar item was not created with the [hs._asm.undocumented.touchbar.item.newButton](#newButton) constructor.\n * This method will generate an error if an image was not provided when the object was created.\n * Setting the image to nil will remove the image and shrink the button, but not as tightly as the button would appear if it had been initially created without an image at all.",
        "stripped_doc" : [
          "Get or set the image for a button item which was initially given an image when created.",
          ""
        ],
        "parameters" : [
          " * `image` - an optional `hs.image` object, or explicit nil, specifying the image for the button item.",
          ""
        ],
        "name" : "buttonImage",
        "notes" : [
          " * This method will generate an error if the touchbar item was not created with the [hs._asm.undocumented.touchbar.item.newButton](#newButton) constructor.",
          " * This method will generate an error if an image was not provided when the object was created.",
          " * Setting the image to nil will remove the image and shrink the button, but not as tightly as the button would appear if it had been initially created without an image at all."
        ],
        "signature" : "hs._asm.undocumented.touchbar.item:buttonImage([image]) -> touchbarItemObject | hs.image object",
        "type" : "Method",
        "returns" : [
          " * if an argument is provided, returns the touchbarItem object; otherwise returns the current value",
          ""
        ],
        "def" : "hs._asm.undocumented.touchbar.item:buttonImage([image]) -> touchbarItemObject | hs.image object",
        "desc" : "Get or set the image for a button item which was initially given an image when created."
      },
      {
        "doc" : "Get or set the button touchbar item's button size.\n\nParameters:\n * `size` - an optional string, default \"regular\", specifying the button touchbar button size.  Must be one of \"regular\", \"small\", or \"mini\".\n\nReturns:\n * if an argument is provided, returns the touchbarItem object; otherwise returns the current value\n\nNotes:\n * This method will generate an error if the touchbar item was not created with the [hs._asm.undocumented.touchbar.item.newButton](#newButton) or [hs._asm.undocumented.touchbar.item.newCanvas](#newCanvas) constructors.\n * The button sizes are defined by the macOS operating system and under macOS 10.12 have the following visual effects (this may change with future macOS updates):\n   * `regular` - presents the button as a rounded grey rectangle with the image and\/or title inside of the grey area.\n   * `mini`    - presents the image and\/or title of the button without a rounded rectangle background. Takes up less space then `regular`.\n   * `small`   - presents the image and\/or title of the button without a rounded rectangle background. Takes up less space in the touchbar then `mini`.",
        "stripped_doc" : [
          "Get or set the button touchbar item's button size.",
          ""
        ],
        "parameters" : [
          " * `size` - an optional string, default \"regular\", specifying the button touchbar button size.  Must be one of \"regular\", \"small\", or \"mini\".",
          ""
        ],
        "name" : "buttonSize",
        "notes" : [
          " * This method will generate an error if the touchbar item was not created with the [hs._asm.undocumented.touchbar.item.newButton](#newButton) or [hs._asm.undocumented.touchbar.item.newCanvas](#newCanvas) constructors.",
          " * The button sizes are defined by the macOS operating system and under macOS 10.12 have the following visual effects (this may change with future macOS updates):",
          "   * `regular` - presents the button as a rounded grey rectangle with the image and\/or title inside of the grey area.",
          "   * `mini`    - presents the image and\/or title of the button without a rounded rectangle background. Takes up less space then `regular`.",
          "   * `small`   - presents the image and\/or title of the button without a rounded rectangle background. Takes up less space in the touchbar then `mini`."
        ],
        "signature" : "hs._asm.undocumented.touchbar.item:buttonSize([size]) -> touchbarItemObject | current value",
        "type" : "Method",
        "returns" : [
          " * if an argument is provided, returns the touchbarItem object; otherwise returns the current value",
          ""
        ],
        "def" : "hs._asm.undocumented.touchbar.item:buttonSize([size]) -> touchbarItemObject | current value",
        "desc" : "Get or set the button touchbar item's button size."
      },
      {
        "doc" : "Get or set the title for a button item which was initially given a title when created.\n\nParameters:\n * `title` - an optional string, or explicit nil, specifying the title for the button item.\n\nReturns:\n * if an argument is provided, returns the touchbarItem object; otherwise returns the current value\n\nNotes:\n * This method will generate an error if the touchbar item was not created with the [hs._asm.undocumented.touchbar.item.newButton](#newButton) constructor.\n * This method will generate an error if a title was not provided when the object was created.\n * Setting the title to nil will remove the title and shrink the button, but not as tightly as the button would appear if it had been initially created without a title at all.",
        "stripped_doc" : [
          "Get or set the title for a button item which was initially given a title when created.",
          ""
        ],
        "parameters" : [
          " * `title` - an optional string, or explicit nil, specifying the title for the button item.",
          ""
        ],
        "name" : "buttonTitle",
        "notes" : [
          " * This method will generate an error if the touchbar item was not created with the [hs._asm.undocumented.touchbar.item.newButton](#newButton) constructor.",
          " * This method will generate an error if a title was not provided when the object was created.",
          " * Setting the title to nil will remove the title and shrink the button, but not as tightly as the button would appear if it had been initially created without a title at all."
        ],
        "signature" : "hs._asm.undocumented.touchbar.item:buttonTitle([title]) -> touchbarItemObject | current value",
        "type" : "Method",
        "returns" : [
          " * if an argument is provided, returns the touchbarItem object; otherwise returns the current value",
          ""
        ],
        "def" : "hs._asm.undocumented.touchbar.item:buttonTitle([title]) -> touchbarItemObject | current value",
        "desc" : "Get or set the title for a button item which was initially given a title when created."
      },
      {
        "doc" : "Get or set the callback function for the touchbar item.\n\nParameters:\n * `fn` - an optional function, or explicit nil to remove, specifying the callback to be invoked when the item is pressed.\n\nReturns:\n * if an argument is provided, returns the touchbarItem object; otherwise returns the current value\n\nNotes:\n * The callback function should return nothing. The arguments provided are type dependent, described here:\n   * Items constructed with [hs._asm.undocumented.touchbar.item.newButton](#newButton):\n     * the touchbar item itself\n\n   * Items constructed with [hs._asm.undocumented.touchbar.item.newCanvas](#newCanvas):\n     * the touchbar item itself\n   * Note that if you use `hs.canvas:canvasMouseEvents` and `hs.canvas:mouseCallback` on the canvas object, you can get `mouseDown`, `mouseUp`, `mouseEntered`, `mouseExited`, and `mouseMove` callbacks as if they were generated by the left mouse button.  You do not need to set a touchbar item callback to take advantage of the canvas callbacks.\n\n   * Items constructed with [hs._asm.undocumented.touchbar.item.newGroup](#newGroup):\n   * A callback assigned to a group touchbar item will never be invoked; instead if the items within the group have a callback assigned, the specific item within the group will have its callback invoked.\n\n   * Items constructed with [hs._asm.undocumented.touchbar.item.newSlider](#newSlider):\n     * the touchbar item itself\n     * a number or string as follows:\n       * if the image assigned with [hs._asm.undocumented.touchbar.item:sliderMinImage](#sliderMinImage) is touched, the string \"minimum\".\n       * if the image assigned with [hs._asm.undocumented.touchbar.item:sliderMaxImage](#sliderMaxImage) is touched, the string \"maximum\".\n       * if the slider knob is moved to a new position, returns a number between [hs._asm.undocumented.touchbar.item:sliderMin](#sliderMin) and [hs._asm.undocumented.touchbar.item:sliderMax](#sliderMax) indicating the new position.",
        "stripped_doc" : [
          "Get or set the callback function for the touchbar item.",
          ""
        ],
        "parameters" : [
          " * `fn` - an optional function, or explicit nil to remove, specifying the callback to be invoked when the item is pressed.",
          ""
        ],
        "name" : "callback",
        "notes" : [
          " * The callback function should return nothing. The arguments provided are type dependent, described here:",
          "   * Items constructed with [hs._asm.undocumented.touchbar.item.newButton](#newButton):",
          "     * the touchbar item itself",
          "",
          "   * Items constructed with [hs._asm.undocumented.touchbar.item.newCanvas](#newCanvas):",
          "     * the touchbar item itself",
          "   * Note that if you use `hs.canvas:canvasMouseEvents` and `hs.canvas:mouseCallback` on the canvas object, you can get `mouseDown`, `mouseUp`, `mouseEntered`, `mouseExited`, and `mouseMove` callbacks as if they were generated by the left mouse button.  You do not need to set a touchbar item callback to take advantage of the canvas callbacks.",
          "",
          "   * Items constructed with [hs._asm.undocumented.touchbar.item.newGroup](#newGroup):",
          "   * A callback assigned to a group touchbar item will never be invoked; instead if the items within the group have a callback assigned, the specific item within the group will have its callback invoked.",
          "",
          "   * Items constructed with [hs._asm.undocumented.touchbar.item.newSlider](#newSlider):",
          "     * the touchbar item itself",
          "     * a number or string as follows:",
          "       * if the image assigned with [hs._asm.undocumented.touchbar.item:sliderMinImage](#sliderMinImage) is touched, the string \"minimum\".",
          "       * if the image assigned with [hs._asm.undocumented.touchbar.item:sliderMaxImage](#sliderMaxImage) is touched, the string \"maximum\".",
          "       * if the slider knob is moved to a new position, returns a number between [hs._asm.undocumented.touchbar.item:sliderMin](#sliderMin) and [hs._asm.undocumented.touchbar.item:sliderMax](#sliderMax) indicating the new position."
        ],
        "signature" : "hs._asm.undocumented.touchbar.item:callback([fn | nil]) -> touchbarItemObject | current value",
        "type" : "Method",
        "returns" : [
          " * if an argument is provided, returns the touchbarItem object; otherwise returns the current value",
          ""
        ],
        "def" : "hs._asm.undocumented.touchbar.item:callback([fn | nil]) -> touchbarItemObject | current value",
        "desc" : "Get or set the callback function for the touchbar item."
      },
      {
        "doc" : "Get or set the background color displayed when a canvas touchbar item is currently being touched.\n\nParameters:\n * `color` - an optional table specifying a color as defined in the `hs.drawing.color` module, or an explicit nil to reset it to the default. Defaults to the macOS System Selected Control Color (`hs.drawing.color.colorsFor(\"System\")[\"selectedControlColor\"]`).\n\nReturns:\n * if an argument is provided, returns the touchbarItem object; otherwise returns the current value\n\nNotes:\n * This method will generate an error if the touchbar item was not created with the [hs._asm.undocumented.touchbar.item.newCanvas](#newCanvas) constructor.\n * To specify that no background color should be displayed when the canvas touchbar item is in an active state, specify a color with an alpha value of 0, e.g. `{ alpha = 0 }`.",
        "stripped_doc" : [
          "Get or set the background color displayed when a canvas touchbar item is currently being touched.",
          ""
        ],
        "parameters" : [
          " * `color` - an optional table specifying a color as defined in the `hs.drawing.color` module, or an explicit nil to reset it to the default. Defaults to the macOS System Selected Control Color (`hs.drawing.color.colorsFor(\"System\")[\"selectedControlColor\"]`).",
          ""
        ],
        "name" : "canvasClickColor",
        "notes" : [
          " * This method will generate an error if the touchbar item was not created with the [hs._asm.undocumented.touchbar.item.newCanvas](#newCanvas) constructor.",
          " * To specify that no background color should be displayed when the canvas touchbar item is in an active state, specify a color with an alpha value of 0, e.g. `{ alpha = 0 }`."
        ],
        "signature" : "hs._asm.undocumented.touchbar.item:canvasClickColor([color]) -> touchbarItemObject | current value",
        "type" : "Method",
        "returns" : [
          " * if an argument is provided, returns the touchbarItem object; otherwise returns the current value",
          ""
        ],
        "def" : "hs._asm.undocumented.touchbar.item:canvasClickColor([color]) -> touchbarItemObject | current value",
        "desc" : "Get or set the background color displayed when a canvas touchbar item is currently being touched."
      },
      {
        "doc" : "Get or set the width of a canvas touchbar item in the touchbar.\n\nParameters:\n * `width` - an optional number specifying the width of the canvas touchbar item in the touchbar.\n\nReturns:\n * if an argument is provided, returns the touchbarItem object; otherwise returns the current value\n\nNotes:\n * This method will generate an error if the touchbar item was not created with the [hs._asm.undocumented.touchbar.item.newCanvas](#newCanvas) constructor.",
        "stripped_doc" : [
          "Get or set the width of a canvas touchbar item in the touchbar.",
          ""
        ],
        "parameters" : [
          " * `width` - an optional number specifying the width of the canvas touchbar item in the touchbar.",
          ""
        ],
        "name" : "canvasWidth",
        "notes" : [
          " * This method will generate an error if the touchbar item was not created with the [hs._asm.undocumented.touchbar.item.newCanvas](#newCanvas) constructor."
        ],
        "signature" : "hs._asm.undocumented.touchbar.item:canvasWidth([width]) -> touchbarItemObject | current value",
        "type" : "Method",
        "returns" : [
          " * if an argument is provided, returns the touchbarItem object; otherwise returns the current value",
          ""
        ],
        "def" : "hs._asm.undocumented.touchbar.item:canvasWidth([width]) -> touchbarItemObject | current value",
        "desc" : "Get or set the width of a canvas touchbar item in the touchbar."
      },
      {
        "doc" : "Get or set the label displayed for the item when the customization panel is being displayed for the touch bar.\n\nParameters:\n * `label` - an optional string, or explicit nil to reset to an empty string, specifying the label to be displayed with the item when the customization panel is being displayed for the touch bar.  Defaults to an empty string.\n\nReturns:\n * if an argument is provided, returns the touchbarItem object; otherwise returns the current value",
        "stripped_doc" : [
          "Get or set the label displayed for the item when the customization panel is being displayed for the touch bar.",
          ""
        ],
        "parameters" : [
          " * `label` - an optional string, or explicit nil to reset to an empty string, specifying the label to be displayed with the item when the customization panel is being displayed for the touch bar.  Defaults to an empty string.",
          ""
        ],
        "name" : "customizationLabel",
        "notes" : [

        ],
        "signature" : "hs._asm.undocumented.touchbar.item:customizationLabel([label]) -> touchbarItemObject | current value",
        "type" : "Method",
        "returns" : [
          " * if an argument is provided, returns the touchbarItem object; otherwise returns the current value"
        ],
        "def" : "hs._asm.undocumented.touchbar.item:customizationLabel([label]) -> touchbarItemObject | current value",
        "desc" : "Get or set the label displayed for the item when the customization panel is being displayed for the touch bar."
      },
      {
        "doc" : "Get or set whether the touchbar item is enabled (accepting touches) or disabled.\n\nParameters:\n * `state` - an optional boolean, default true, specifying whether or not the touchbar item is currently enabled.\n\nReturns:\n * if an argument is provided, returns the touchbarItem object; otherwise returns the current value\n\nNotes:\n * This method will generate an error if the touchbar item was not created with the [hs._asm.undocumented.touchbar.item.newButton](#newButton) or [hs._asm.undocumented.touchbar.item.newCanvas](#newCanvas) constructors.",
        "stripped_doc" : [
          "Get or set whether the touchbar item is enabled (accepting touches) or disabled.",
          ""
        ],
        "parameters" : [
          " * `state` - an optional boolean, default true, specifying whether or not the touchbar item is currently enabled.",
          ""
        ],
        "name" : "enabled",
        "notes" : [
          " * This method will generate an error if the touchbar item was not created with the [hs._asm.undocumented.touchbar.item.newButton](#newButton) or [hs._asm.undocumented.touchbar.item.newCanvas](#newCanvas) constructors."
        ],
        "signature" : "hs._asm.undocumented.touchbar.item:enabled([state]) -> touchbarItemObject | current value",
        "type" : "Method",
        "returns" : [
          " * if an argument is provided, returns the touchbarItem object; otherwise returns the current value",
          ""
        ],
        "def" : "hs._asm.undocumented.touchbar.item:enabled([state]) -> touchbarItemObject | current value",
        "desc" : "Get or set whether the touchbar item is enabled (accepting touches) or disabled."
      },
      {
        "doc" : "Get or set the touchbar item objects which belong to this group touchbar item.\n\nParameters:\n * `itemsTable` - an optional table as an array of touchbar item objects to display when this group touchbar item is present in the touchbar.\n\nReturns:\n * if an argument is provided, returns the touchbarItem object; otherwise returns the current value\n\nNotes:\n * This method will generate an error if the touchbar item was not created with the [hs._asm.undocumented.touchbar.item.newGroup](#newGroup) constructor.\n * The group touchbar item's callback, if set, is never invoked; instead the callback for the items within the group item is invoked when the item is touched.\n * This is a convenience method which creates an `hs._asm.undocumented.touchbar.bar` object and uses [hs._asm.undocumented.touchbar.item:groupTouchbar](#groupTouchbar) to assign the items to the group item.",
        "stripped_doc" : [
          "Get or set the touchbar item objects which belong to this group touchbar item.",
          ""
        ],
        "parameters" : [
          " * `itemsTable` - an optional table as an array of touchbar item objects to display when this group touchbar item is present in the touchbar.",
          ""
        ],
        "name" : "groupItems",
        "notes" : [
          " * This method will generate an error if the touchbar item was not created with the [hs._asm.undocumented.touchbar.item.newGroup](#newGroup) constructor.",
          " * The group touchbar item's callback, if set, is never invoked; instead the callback for the items within the group item is invoked when the item is touched.",
          " * This is a convenience method which creates an `hs._asm.undocumented.touchbar.bar` object and uses [hs._asm.undocumented.touchbar.item:groupTouchbar](#groupTouchbar) to assign the items to the group item."
        ],
        "signature" : "hs._asm.undocumented.touchbar.item:groupItems([itemsTable]) -> touchbarItemObject | current value",
        "type" : "Method",
        "returns" : [
          " * if an argument is provided, returns the touchbarItem object; otherwise returns the current value",
          ""
        ],
        "def" : "hs._asm.undocumented.touchbar.item:groupItems([itemsTable]) -> touchbarItemObject | current value",
        "desc" : "Get or set the touchbar item objects which belong to this group touchbar item."
      },
      {
        "doc" : "Get or set the bar object which contains the touchbar items that belong to the group touchbar item.\n\nParameters:\n * `touchbar` - an optional `hs._asm.undocumented.touchbar.bar` object containing the touchbar items to display when this group touchbar item is present in the touchbar.\n\nReturns:\n * if an argument is provided, returns the touchbarItem object; otherwise returns the current value\n\nNotes:\n * This method will generate an error if the touchbar item was not created with the [hs._asm.undocumented.touchbar.item.newGroup](#newGroup) constructor.\n * The group touchbar item's callback, if set, is never invoked; instead the callback for the items within the group item is invoked when the item is touched.\n * See also [hs._asm.undocumented.touchbar.item:groupItems](#groupItems)",
        "stripped_doc" : [
          "Get or set the bar object which contains the touchbar items that belong to the group touchbar item.",
          ""
        ],
        "parameters" : [
          " * `touchbar` - an optional `hs._asm.undocumented.touchbar.bar` object containing the touchbar items to display when this group touchbar item is present in the touchbar.",
          ""
        ],
        "name" : "groupTouchbar",
        "notes" : [
          " * This method will generate an error if the touchbar item was not created with the [hs._asm.undocumented.touchbar.item.newGroup](#newGroup) constructor.",
          " * The group touchbar item's callback, if set, is never invoked; instead the callback for the items within the group item is invoked when the item is touched.",
          " * See also [hs._asm.undocumented.touchbar.item:groupItems](#groupItems)"
        ],
        "signature" : "hs._asm.undocumented.touchbar.item:groupTouchbar([touchbar]) -> touchbarItemObject | current value",
        "type" : "Method",
        "returns" : [
          " * if an argument is provided, returns the touchbarItem object; otherwise returns the current value",
          ""
        ],
        "def" : "hs._asm.undocumented.touchbar.item:groupTouchbar([touchbar]) -> touchbarItemObject | current value",
        "desc" : "Get or set the bar object which contains the touchbar items that belong to the group touchbar item."
      },
      {
        "doc" : "Returns the identifier for the touchbarItem object\n\nParameters:\n * None\n\nReturns:\n * the identifier for the item as a string",
        "stripped_doc" : [
          "Returns the identifier for the touchbarItem object",
          ""
        ],
        "parameters" : [
          " * None",
          ""
        ],
        "name" : "identifier",
        "notes" : [

        ],
        "signature" : "hs._asm.undocumented.touchbar.item:identifier() -> string",
        "type" : "Method",
        "returns" : [
          " * the identifier for the item as a string"
        ],
        "def" : "hs._asm.undocumented.touchbar.item:identifier() -> string",
        "desc" : "Returns the identifier for the touchbarItem object"
      },
      {
        "doc" : "Returns a boolean indicating whether or not the item is currently visible in the bar that it is assigned to.\n\nParameters:\n * None\n\nReturns:\n * a boolean specifying whether or not the item is currently visible in the bar that it is assigned to.\n\nNotes:\n * If the bar that the item is assigned to has been visible at some point in the past, and the item was visible at that time, this method will return true even if the bar is not currently visible. If you want to know if the item is visible in the touch bar display *right now*, you should use `reallyVisible = bar:isVisible() and item:isVisible()`",
        "stripped_doc" : [
          "Returns a boolean indicating whether or not the item is currently visible in the bar that it is assigned to.",
          ""
        ],
        "parameters" : [
          " * None",
          ""
        ],
        "name" : "isVisible",
        "notes" : [
          " * If the bar that the item is assigned to has been visible at some point in the past, and the item was visible at that time, this method will return true even if the bar is not currently visible. If you want to know if the item is visible in the touch bar display *right now*, you should use `reallyVisible = bar:isVisible() and item:isVisible()`"
        ],
        "signature" : "hs._asm.undocumented.touchbar.item:isVisible() -> boolean",
        "type" : "Method",
        "returns" : [
          " * a boolean specifying whether or not the item is currently visible in the bar that it is assigned to.",
          ""
        ],
        "def" : "hs._asm.undocumented.touchbar.item:isVisible() -> boolean",
        "desc" : "Returns a boolean indicating whether or not the item is currently visible in the bar that it is assigned to."
      },
      {
        "doc" : "Returns the type of the touchbar item as a string.\n\nParameters:\n * None\n\nReturns:\n * the type of the touchbar item as one of the following strings: \"buttonWithText\", \"buttonWithImage\", \"buttonWithImageAndText\", \"group\", \"slider\", or \"canvas\".\n\nNotes:\n * other types may be added in future updates.",
        "stripped_doc" : [
          "Returns the type of the touchbar item as a string.",
          ""
        ],
        "parameters" : [
          " * None",
          ""
        ],
        "name" : "itemType",
        "notes" : [
          " * other types may be added in future updates."
        ],
        "signature" : "hs._asm.undocumented.touchbar.item:itemType() -> string",
        "type" : "Method",
        "returns" : [
          " * the type of the touchbar item as one of the following strings: \"buttonWithText\", \"buttonWithImage\", \"buttonWithImageAndText\", \"group\", \"slider\", or \"canvas\".",
          ""
        ],
        "def" : "hs._asm.undocumented.touchbar.item:itemType() -> string",
        "desc" : "Returns the type of the touchbar item as a string."
      },
      {
        "doc" : "Presents a bar in the touch bar display modally and hides this item if it is present in the System Tray of the touch bar display.\n\nParameters:\n * `touchbar` - An `hs._asm.undocumented.touchbar.bar` object of the bar to display modally in the touch bar display.\n * `dismissButton` - an optional boolean, default true, specifying whether or not the system escape (or its current replacement) button should be replaced by a button to remove the modal bar from the touch bar display when pressed.\n\nReturns:\n * the touchbarItem object\n\nNotes:\n * If you specify `dismissButton` as false, then you must use `hs._asm.undocumented.touchbar.bar:minimizeModalBar` or `hs._asm.undocumented.touchbar.bar:dismissModalBar` to remove the modal bar from the touch bar display.\n   * Use `hs._asm.undocumented.touchbar.bar:minimizeModalBar` if you want the item to reappear in the System Tray (if it was present before displaying the bar).\n\n * If you do not have \"Touch Bar Shows\" set to \"App Controls With Control Strip\" set in the Keyboard System Preferences, the modal bar will only be displayed when the Hammerspoon application is the frontmost application.\n\n * This method is actually a wrapper to `hs._asm.undocumented.touchbar.bar:presentModalBar` provided for convenience.\n\n * This method uses undocumented functions and\/or framework methods and is not guaranteed to work with future updates to macOS. It has currently been tested with 10.12.6.",
        "stripped_doc" : [
          "Presents a bar in the touch bar display modally and hides this item if it is present in the System Tray of the touch bar display.",
          ""
        ],
        "parameters" : [
          " * `touchbar` - An `hs._asm.undocumented.touchbar.bar` object of the bar to display modally in the touch bar display.",
          " * `dismissButton` - an optional boolean, default true, specifying whether or not the system escape (or its current replacement) button should be replaced by a button to remove the modal bar from the touch bar display when pressed.",
          ""
        ],
        "name" : "presentModalBar",
        "notes" : [
          " * If you specify `dismissButton` as false, then you must use `hs._asm.undocumented.touchbar.bar:minimizeModalBar` or `hs._asm.undocumented.touchbar.bar:dismissModalBar` to remove the modal bar from the touch bar display.",
          "   * Use `hs._asm.undocumented.touchbar.bar:minimizeModalBar` if you want the item to reappear in the System Tray (if it was present before displaying the bar).",
          "",
          " * If you do not have \"Touch Bar Shows\" set to \"App Controls With Control Strip\" set in the Keyboard System Preferences, the modal bar will only be displayed when the Hammerspoon application is the frontmost application.",
          "",
          " * This method is actually a wrapper to `hs._asm.undocumented.touchbar.bar:presentModalBar` provided for convenience.",
          "",
          " * This method uses undocumented functions and\/or framework methods and is not guaranteed to work with future updates to macOS. It has currently been tested with 10.12.6."
        ],
        "signature" : "hs._asm.undocumented.touchbar.item:presentModalBar(touchbar, [dismissButton]) -> touchbarItemObject",
        "type" : "Method",
        "returns" : [
          " * the touchbarItem object",
          ""
        ],
        "def" : "hs._asm.undocumented.touchbar.item:presentModalBar(touchbar, [dismissButton]) -> touchbarItemObject",
        "desc" : "Presents a bar in the touch bar display modally and hides this item if it is present in the System Tray of the touch bar display."
      },
      {
        "doc" : "Get or set the maximum value for a slider touchbar item.\n\nParameters:\n * `value` - an optional number specifying the maximum value for a slider touchbar item. This represents the slider's value when the knob of the slider is all the way to the right. Defaults to 1.0.\n\nReturns:\n * if an argument is provided, returns the touchbarItem object; otherwise returns the current value\n\nNotes:\n * This method will generate an error if the touchbar item was not created with the [hs._asm.undocumented.touchbar.item.newSlider](#newSlider) constructor.",
        "stripped_doc" : [
          "Get or set the maximum value for a slider touchbar item.",
          ""
        ],
        "parameters" : [
          " * `value` - an optional number specifying the maximum value for a slider touchbar item. This represents the slider's value when the knob of the slider is all the way to the right. Defaults to 1.0.",
          ""
        ],
        "name" : "sliderMax",
        "notes" : [
          " * This method will generate an error if the touchbar item was not created with the [hs._asm.undocumented.touchbar.item.newSlider](#newSlider) constructor."
        ],
        "signature" : "hs._asm.undocumented.touchbar.item:sliderMax([value]) -> touchbarItemObject | current value",
        "type" : "Method",
        "returns" : [
          " * if an argument is provided, returns the touchbarItem object; otherwise returns the current value",
          ""
        ],
        "def" : "hs._asm.undocumented.touchbar.item:sliderMax([value]) -> touchbarItemObject | current value",
        "desc" : "Get or set the maximum value for a slider touchbar item."
      },
      {
        "doc" : "Get or set the image displayed at the right side of a slider touchbar item.\n\nParameters:\n * `image` - an optional image, or explicit nil to remove, specifying the image to be displayed at the right side of a slider touchbar item.  Defaults to nil.\n\nReturns:\n * if an argument is provided, returns the touchbarItem object; otherwise returns the current value\n\nNotes:\n * This method will generate an error if the touchbar item was not created with the [hs._asm.undocumented.touchbar.item.newSlider](#newSlider) constructor.\n * When this image is clicked on, the touchbar item's callback, if set, will receive the string \"maximum\" as it's second argument.",
        "stripped_doc" : [
          "Get or set the image displayed at the right side of a slider touchbar item.",
          ""
        ],
        "parameters" : [
          " * `image` - an optional image, or explicit nil to remove, specifying the image to be displayed at the right side of a slider touchbar item.  Defaults to nil.",
          ""
        ],
        "name" : "sliderMaxImage",
        "notes" : [
          " * This method will generate an error if the touchbar item was not created with the [hs._asm.undocumented.touchbar.item.newSlider](#newSlider) constructor.",
          " * When this image is clicked on, the touchbar item's callback, if set, will receive the string \"maximum\" as it's second argument."
        ],
        "signature" : "hs._asm.undocumented.touchbar.item:sliderMaxImage([image]) -> touchbarItemObject | current value",
        "type" : "Method",
        "returns" : [
          " * if an argument is provided, returns the touchbarItem object; otherwise returns the current value",
          ""
        ],
        "def" : "hs._asm.undocumented.touchbar.item:sliderMaxImage([image]) -> touchbarItemObject | current value",
        "desc" : "Get or set the image displayed at the right side of a slider touchbar item."
      },
      {
        "doc" : "Get or set the minimum value for a slider touchbar item.\n\nParameters:\n * `value` - an optional number specifying the minimum value for a slider touchbar item. This represents the slider's value when the knob of the slider is all the way to the left. Defaults to 0.0.\n\nReturns:\n * if an argument is provided, returns the touchbarItem object; otherwise returns the current value\n\nNotes:\n * This method will generate an error if the touchbar item was not created with the [hs._asm.undocumented.touchbar.item.newSlider](#newSlider) constructor.",
        "stripped_doc" : [
          "Get or set the minimum value for a slider touchbar item.",
          ""
        ],
        "parameters" : [
          " * `value` - an optional number specifying the minimum value for a slider touchbar item. This represents the slider's value when the knob of the slider is all the way to the left. Defaults to 0.0.",
          ""
        ],
        "name" : "sliderMin",
        "notes" : [
          " * This method will generate an error if the touchbar item was not created with the [hs._asm.undocumented.touchbar.item.newSlider](#newSlider) constructor."
        ],
        "signature" : "hs._asm.undocumented.touchbar.item:sliderMin([value]) -> touchbarItemObject | current value",
        "type" : "Method",
        "returns" : [
          " * if an argument is provided, returns the touchbarItem object; otherwise returns the current value",
          ""
        ],
        "def" : "hs._asm.undocumented.touchbar.item:sliderMin([value]) -> touchbarItemObject | current value",
        "desc" : "Get or set the minimum value for a slider touchbar item."
      },
      {
        "doc" : "Get or set the image displayed at the left side of a slider touchbar item.\n\nParameters:\n * `image` - an optional image, or explicit nil to remove, specifying the image to be displayed at the left side of a slider touchbar item.  Defaults to nil.\n\nReturns:\n * if an argument is provided, returns the touchbarItem object; otherwise returns the current value\n\nNotes:\n * This method will generate an error if the touchbar item was not created with the [hs._asm.undocumented.touchbar.item.newSlider](#newSlider) constructor.\n * When this image is clicked on, the touchbar item's callback, if set, will receive the string \"minimum\" as it's second argument.",
        "stripped_doc" : [
          "Get or set the image displayed at the left side of a slider touchbar item.",
          ""
        ],
        "parameters" : [
          " * `image` - an optional image, or explicit nil to remove, specifying the image to be displayed at the left side of a slider touchbar item.  Defaults to nil.",
          ""
        ],
        "name" : "sliderMinImage",
        "notes" : [
          " * This method will generate an error if the touchbar item was not created with the [hs._asm.undocumented.touchbar.item.newSlider](#newSlider) constructor.",
          " * When this image is clicked on, the touchbar item's callback, if set, will receive the string \"minimum\" as it's second argument."
        ],
        "signature" : "hs._asm.undocumented.touchbar.item:sliderMinImage([image]) -> touchbarItemObject | current value",
        "type" : "Method",
        "returns" : [
          " * if an argument is provided, returns the touchbarItem object; otherwise returns the current value",
          ""
        ],
        "def" : "hs._asm.undocumented.touchbar.item:sliderMinImage([image]) -> touchbarItemObject | current value",
        "desc" : "Get or set the image displayed at the left side of a slider touchbar item."
      },
      {
        "doc" : "Get or set the current value for a slider touchbar item.\n\nParameters:\n * `value` - an optional number specifying the value to set for the slider. This value will be automatically constrained to the current minimum and maximum as set by [hs._asm.undocumented.touchbar.item:sliderMin](#sliderMin) and [hs._asm.undocumented.touchbar.item:sliderMax](#sliderMax).\n\nReturns:\n * if an argument is provided, returns the touchbarItem object; otherwise returns the current value\n\nNotes:\n * This method will generate an error if the touchbar item was not created with the [hs._asm.undocumented.touchbar.item.newSlider](#newSlider) constructor.\n * The slider touchbar items callback, if set, will not be invoked if you use this method to change the slider's value.",
        "stripped_doc" : [
          "Get or set the current value for a slider touchbar item.",
          ""
        ],
        "parameters" : [
          " * `value` - an optional number specifying the value to set for the slider. This value will be automatically constrained to the current minimum and maximum as set by [hs._asm.undocumented.touchbar.item:sliderMin](#sliderMin) and [hs._asm.undocumented.touchbar.item:sliderMax](#sliderMax).",
          ""
        ],
        "name" : "sliderValue",
        "notes" : [
          " * This method will generate an error if the touchbar item was not created with the [hs._asm.undocumented.touchbar.item.newSlider](#newSlider) constructor.",
          " * The slider touchbar items callback, if set, will not be invoked if you use this method to change the slider's value."
        ],
        "signature" : "hs._asm.undocumented.touchbar.item:sliderValue([value]) -> touchbarItemObject | current value",
        "type" : "Method",
        "returns" : [
          " * if an argument is provided, returns the touchbarItem object; otherwise returns the current value",
          ""
        ],
        "def" : "hs._asm.undocumented.touchbar.item:sliderValue([value]) -> touchbarItemObject | current value",
        "desc" : "Get or set the current value for a slider touchbar item."
      },
      {
        "doc" : "Get or set the visibility callback function for the touchbar item object.\n\nParameters:\n * `fn` - an optional function, or explicit nil to remove, specifying the visibility callback for the touchbar item object.\n\nReturns:\n * if an argument is provided, returns the touchbarItem object; otherwise returns the current value\n\nNotes:\n * The callback function should expect two arguments, the touchbarItem itself and a boolean indicating the new visibility of the item.  It should return none.\n\n * See also the notes for [hs._asm.undocumented.touchbar.item:isVisible](#isVisible) and `hs._asm.undocumented.touchbar.bar.visibilityCallback`.",
        "stripped_doc" : [
          "Get or set the visibility callback function for the touchbar item object.",
          ""
        ],
        "parameters" : [
          " * `fn` - an optional function, or explicit nil to remove, specifying the visibility callback for the touchbar item object.",
          ""
        ],
        "name" : "visibilityCallback",
        "notes" : [
          " * The callback function should expect two arguments, the touchbarItem itself and a boolean indicating the new visibility of the item.  It should return none.",
          "",
          " * See also the notes for [hs._asm.undocumented.touchbar.item:isVisible](#isVisible) and `hs._asm.undocumented.touchbar.bar.visibilityCallback`."
        ],
        "signature" : "hs._asm.undocumented.touchbar.item:visibilityCallback([fn | nil]) -> touchbarItemObject | current value",
        "type" : "Method",
        "returns" : [
          " * if an argument is provided, returns the touchbarItem object; otherwise returns the current value",
          ""
        ],
        "def" : "hs._asm.undocumented.touchbar.item:visibilityCallback([fn | nil]) -> touchbarItemObject | current value",
        "desc" : "Get or set the visibility callback function for the touchbar item object."
      },
      {
        "doc" : "Get or set the visibility priority for the touchbar item.\n\nParameters:\n * `priority` - an optional number specifying the visibility priority for the item.\n\nReturns:\n * if an argument is provided, returns the touchbarItem object; otherwise returns the current value\n\nNotes:\n * If their are more items to be presented in the touch bar display than space permits, items with a lower visibility priority will be hidden first.\n * Some predefined visibility values are defined in [hs._asm.undocumented.touchbar.item.visibilityPriorities](#visibilityPriorities), though others are allowed. The default priority for an item object is `hs._asm.undocumented.touchbar.item.visibilityPriorities.normal`.",
        "stripped_doc" : [
          "Get or set the visibility priority for the touchbar item.",
          ""
        ],
        "parameters" : [
          " * `priority` - an optional number specifying the visibility priority for the item.",
          ""
        ],
        "name" : "visibilityPriority",
        "notes" : [
          " * If their are more items to be presented in the touch bar display than space permits, items with a lower visibility priority will be hidden first.",
          " * Some predefined visibility values are defined in [hs._asm.undocumented.touchbar.item.visibilityPriorities](#visibilityPriorities), though others are allowed. The default priority for an item object is `hs._asm.undocumented.touchbar.item.visibilityPriorities.normal`."
        ],
        "signature" : "hs._asm.undocumented.touchbar.item:visibilityPriority([priority]) -> touchbarItemObject | current value",
        "type" : "Method",
        "returns" : [
          " * if an argument is provided, returns the touchbarItem object; otherwise returns the current value",
          ""
        ],
        "def" : "hs._asm.undocumented.touchbar.item:visibilityPriority([priority]) -> touchbarItemObject | current value",
        "desc" : "Get or set the visibility priority for the touchbar item."
      }
    ],
    "Field" : [

    ],
    "name" : "hs._asm.undocumented.touchbar.item"
  },
  {
    "Constant" : [

    ],
    "submodules" : [

    ],
    "Function" : [
      {
        "doc" : "Creates a new touchbarObject representing a window which displays the Apple Touch Bar.\n\nParameters:\n * None\n\nReturns:\n * the touchbarObject or nil if one could not be created\n\nNotes:\n * The most common reason a touchbarObject cannot be created is if your macOS version is not new enough. Type the following into your Hammerspoon console to check: `require(\"hs._asm.undocumented.touchbar\").supported(true)`.",
        "stripped_doc" : [
          "Creates a new touchbarObject representing a window which displays the Apple Touch Bar.",
          ""
        ],
        "parameters" : [
          " * None",
          ""
        ],
        "name" : "new",
        "notes" : [
          " * The most common reason a touchbarObject cannot be created is if your macOS version is not new enough. Type the following into your Hammerspoon console to check: `require(\"hs._asm.undocumented.touchbar\").supported(true)`."
        ],
        "signature" : "hs._asm.undocumented.touchbar.virtual.new() -> touchbarObject | nil",
        "type" : "Function",
        "returns" : [
          " * the touchbarObject or nil if one could not be created",
          ""
        ],
        "def" : "hs._asm.undocumented.touchbar.virtual.new() -> touchbarObject | nil",
        "desc" : "Creates a new touchbarObject representing a window which displays the Apple Touch Bar."
      }
    ],
    "Variable" : [

    ],
    "stripped_doc" : [

    ],
    "type" : "Module",
    "desc" : "This submodule provides support for creating a virtual touchbar which can be displayed on the users screen.",
    "Deprecated" : [

    ],
    "Constructor" : [

    ],
    "doc" : "This submodule provides support for creating a virtual touchbar which can be displayed on the users screen.\n\nWhile this submodule will be primarily of interest to those without a touchbar enabled mac, it can also be used on machines which *do* have a touchbar and is in fact required if you wish to create an image of the current contents of the touchbar -- see [hs._asm.undocumented.touchbar:image](#image).\n\nThis module is very experimental and is still under development, so the exact functions and methods may be subject to change without notice.\n\nThis submodule is based in heavily on code from the following sources:\n* https:\/\/github.com\/bikkelbroeders\/TouchBarDemoApp - For the virtual touchbar itself (see [hs._asm.undocumented.touchbar.new](#new)). Unlike the code found at this link, we only support displaying the touch bar window on your computer screen and not on an attached iOS device.\n* https:\/\/github.com\/steventroughtonsmith\/TouchBarScreenshotter\/blob\/master\/TouchBarScreenshotter - for the code to create an image of the touchbar (see [hs._asm.undocumented.touchbar:image](#image))",
    "Method" : [
      {
        "doc" : "Toggle's the visibility of the touch bar window.\n\nParameters:\n * `duration` - an optional number, default 0.0, specifying the fade-in\/out time when changing the visibility of the touch bar window.\n\nReturns:\n * the touchbarObject",
        "stripped_doc" : [
          "Toggle's the visibility of the touch bar window.",
          ""
        ],
        "parameters" : [
          " * `duration` - an optional number, default 0.0, specifying the fade-in\/out time when changing the visibility of the touch bar window.",
          ""
        ],
        "name" : "toggle",
        "notes" : [

        ],
        "signature" : "hs._asm.undocumented.touchbar.virtual:toggle([duration]) -> touchbarObject",
        "type" : "Method",
        "returns" : [
          " * the touchbarObject"
        ],
        "def" : "hs._asm.undocumented.touchbar.virtual:toggle([duration]) -> touchbarObject",
        "desc" : "Toggle's the visibility of the touch bar window."
      },
      {
        "doc" : "Moves the touch bar window so that it is centered directly underneath the mouse pointer.\n\nParameters:\n * None\n\nReturns:\n * the touchbarObject\n\nNotes:\n * This method mimics the display location as set by the sample code this module is based on.  See https:\/\/github.com\/bikkelbroeders\/TouchBarDemoApp for more information.\n * The touch bar position will be adjusted so that it is fully visible on the screen even if this moves it left or right from the mouse's current position.",
        "stripped_doc" : [
          "Moves the touch bar window so that it is centered directly underneath the mouse pointer.",
          ""
        ],
        "parameters" : [
          " * None",
          ""
        ],
        "name" : "atMousePosition",
        "notes" : [
          " * This method mimics the display location as set by the sample code this module is based on.  See https:\/\/github.com\/bikkelbroeders\/TouchBarDemoApp for more information.",
          " * The touch bar position will be adjusted so that it is fully visible on the screen even if this moves it left or right from the mouse's current position."
        ],
        "signature" : "hs._asm.undocumented.touchbar.virtual:atMousePosition() -> touchbarObject",
        "type" : "Method",
        "returns" : [
          " * the touchbarObject",
          ""
        ],
        "def" : "hs._asm.undocumented.touchbar.virtual:atMousePosition() -> touchbarObject",
        "desc" : "Moves the touch bar window so that it is centered directly underneath the mouse pointer."
      },
      {
        "doc" : "Moves the touch bar window to the top or bottom center of the main screen.\n\nParameters:\n * `top` - an optional boolean, default false, specifying whether the touch bar should be centered at the top (true) of the screen or at the bottom (false).\n\nReturns:\n * the touchbarObject",
        "stripped_doc" : [
          "Moves the touch bar window to the top or bottom center of the main screen.",
          ""
        ],
        "parameters" : [
          " * `top` - an optional boolean, default false, specifying whether the touch bar should be centered at the top (true) of the screen or at the bottom (false).",
          ""
        ],
        "name" : "centered",
        "notes" : [

        ],
        "signature" : "hs._asm.undocumented.touchbar.virtual:centered([top]) -> touchbarObject",
        "type" : "Method",
        "returns" : [
          " * the touchbarObject"
        ],
        "def" : "hs._asm.undocumented.touchbar.virtual:centered([top]) -> touchbarObject",
        "desc" : "Moves the touch bar window to the top or bottom center of the main screen."
      },
      {
        "doc" : "Display the touch bar window with an optional fade-in delay.\n\nParameters:\n * `duration` - an optional number, default 0.0, specifying the fade-in time for the touch bar window.\n\nReturns:\n * the touchbarObject\n\nNotes:\n * This method does nothing if the window is already visible.",
        "stripped_doc" : [
          "Display the touch bar window with an optional fade-in delay.",
          ""
        ],
        "parameters" : [
          " * `duration` - an optional number, default 0.0, specifying the fade-in time for the touch bar window.",
          ""
        ],
        "name" : "show",
        "notes" : [
          " * This method does nothing if the window is already visible."
        ],
        "signature" : "hs._asm.undocumented.touchbar.virtual:show([duration]) -> touchbarObject",
        "type" : "Method",
        "returns" : [
          " * the touchbarObject",
          ""
        ],
        "def" : "hs._asm.undocumented.touchbar.virtual:show([duration]) -> touchbarObject",
        "desc" : "Display the touch bar window with an optional fade-in delay."
      },
      {
        "doc" : "Enable or disable updates to the virtual touchbar.\n\nParameters:\n * `state` - a boolean specifying whether or not the virtual touchbar window should be updated to reflect the current contents of the touchbar.\n\nReturns:\n * the touchbarObject\n\nNotes:\n * This method is invoked automatically with `true` when [hs._asm.undocumented.touchbar.virtual:show](#show) is invoked and with `false` when [hs._asm.undocumented.touchbar.virtual:hide](#hide) is invoked.\n * In order for [hs._asm.undocumented.touchbar.virtual:image](#image) to be able to capture a snapshot of the touchbar, the virtual touchbar must be currently receiving updates; this method will allow you to enable the updates even if the virtual touchbar is not currently visible on the screen (for example, if you have a physical touchbar on your laptop and do not wish to clutter the display with a duplicate of what you already posses).",
        "stripped_doc" : [
          "Enable or disable updates to the virtual touchbar.",
          ""
        ],
        "parameters" : [
          " * `state` - a boolean specifying whether or not the virtual touchbar window should be updated to reflect the current contents of the touchbar.",
          ""
        ],
        "name" : "streaming",
        "notes" : [
          " * This method is invoked automatically with `true` when [hs._asm.undocumented.touchbar.virtual:show](#show) is invoked and with `false` when [hs._asm.undocumented.touchbar.virtual:hide](#hide) is invoked.",
          " * In order for [hs._asm.undocumented.touchbar.virtual:image](#image) to be able to capture a snapshot of the touchbar, the virtual touchbar must be currently receiving updates; this method will allow you to enable the updates even if the virtual touchbar is not currently visible on the screen (for example, if you have a physical touchbar on your laptop and do not wish to clutter the display with a duplicate of what you already posses)."
        ],
        "signature" : "hs._asm.undocumented.touchbar.virtual:streaming(state) -> touchbarObject",
        "type" : "Method",
        "returns" : [
          " * the touchbarObject",
          ""
        ],
        "def" : "hs._asm.undocumented.touchbar.virtual:streaming(state) -> touchbarObject",
        "desc" : "Enable or disable updates to the virtual touchbar."
      },
      {
        "doc" : "Display the touch bar window with an optional fade-out delay.\n\nParameters:\n * `duration` - an optional number, default 0.0, specifying the fade-out time for the touch bar window.\n\nReturns:\n * the touchbarObject\n\nNotes:\n * This method does nothing if the window is already hidden.\n * The value used in the sample code referenced in the module header is 0.1.",
        "stripped_doc" : [
          "Display the touch bar window with an optional fade-out delay.",
          ""
        ],
        "parameters" : [
          " * `duration` - an optional number, default 0.0, specifying the fade-out time for the touch bar window.",
          ""
        ],
        "name" : "hide",
        "notes" : [
          " * This method does nothing if the window is already hidden.",
          " * The value used in the sample code referenced in the module header is 0.1."
        ],
        "signature" : "hs._asm.undocumented.touchbar.virtual:hide([duration]) -> touchbarObject",
        "type" : "Method",
        "returns" : [
          " * the touchbarObject",
          ""
        ],
        "def" : "hs._asm.undocumented.touchbar.virtual:hide([duration]) -> touchbarObject",
        "desc" : "Display the touch bar window with an optional fade-out delay."
      },
      {
        "doc" : "Get or set the top-left of the touch bar window.\n\nParameters:\n * `point` - an optional table specifying where the top left of the touch bar window should be moved to.\n\nReturns:\n * if a value is provided, returns the touchbarObject; otherwise returns the current value.\n\nNotes:\n * A point table is a table with at least `x` and `y` key-value pairs which specify the coordinates on the computer screen where the window should be moved to.  Hammerspoon considers the upper left corner of the primary screen to be { x = 0.0, y = 0.0 }.",
        "stripped_doc" : [
          "Get or set the top-left of the touch bar window.",
          ""
        ],
        "parameters" : [
          " * `point` - an optional table specifying where the top left of the touch bar window should be moved to.",
          ""
        ],
        "name" : "topLeft",
        "notes" : [
          " * A point table is a table with at least `x` and `y` key-value pairs which specify the coordinates on the computer screen where the window should be moved to.  Hammerspoon considers the upper left corner of the primary screen to be { x = 0.0, y = 0.0 }."
        ],
        "signature" : "hs._asm.undocumented.touchbar.virtual:topLeft([point]) -> table | touchbarObject",
        "type" : "Method",
        "returns" : [
          " * if a value is provided, returns the touchbarObject; otherwise returns the current value.",
          ""
        ],
        "def" : "hs._asm.undocumented.touchbar.virtual:topLeft([point]) -> table | touchbarObject",
        "desc" : "Get or set the top-left of the touch bar window."
      },
      {
        "doc" : "Gets the frame of the touch bar window\n\nParameters:\n * None\n\nReturns:\n * a frame table with key-value pairs specifying the top left corner of the touch bar window and its width and height.\n\nNotes:\n * A frame table is a table with at least `x`, `y`, `h` and `w` key-value pairs which specify the coordinates on the computer screen of the window and its width (w) and height(h).\n * This allows you to get the frame so that you can include its height and width in calculations - it does not allow you to change the size of the touch bar window itself.",
        "stripped_doc" : [
          "Gets the frame of the touch bar window",
          ""
        ],
        "parameters" : [
          " * None",
          ""
        ],
        "name" : "getFrame",
        "notes" : [
          " * A frame table is a table with at least `x`, `y`, `h` and `w` key-value pairs which specify the coordinates on the computer screen of the window and its width (w) and height(h).",
          " * This allows you to get the frame so that you can include its height and width in calculations - it does not allow you to change the size of the touch bar window itself."
        ],
        "signature" : "hs._asm.undocumented.touchbar.virtual:getFrame() -> table",
        "type" : "Method",
        "returns" : [
          " * a frame table with key-value pairs specifying the top left corner of the touch bar window and its width and height.",
          ""
        ],
        "def" : "hs._asm.undocumented.touchbar.virtual:getFrame() -> table",
        "desc" : "Gets the frame of the touch bar window"
      },
      {
        "doc" : "Returns a boolean indicating whether or not the touch bar window is current visible.\n\nParameters:\n * None\n\nReturns:\n * a boolean specifying whether the touch bar window is visible (true) or not (false).",
        "stripped_doc" : [
          "Returns a boolean indicating whether or not the touch bar window is current visible.",
          ""
        ],
        "parameters" : [
          " * None",
          ""
        ],
        "name" : "isVisible",
        "notes" : [

        ],
        "signature" : "hs._asm.undocumented.touchbar.virtual:isVisible() -> boolean",
        "type" : "Method",
        "returns" : [
          " * a boolean specifying whether the touch bar window is visible (true) or not (false)."
        ],
        "def" : "hs._asm.undocumented.touchbar.virtual:isVisible() -> boolean",
        "desc" : "Returns a boolean indicating whether or not the touch bar window is current visible."
      },
      {
        "doc" : "Get or set the alpha value for the touch bar window when the mouse is not hovering over it.\n\nParameters:\n * alpha - an optional number between 0.0 and 1.0 inclusive specifying the alpha value for the touch bar window when the mouse is not over it.  Defaults to 0.5.\n\nReturns:\n * if a value is provided, returns the touchbarObject; otherwise returns the current value",
        "stripped_doc" : [
          "Get or set the alpha value for the touch bar window when the mouse is not hovering over it.",
          ""
        ],
        "parameters" : [
          " * alpha - an optional number between 0.0 and 1.0 inclusive specifying the alpha value for the touch bar window when the mouse is not over it.  Defaults to 0.5.",
          ""
        ],
        "name" : "inactiveAlpha",
        "notes" : [

        ],
        "signature" : "hs._asm.undocumented.touchbar.virtual:inactiveAlpha([alpha]) -> number | touchbarObject",
        "type" : "Method",
        "returns" : [
          " * if a value is provided, returns the touchbarObject; otherwise returns the current value"
        ],
        "def" : "hs._asm.undocumented.touchbar.virtual:inactiveAlpha([alpha]) -> number | touchbarObject",
        "desc" : "Get or set the alpha value for the touch bar window when the mouse is not hovering over it."
      },
      {
        "doc" : "Get or set whether or not the touch bar window is movable by clicking on it and holding down the mouse button while moving the mouse.\n\nParameters:\n * `state` - an optional boolean which specifies whether the touch bar window is movable (true) or not (false).  Default false.\n\nReturns:\n * if an argument is provided, returns the touchbarObject; otherwise returns the current value.\n\nNotes:\n * While the touch bar is movable, actions which require moving the mouse while clicking on the touch bar are not accessible.\n * See also [hs._asm.undocumented.touchbar.virtual:acceptsMouseEvents](#acceptsMouseEvents).",
        "stripped_doc" : [
          "Get or set whether or not the touch bar window is movable by clicking on it and holding down the mouse button while moving the mouse.",
          ""
        ],
        "parameters" : [
          " * `state` - an optional boolean which specifies whether the touch bar window is movable (true) or not (false).  Default false.",
          ""
        ],
        "name" : "movable",
        "notes" : [
          " * While the touch bar is movable, actions which require moving the mouse while clicking on the touch bar are not accessible.",
          " * See also [hs._asm.undocumented.touchbar.virtual:acceptsMouseEvents](#acceptsMouseEvents)."
        ],
        "signature" : "hs._asm.undocumented.touchbar.virtual:movable([state]) -> boolean | touchbarObject",
        "type" : "Method",
        "returns" : [
          " * if an argument is provided, returns the touchbarObject; otherwise returns the current value.",
          ""
        ],
        "def" : "hs._asm.undocumented.touchbar.virtual:movable([state]) -> boolean | touchbarObject",
        "desc" : "Get or set whether or not the touch bar window is movable by clicking on it and holding down the mouse button while moving the mouse."
      },
      {
        "doc" : "Get or set whether or not the touch bar accepts mouse events.\n\nParameters:\n * `state` - an optional boolean which specifies whether the touch bar accepts mouse events (true) or not (false).  Default true.\n\nReturns:\n * if an argument is provided, returns the touchbarObject; otherwise returns the current value.\n\nNotes:\n * This method can be used to prevent mouse clicks in the touch bar from triggering the touch bar buttons.\n * This can be useful when [hs._asm.undocumented.touchbar.virtual:movable](#movable) is set to true to prevent accidentally triggering an action.",
        "stripped_doc" : [
          "Get or set whether or not the touch bar accepts mouse events.",
          ""
        ],
        "parameters" : [
          " * `state` - an optional boolean which specifies whether the touch bar accepts mouse events (true) or not (false).  Default true.",
          ""
        ],
        "name" : "acceptsMouseEvents",
        "notes" : [
          " * This method can be used to prevent mouse clicks in the touch bar from triggering the touch bar buttons.",
          " * This can be useful when [hs._asm.undocumented.touchbar.virtual:movable](#movable) is set to true to prevent accidentally triggering an action."
        ],
        "signature" : "hs._asm.undocumented.touchbar.virtual:acceptsMouseEvents([state]) -> boolean | touchbarObject",
        "type" : "Method",
        "returns" : [
          " * if an argument is provided, returns the touchbarObject; otherwise returns the current value.",
          ""
        ],
        "def" : "hs._asm.undocumented.touchbar.virtual:acceptsMouseEvents([state]) -> boolean | touchbarObject",
        "desc" : "Get or set whether or not the touch bar accepts mouse events."
      },
      {
        "doc" : "Get or set the background color for the touch bar window.\n\nParameters:\n * `color` - an optional color table as defined in `hs.drawing.color` specifying the background color for the touch bar window.  Defaults to black, i.e. `{ white = 0.0, alpha = 1.0 }`.\n\nReturns:\n * if an argument is provided, returns the touchbarObject; otherwise returns the current value.\n\nNotes:\n * The visual effect of this method is to change the border color around the touch bar -- the touch bar itself remains the color as defined by the application which is providing the current touch bar items for display.",
        "stripped_doc" : [
          "Get or set the background color for the touch bar window.",
          ""
        ],
        "parameters" : [
          " * `color` - an optional color table as defined in `hs.drawing.color` specifying the background color for the touch bar window.  Defaults to black, i.e. `{ white = 0.0, alpha = 1.0 }`.",
          ""
        ],
        "name" : "backgroundColor",
        "notes" : [
          " * The visual effect of this method is to change the border color around the touch bar -- the touch bar itself remains the color as defined by the application which is providing the current touch bar items for display."
        ],
        "signature" : "hs._asm.undocumented.touchbar.virtual:backgroundColor([color]) -> color | touchbarObject",
        "type" : "Method",
        "returns" : [
          " * if an argument is provided, returns the touchbarObject; otherwise returns the current value.",
          ""
        ],
        "def" : "hs._asm.undocumented.touchbar.virtual:backgroundColor([color]) -> color | touchbarObject",
        "desc" : "Get or set the background color for the touch bar window."
      },
      {
        "doc" : "Sets the callback function for the touch bar window.\n\nParameters:\n * `fn` - a function to set as the callback for the touch bar window, or nil to remove the existing callback function.\n\nReturns:\n * the touchbarObject\n\nNotes:\n * The function should expect 2 arguments and return none.  The arguments will be one of the following:\n\n   * obj, \"didEnter\" - indicates that the mouse pointer has entered the window containing the touch bar\n     * `obj`     - the touchbarObject the callback is for\n     * `message` - the message to the callback, in this case \"didEnter\"\n\n   * obj, \"didExit\" - indicates that the mouse pointer has exited the window containing the touch bar\n     * `obj`     - the touchbarObject the callback is for\n     * `message` - the message to the callback, in this case \"didEnter\"",
        "stripped_doc" : [
          "Sets the callback function for the touch bar window.",
          ""
        ],
        "parameters" : [
          " * `fn` - a function to set as the callback for the touch bar window, or nil to remove the existing callback function.",
          ""
        ],
        "name" : "setCallback",
        "notes" : [
          " * The function should expect 2 arguments and return none.  The arguments will be one of the following:",
          "",
          "   * obj, \"didEnter\" - indicates that the mouse pointer has entered the window containing the touch bar",
          "     * `obj`     - the touchbarObject the callback is for",
          "     * `message` - the message to the callback, in this case \"didEnter\"",
          "",
          "   * obj, \"didExit\" - indicates that the mouse pointer has exited the window containing the touch bar",
          "     * `obj`     - the touchbarObject the callback is for",
          "     * `message` - the message to the callback, in this case \"didEnter\""
        ],
        "signature" : "hs._asm.undocumented.touchbar.virtual:setCallback(fn | nil) -> touchbarObject",
        "type" : "Method",
        "returns" : [
          " * the touchbarObject",
          ""
        ],
        "def" : "hs._asm.undocumented.touchbar.virtual:setCallback(fn | nil) -> touchbarObject",
        "desc" : "Sets the callback function for the touch bar window."
      },
      {
        "doc" : "Returns an image of the current contents of the virtual touchbar, or nil if the virtual touchbar is not currently being updated.\n\nParameters:\n * None\n\nReturns:\n * an `hs.image` object of the current contents of the virtual touchbar, or nil if the virtual touchbar is not currently being updated.\n\nNotes:\n * By default, the virtual touchbar is only receiving upates when it is visible on the screen -- [hs._asm.undocumented.touchbar.virtual:show](#show). If you wish to take a snapshot of the virtual touchbar but do not want it to be visible on the screen, you must invoke [hs._asm.undocumented.touchbar.virtual:streaming(true)](#streaming) before using this method.\n   * Note that it may take a second or two after invoking [hs._asm.undocumented.touchbar.virtual:streaming(true)](#streaming) before the first image can be made, so you should check that the return value is not `nil` before using the image; you can use something like the following:\n\n         myTouchbar = require(\"hs._asm.undocumented.touchbar\").viritual.new():streaming(true)\n         hs.timer.waitUntil(function() return myTouchbar:image() end, function()\n            -- whatever you need now that images can be captured\n         end)\n\n   * Once streaming has been enabled and the first image is received, subsequent image requests will continue to succeed until streaming is stopped with [hs._asm.undocumented.touchbar.virtual:streaming(false)](#streaming) or [hs._asm.undocumented.touchbar.virtual:hide()](#hide).",
        "stripped_doc" : [
          "Returns an image of the current contents of the virtual touchbar, or nil if the virtual touchbar is not currently being updated.",
          ""
        ],
        "parameters" : [
          " * None",
          ""
        ],
        "name" : "image",
        "notes" : [
          " * By default, the virtual touchbar is only receiving upates when it is visible on the screen -- [hs._asm.undocumented.touchbar.virtual:show](#show). If you wish to take a snapshot of the virtual touchbar but do not want it to be visible on the screen, you must invoke [hs._asm.undocumented.touchbar.virtual:streaming(true)](#streaming) before using this method.",
          "   * Note that it may take a second or two after invoking [hs._asm.undocumented.touchbar.virtual:streaming(true)](#streaming) before the first image can be made, so you should check that the return value is not `nil` before using the image; you can use something like the following:",
          "",
          "         myTouchbar = require(\"hs._asm.undocumented.touchbar\").viritual.new():streaming(true)",
          "         hs.timer.waitUntil(function() return myTouchbar:image() end, function()",
          "            -- whatever you need now that images can be captured",
          "         end)",
          "",
          "   * Once streaming has been enabled and the first image is received, subsequent image requests will continue to succeed until streaming is stopped with [hs._asm.undocumented.touchbar.virtual:streaming(false)](#streaming) or [hs._asm.undocumented.touchbar.virtual:hide()](#hide)."
        ],
        "signature" : "hs._asm.undocumented.touchbar.virtual:image() -> hs.image Object | nil",
        "type" : "Method",
        "returns" : [
          " * an `hs.image` object of the current contents of the virtual touchbar, or nil if the virtual touchbar is not currently being updated.",
          ""
        ],
        "def" : "hs._asm.undocumented.touchbar.virtual:image() -> hs.image Object | nil",
        "desc" : "Returns an image of the current contents of the virtual touchbar, or nil if the virtual touchbar is not currently being updated."
      }
    ],
    "Command" : [

    ],
    "items" : [
      {
        "doc" : "Creates a new touchbarObject representing a window which displays the Apple Touch Bar.\n\nParameters:\n * None\n\nReturns:\n * the touchbarObject or nil if one could not be created\n\nNotes:\n * The most common reason a touchbarObject cannot be created is if your macOS version is not new enough. Type the following into your Hammerspoon console to check: `require(\"hs._asm.undocumented.touchbar\").supported(true)`.",
        "stripped_doc" : [
          "Creates a new touchbarObject representing a window which displays the Apple Touch Bar.",
          ""
        ],
        "parameters" : [
          " * None",
          ""
        ],
        "name" : "new",
        "notes" : [
          " * The most common reason a touchbarObject cannot be created is if your macOS version is not new enough. Type the following into your Hammerspoon console to check: `require(\"hs._asm.undocumented.touchbar\").supported(true)`."
        ],
        "signature" : "hs._asm.undocumented.touchbar.virtual.new() -> touchbarObject | nil",
        "type" : "Function",
        "returns" : [
          " * the touchbarObject or nil if one could not be created",
          ""
        ],
        "def" : "hs._asm.undocumented.touchbar.virtual.new() -> touchbarObject | nil",
        "desc" : "Creates a new touchbarObject representing a window which displays the Apple Touch Bar."
      },
      {
        "doc" : "Get or set whether or not the touch bar accepts mouse events.\n\nParameters:\n * `state` - an optional boolean which specifies whether the touch bar accepts mouse events (true) or not (false).  Default true.\n\nReturns:\n * if an argument is provided, returns the touchbarObject; otherwise returns the current value.\n\nNotes:\n * This method can be used to prevent mouse clicks in the touch bar from triggering the touch bar buttons.\n * This can be useful when [hs._asm.undocumented.touchbar.virtual:movable](#movable) is set to true to prevent accidentally triggering an action.",
        "stripped_doc" : [
          "Get or set whether or not the touch bar accepts mouse events.",
          ""
        ],
        "parameters" : [
          " * `state` - an optional boolean which specifies whether the touch bar accepts mouse events (true) or not (false).  Default true.",
          ""
        ],
        "name" : "acceptsMouseEvents",
        "notes" : [
          " * This method can be used to prevent mouse clicks in the touch bar from triggering the touch bar buttons.",
          " * This can be useful when [hs._asm.undocumented.touchbar.virtual:movable](#movable) is set to true to prevent accidentally triggering an action."
        ],
        "signature" : "hs._asm.undocumented.touchbar.virtual:acceptsMouseEvents([state]) -> boolean | touchbarObject",
        "type" : "Method",
        "returns" : [
          " * if an argument is provided, returns the touchbarObject; otherwise returns the current value.",
          ""
        ],
        "def" : "hs._asm.undocumented.touchbar.virtual:acceptsMouseEvents([state]) -> boolean | touchbarObject",
        "desc" : "Get or set whether or not the touch bar accepts mouse events."
      },
      {
        "doc" : "Moves the touch bar window so that it is centered directly underneath the mouse pointer.\n\nParameters:\n * None\n\nReturns:\n * the touchbarObject\n\nNotes:\n * This method mimics the display location as set by the sample code this module is based on.  See https:\/\/github.com\/bikkelbroeders\/TouchBarDemoApp for more information.\n * The touch bar position will be adjusted so that it is fully visible on the screen even if this moves it left or right from the mouse's current position.",
        "stripped_doc" : [
          "Moves the touch bar window so that it is centered directly underneath the mouse pointer.",
          ""
        ],
        "parameters" : [
          " * None",
          ""
        ],
        "name" : "atMousePosition",
        "notes" : [
          " * This method mimics the display location as set by the sample code this module is based on.  See https:\/\/github.com\/bikkelbroeders\/TouchBarDemoApp for more information.",
          " * The touch bar position will be adjusted so that it is fully visible on the screen even if this moves it left or right from the mouse's current position."
        ],
        "signature" : "hs._asm.undocumented.touchbar.virtual:atMousePosition() -> touchbarObject",
        "type" : "Method",
        "returns" : [
          " * the touchbarObject",
          ""
        ],
        "def" : "hs._asm.undocumented.touchbar.virtual:atMousePosition() -> touchbarObject",
        "desc" : "Moves the touch bar window so that it is centered directly underneath the mouse pointer."
      },
      {
        "doc" : "Get or set the background color for the touch bar window.\n\nParameters:\n * `color` - an optional color table as defined in `hs.drawing.color` specifying the background color for the touch bar window.  Defaults to black, i.e. `{ white = 0.0, alpha = 1.0 }`.\n\nReturns:\n * if an argument is provided, returns the touchbarObject; otherwise returns the current value.\n\nNotes:\n * The visual effect of this method is to change the border color around the touch bar -- the touch bar itself remains the color as defined by the application which is providing the current touch bar items for display.",
        "stripped_doc" : [
          "Get or set the background color for the touch bar window.",
          ""
        ],
        "parameters" : [
          " * `color` - an optional color table as defined in `hs.drawing.color` specifying the background color for the touch bar window.  Defaults to black, i.e. `{ white = 0.0, alpha = 1.0 }`.",
          ""
        ],
        "name" : "backgroundColor",
        "notes" : [
          " * The visual effect of this method is to change the border color around the touch bar -- the touch bar itself remains the color as defined by the application which is providing the current touch bar items for display."
        ],
        "signature" : "hs._asm.undocumented.touchbar.virtual:backgroundColor([color]) -> color | touchbarObject",
        "type" : "Method",
        "returns" : [
          " * if an argument is provided, returns the touchbarObject; otherwise returns the current value.",
          ""
        ],
        "def" : "hs._asm.undocumented.touchbar.virtual:backgroundColor([color]) -> color | touchbarObject",
        "desc" : "Get or set the background color for the touch bar window."
      },
      {
        "doc" : "Moves the touch bar window to the top or bottom center of the main screen.\n\nParameters:\n * `top` - an optional boolean, default false, specifying whether the touch bar should be centered at the top (true) of the screen or at the bottom (false).\n\nReturns:\n * the touchbarObject",
        "stripped_doc" : [
          "Moves the touch bar window to the top or bottom center of the main screen.",
          ""
        ],
        "parameters" : [
          " * `top` - an optional boolean, default false, specifying whether the touch bar should be centered at the top (true) of the screen or at the bottom (false).",
          ""
        ],
        "name" : "centered",
        "notes" : [

        ],
        "signature" : "hs._asm.undocumented.touchbar.virtual:centered([top]) -> touchbarObject",
        "type" : "Method",
        "returns" : [
          " * the touchbarObject"
        ],
        "def" : "hs._asm.undocumented.touchbar.virtual:centered([top]) -> touchbarObject",
        "desc" : "Moves the touch bar window to the top or bottom center of the main screen."
      },
      {
        "doc" : "Gets the frame of the touch bar window\n\nParameters:\n * None\n\nReturns:\n * a frame table with key-value pairs specifying the top left corner of the touch bar window and its width and height.\n\nNotes:\n * A frame table is a table with at least `x`, `y`, `h` and `w` key-value pairs which specify the coordinates on the computer screen of the window and its width (w) and height(h).\n * This allows you to get the frame so that you can include its height and width in calculations - it does not allow you to change the size of the touch bar window itself.",
        "stripped_doc" : [
          "Gets the frame of the touch bar window",
          ""
        ],
        "parameters" : [
          " * None",
          ""
        ],
        "name" : "getFrame",
        "notes" : [
          " * A frame table is a table with at least `x`, `y`, `h` and `w` key-value pairs which specify the coordinates on the computer screen of the window and its width (w) and height(h).",
          " * This allows you to get the frame so that you can include its height and width in calculations - it does not allow you to change the size of the touch bar window itself."
        ],
        "signature" : "hs._asm.undocumented.touchbar.virtual:getFrame() -> table",
        "type" : "Method",
        "returns" : [
          " * a frame table with key-value pairs specifying the top left corner of the touch bar window and its width and height.",
          ""
        ],
        "def" : "hs._asm.undocumented.touchbar.virtual:getFrame() -> table",
        "desc" : "Gets the frame of the touch bar window"
      },
      {
        "doc" : "Display the touch bar window with an optional fade-out delay.\n\nParameters:\n * `duration` - an optional number, default 0.0, specifying the fade-out time for the touch bar window.\n\nReturns:\n * the touchbarObject\n\nNotes:\n * This method does nothing if the window is already hidden.\n * The value used in the sample code referenced in the module header is 0.1.",
        "stripped_doc" : [
          "Display the touch bar window with an optional fade-out delay.",
          ""
        ],
        "parameters" : [
          " * `duration` - an optional number, default 0.0, specifying the fade-out time for the touch bar window.",
          ""
        ],
        "name" : "hide",
        "notes" : [
          " * This method does nothing if the window is already hidden.",
          " * The value used in the sample code referenced in the module header is 0.1."
        ],
        "signature" : "hs._asm.undocumented.touchbar.virtual:hide([duration]) -> touchbarObject",
        "type" : "Method",
        "returns" : [
          " * the touchbarObject",
          ""
        ],
        "def" : "hs._asm.undocumented.touchbar.virtual:hide([duration]) -> touchbarObject",
        "desc" : "Display the touch bar window with an optional fade-out delay."
      },
      {
        "doc" : "Returns an image of the current contents of the virtual touchbar, or nil if the virtual touchbar is not currently being updated.\n\nParameters:\n * None\n\nReturns:\n * an `hs.image` object of the current contents of the virtual touchbar, or nil if the virtual touchbar is not currently being updated.\n\nNotes:\n * By default, the virtual touchbar is only receiving upates when it is visible on the screen -- [hs._asm.undocumented.touchbar.virtual:show](#show). If you wish to take a snapshot of the virtual touchbar but do not want it to be visible on the screen, you must invoke [hs._asm.undocumented.touchbar.virtual:streaming(true)](#streaming) before using this method.\n   * Note that it may take a second or two after invoking [hs._asm.undocumented.touchbar.virtual:streaming(true)](#streaming) before the first image can be made, so you should check that the return value is not `nil` before using the image; you can use something like the following:\n\n         myTouchbar = require(\"hs._asm.undocumented.touchbar\").viritual.new():streaming(true)\n         hs.timer.waitUntil(function() return myTouchbar:image() end, function()\n            -- whatever you need now that images can be captured\n         end)\n\n   * Once streaming has been enabled and the first image is received, subsequent image requests will continue to succeed until streaming is stopped with [hs._asm.undocumented.touchbar.virtual:streaming(false)](#streaming) or [hs._asm.undocumented.touchbar.virtual:hide()](#hide).",
        "stripped_doc" : [
          "Returns an image of the current contents of the virtual touchbar, or nil if the virtual touchbar is not currently being updated.",
          ""
        ],
        "parameters" : [
          " * None",
          ""
        ],
        "name" : "image",
        "notes" : [
          " * By default, the virtual touchbar is only receiving upates when it is visible on the screen -- [hs._asm.undocumented.touchbar.virtual:show](#show). If you wish to take a snapshot of the virtual touchbar but do not want it to be visible on the screen, you must invoke [hs._asm.undocumented.touchbar.virtual:streaming(true)](#streaming) before using this method.",
          "   * Note that it may take a second or two after invoking [hs._asm.undocumented.touchbar.virtual:streaming(true)](#streaming) before the first image can be made, so you should check that the return value is not `nil` before using the image; you can use something like the following:",
          "",
          "         myTouchbar = require(\"hs._asm.undocumented.touchbar\").viritual.new():streaming(true)",
          "         hs.timer.waitUntil(function() return myTouchbar:image() end, function()",
          "            -- whatever you need now that images can be captured",
          "         end)",
          "",
          "   * Once streaming has been enabled and the first image is received, subsequent image requests will continue to succeed until streaming is stopped with [hs._asm.undocumented.touchbar.virtual:streaming(false)](#streaming) or [hs._asm.undocumented.touchbar.virtual:hide()](#hide)."
        ],
        "signature" : "hs._asm.undocumented.touchbar.virtual:image() -> hs.image Object | nil",
        "type" : "Method",
        "returns" : [
          " * an `hs.image` object of the current contents of the virtual touchbar, or nil if the virtual touchbar is not currently being updated.",
          ""
        ],
        "def" : "hs._asm.undocumented.touchbar.virtual:image() -> hs.image Object | nil",
        "desc" : "Returns an image of the current contents of the virtual touchbar, or nil if the virtual touchbar is not currently being updated."
      },
      {
        "doc" : "Get or set the alpha value for the touch bar window when the mouse is not hovering over it.\n\nParameters:\n * alpha - an optional number between 0.0 and 1.0 inclusive specifying the alpha value for the touch bar window when the mouse is not over it.  Defaults to 0.5.\n\nReturns:\n * if a value is provided, returns the touchbarObject; otherwise returns the current value",
        "stripped_doc" : [
          "Get or set the alpha value for the touch bar window when the mouse is not hovering over it.",
          ""
        ],
        "parameters" : [
          " * alpha - an optional number between 0.0 and 1.0 inclusive specifying the alpha value for the touch bar window when the mouse is not over it.  Defaults to 0.5.",
          ""
        ],
        "name" : "inactiveAlpha",
        "notes" : [

        ],
        "signature" : "hs._asm.undocumented.touchbar.virtual:inactiveAlpha([alpha]) -> number | touchbarObject",
        "type" : "Method",
        "returns" : [
          " * if a value is provided, returns the touchbarObject; otherwise returns the current value"
        ],
        "def" : "hs._asm.undocumented.touchbar.virtual:inactiveAlpha([alpha]) -> number | touchbarObject",
        "desc" : "Get or set the alpha value for the touch bar window when the mouse is not hovering over it."
      },
      {
        "doc" : "Returns a boolean indicating whether or not the touch bar window is current visible.\n\nParameters:\n * None\n\nReturns:\n * a boolean specifying whether the touch bar window is visible (true) or not (false).",
        "stripped_doc" : [
          "Returns a boolean indicating whether or not the touch bar window is current visible.",
          ""
        ],
        "parameters" : [
          " * None",
          ""
        ],
        "name" : "isVisible",
        "notes" : [

        ],
        "signature" : "hs._asm.undocumented.touchbar.virtual:isVisible() -> boolean",
        "type" : "Method",
        "returns" : [
          " * a boolean specifying whether the touch bar window is visible (true) or not (false)."
        ],
        "def" : "hs._asm.undocumented.touchbar.virtual:isVisible() -> boolean",
        "desc" : "Returns a boolean indicating whether or not the touch bar window is current visible."
      },
      {
        "doc" : "Get or set whether or not the touch bar window is movable by clicking on it and holding down the mouse button while moving the mouse.\n\nParameters:\n * `state` - an optional boolean which specifies whether the touch bar window is movable (true) or not (false).  Default false.\n\nReturns:\n * if an argument is provided, returns the touchbarObject; otherwise returns the current value.\n\nNotes:\n * While the touch bar is movable, actions which require moving the mouse while clicking on the touch bar are not accessible.\n * See also [hs._asm.undocumented.touchbar.virtual:acceptsMouseEvents](#acceptsMouseEvents).",
        "stripped_doc" : [
          "Get or set whether or not the touch bar window is movable by clicking on it and holding down the mouse button while moving the mouse.",
          ""
        ],
        "parameters" : [
          " * `state` - an optional boolean which specifies whether the touch bar window is movable (true) or not (false).  Default false.",
          ""
        ],
        "name" : "movable",
        "notes" : [
          " * While the touch bar is movable, actions which require moving the mouse while clicking on the touch bar are not accessible.",
          " * See also [hs._asm.undocumented.touchbar.virtual:acceptsMouseEvents](#acceptsMouseEvents)."
        ],
        "signature" : "hs._asm.undocumented.touchbar.virtual:movable([state]) -> boolean | touchbarObject",
        "type" : "Method",
        "returns" : [
          " * if an argument is provided, returns the touchbarObject; otherwise returns the current value.",
          ""
        ],
        "def" : "hs._asm.undocumented.touchbar.virtual:movable([state]) -> boolean | touchbarObject",
        "desc" : "Get or set whether or not the touch bar window is movable by clicking on it and holding down the mouse button while moving the mouse."
      },
      {
        "doc" : "Sets the callback function for the touch bar window.\n\nParameters:\n * `fn` - a function to set as the callback for the touch bar window, or nil to remove the existing callback function.\n\nReturns:\n * the touchbarObject\n\nNotes:\n * The function should expect 2 arguments and return none.  The arguments will be one of the following:\n\n   * obj, \"didEnter\" - indicates that the mouse pointer has entered the window containing the touch bar\n     * `obj`     - the touchbarObject the callback is for\n     * `message` - the message to the callback, in this case \"didEnter\"\n\n   * obj, \"didExit\" - indicates that the mouse pointer has exited the window containing the touch bar\n     * `obj`     - the touchbarObject the callback is for\n     * `message` - the message to the callback, in this case \"didEnter\"",
        "stripped_doc" : [
          "Sets the callback function for the touch bar window.",
          ""
        ],
        "parameters" : [
          " * `fn` - a function to set as the callback for the touch bar window, or nil to remove the existing callback function.",
          ""
        ],
        "name" : "setCallback",
        "notes" : [
          " * The function should expect 2 arguments and return none.  The arguments will be one of the following:",
          "",
          "   * obj, \"didEnter\" - indicates that the mouse pointer has entered the window containing the touch bar",
          "     * `obj`     - the touchbarObject the callback is for",
          "     * `message` - the message to the callback, in this case \"didEnter\"",
          "",
          "   * obj, \"didExit\" - indicates that the mouse pointer has exited the window containing the touch bar",
          "     * `obj`     - the touchbarObject the callback is for",
          "     * `message` - the message to the callback, in this case \"didEnter\""
        ],
        "signature" : "hs._asm.undocumented.touchbar.virtual:setCallback(fn | nil) -> touchbarObject",
        "type" : "Method",
        "returns" : [
          " * the touchbarObject",
          ""
        ],
        "def" : "hs._asm.undocumented.touchbar.virtual:setCallback(fn | nil) -> touchbarObject",
        "desc" : "Sets the callback function for the touch bar window."
      },
      {
        "doc" : "Display the touch bar window with an optional fade-in delay.\n\nParameters:\n * `duration` - an optional number, default 0.0, specifying the fade-in time for the touch bar window.\n\nReturns:\n * the touchbarObject\n\nNotes:\n * This method does nothing if the window is already visible.",
        "stripped_doc" : [
          "Display the touch bar window with an optional fade-in delay.",
          ""
        ],
        "parameters" : [
          " * `duration` - an optional number, default 0.0, specifying the fade-in time for the touch bar window.",
          ""
        ],
        "name" : "show",
        "notes" : [
          " * This method does nothing if the window is already visible."
        ],
        "signature" : "hs._asm.undocumented.touchbar.virtual:show([duration]) -> touchbarObject",
        "type" : "Method",
        "returns" : [
          " * the touchbarObject",
          ""
        ],
        "def" : "hs._asm.undocumented.touchbar.virtual:show([duration]) -> touchbarObject",
        "desc" : "Display the touch bar window with an optional fade-in delay."
      },
      {
        "doc" : "Enable or disable updates to the virtual touchbar.\n\nParameters:\n * `state` - a boolean specifying whether or not the virtual touchbar window should be updated to reflect the current contents of the touchbar.\n\nReturns:\n * the touchbarObject\n\nNotes:\n * This method is invoked automatically with `true` when [hs._asm.undocumented.touchbar.virtual:show](#show) is invoked and with `false` when [hs._asm.undocumented.touchbar.virtual:hide](#hide) is invoked.\n * In order for [hs._asm.undocumented.touchbar.virtual:image](#image) to be able to capture a snapshot of the touchbar, the virtual touchbar must be currently receiving updates; this method will allow you to enable the updates even if the virtual touchbar is not currently visible on the screen (for example, if you have a physical touchbar on your laptop and do not wish to clutter the display with a duplicate of what you already posses).",
        "stripped_doc" : [
          "Enable or disable updates to the virtual touchbar.",
          ""
        ],
        "parameters" : [
          " * `state` - a boolean specifying whether or not the virtual touchbar window should be updated to reflect the current contents of the touchbar.",
          ""
        ],
        "name" : "streaming",
        "notes" : [
          " * This method is invoked automatically with `true` when [hs._asm.undocumented.touchbar.virtual:show](#show) is invoked and with `false` when [hs._asm.undocumented.touchbar.virtual:hide](#hide) is invoked.",
          " * In order for [hs._asm.undocumented.touchbar.virtual:image](#image) to be able to capture a snapshot of the touchbar, the virtual touchbar must be currently receiving updates; this method will allow you to enable the updates even if the virtual touchbar is not currently visible on the screen (for example, if you have a physical touchbar on your laptop and do not wish to clutter the display with a duplicate of what you already posses)."
        ],
        "signature" : "hs._asm.undocumented.touchbar.virtual:streaming(state) -> touchbarObject",
        "type" : "Method",
        "returns" : [
          " * the touchbarObject",
          ""
        ],
        "def" : "hs._asm.undocumented.touchbar.virtual:streaming(state) -> touchbarObject",
        "desc" : "Enable or disable updates to the virtual touchbar."
      },
      {
        "doc" : "Toggle's the visibility of the touch bar window.\n\nParameters:\n * `duration` - an optional number, default 0.0, specifying the fade-in\/out time when changing the visibility of the touch bar window.\n\nReturns:\n * the touchbarObject",
        "stripped_doc" : [
          "Toggle's the visibility of the touch bar window.",
          ""
        ],
        "parameters" : [
          " * `duration` - an optional number, default 0.0, specifying the fade-in\/out time when changing the visibility of the touch bar window.",
          ""
        ],
        "name" : "toggle",
        "notes" : [

        ],
        "signature" : "hs._asm.undocumented.touchbar.virtual:toggle([duration]) -> touchbarObject",
        "type" : "Method",
        "returns" : [
          " * the touchbarObject"
        ],
        "def" : "hs._asm.undocumented.touchbar.virtual:toggle([duration]) -> touchbarObject",
        "desc" : "Toggle's the visibility of the touch bar window."
      },
      {
        "doc" : "Get or set the top-left of the touch bar window.\n\nParameters:\n * `point` - an optional table specifying where the top left of the touch bar window should be moved to.\n\nReturns:\n * if a value is provided, returns the touchbarObject; otherwise returns the current value.\n\nNotes:\n * A point table is a table with at least `x` and `y` key-value pairs which specify the coordinates on the computer screen where the window should be moved to.  Hammerspoon considers the upper left corner of the primary screen to be { x = 0.0, y = 0.0 }.",
        "stripped_doc" : [
          "Get or set the top-left of the touch bar window.",
          ""
        ],
        "parameters" : [
          " * `point` - an optional table specifying where the top left of the touch bar window should be moved to.",
          ""
        ],
        "name" : "topLeft",
        "notes" : [
          " * A point table is a table with at least `x` and `y` key-value pairs which specify the coordinates on the computer screen where the window should be moved to.  Hammerspoon considers the upper left corner of the primary screen to be { x = 0.0, y = 0.0 }."
        ],
        "signature" : "hs._asm.undocumented.touchbar.virtual:topLeft([point]) -> table | touchbarObject",
        "type" : "Method",
        "returns" : [
          " * if a value is provided, returns the touchbarObject; otherwise returns the current value.",
          ""
        ],
        "def" : "hs._asm.undocumented.touchbar.virtual:topLeft([point]) -> table | touchbarObject",
        "desc" : "Get or set the top-left of the touch bar window."
      }
    ],
    "Field" : [

    ],
    "name" : "hs._asm.undocumented.touchbar.virtual"
  }
]
